Workbook
Name AsOfDate: LEEME!$C$6
Name CostPerHour: LEEME!$C$8
Name HS_ARR: E3_Health_Score!$E$8:$E$145
Name HS_Cat: E3_Health_Score!$T$8:$T$145
Name HS_CSM: E3_Health_Score!$D$8:$D$145
Name HS_Days: E3_Health_Score!$N$8:$N$145
Name HS_ID: E3_Health_Score!$A$8:$A$145
Name HS_Name: E3_Health_Score!$B$8:$B$145
Name HS_Score: E3_Health_Score!$S$8:$S$145
Name HS_Segment: E3_Health_Score!$C$8:$C$145
Name HS_Tickets: E3_Health_Score!$L$8:$L$145
Name LastMonth: LEEME!$C$7

Sheet LEEME
A1: Práctica de Excel · Analyst, Customer Success Operations
A2: Versión: PRÁCTICA (llena las celdas amarillas)
B3: Escenario: eres analista de CS Ops en una empresa SaaS B2B. Liderazgo quiere (1) entender la salud de las cuentas para que los CSMs prioricen, (2) auditar los reportes actuales para decidir qué mantener, consolidar, automatizar o retirar, y (3) tener datos limpios y confiables para QBRs/EBRs, renovaciones y reportes contractuales. Todos los datos son ficticios.
B5: Parámetros (usados en todas las fórmulas)
B6: AsOfDate (fecha de corte) | C6: 46295 | D6: Nombre definido AsOfDate. Se usa en lugar de TODAY() para que los resultados sean reproducibles.
B7: LastMonth (último mes cerrado) | C7: =DATE(YEAR(AsOfDate),MONTH(AsOfDate),1) -> 46266 | D7: Nombre definido LastMonth = primer día del mes de AsOfDate.
B8: CostPerHour (USD) | C8: 35 | D8: Costo por hora de analista; se usa para estimar el costo de mantener un reporte.
B10: Cómo usar este libro
B11: 1. Cada hoja E# es un ejercicio. Lee el objetivo (fila 2), el contexto de negocio (fila 3) y la pista gris debajo de cada encabezado.
B12: 2. Escribe tus fórmulas en las celdas AMARILLAS. Las columnas ✓/✗ se validan solas contra la respuesta correcta (oculta). Copia/arrastra la fórmula de la primera fila hacia abajo.
B13: 3. Si te atoras, abre CS_Ops_Soluciones.xlsx (mismo set de datos) y compara tu fórmula.
B14: 4. Los datos están en las hojas grises como Tablas de Excel (tbl_Accounts, tbl_Usage, etc.). Úsalas con referencias estructuradas: tbl_Accounts[ARR_USD]. Revisa la hoja Diccionario.
B15: 5. Las verificaciones asumen los parámetros y pesos por defecto. Si los cambias para experimentar, algunas ✓ pasarán a ✗ (eso es normal).
B16: 6. Regenera el archivo con otra semilla (python generar_practica_excel.py --semilla 123) para practicar de nuevo con números diferentes.
B17: 7. Excel en español: los nombres de funciones se traducen solos al abrir el archivo y el separador puede ser ';' en vez de ','. Abajo a la derecha tienes la tabla de traducción.
B19: Ejercicios y progreso
B20: Hoja | C20: Habilidad clave | D20: Qué practicas / para qué sirve en el puesto | E20: ✓ | F20: Total | G20: Avance
B21: E1_Lookups | C21: Lookups | D21: VLOOKUP, INDEX/MATCH, XLOOKUP anidado, búsqueda aproximada (tiers), búsqueda inversa (último registro), IFERROR y TRIM. | E21: =COUNTIF('E1_Lookups'!$A$1:$BZ$400,"✓") -> 0 | F21: 120 | G21: =IFERROR(E21/F21,0) -> 0
B22: E2_Agregaciones | C22: SUMIFS/COUNTIFS | D22: Matrices ARR segmento×región, book of business por CSM, tickets por prioridad, NPS. Base de cualquier reporte. | E22: =COUNTIF('E2_Agregaciones'!$A$1:$BZ$400,"✓") -> 0 | F22: 101 | G22: =IFERROR(E22/F22,0) -> 0
B23: E3_Health_Score | C23: Health score | D23: Construir un health score ponderado (adopción, tendencia, soporte, NPS), categorías Green/Yellow/Red y riesgo de renovación. | E23: =COUNTIF('E3_Health_Score'!$A$1:$BZ$400,"✓") -> 0 | F23: 976 | G23: =IFERROR(E23/F23,0) -> 0
B24: E4_Auditoria_Reportes | C24: Auditoría de reportes | D24: Uso real de cada reporte, usuarios únicos, última consulta, costo por vista y recomendación (retirar / consolidar / automatizar / mantener). | E24: =COUNTIF('E4_Auditoria_Reportes'!$A$1:$BZ$400,"✓") -> 0 | F24: 272 | G24: =IFERROR(E24/F24,0) -> 0
B25: E5_Limpieza_Datos | C25: Calidad de datos | D25: Limpiar un export del CRM: espacios, mayúsculas, montos y fechas en texto, duplicados, IDs inexistentes y diferencias vs. el maestro. | E25: =COUNTIF('E5_Limpieza_Datos'!$A$1:$BZ$400,"✓") -> 0 | F25: 587 | G25: =IFERROR(E25/F25,0) -> 0
B26: E6_Pivots | C26: Tablas dinámicas | D26: Construir pivots (agrupación por mes, % del total, campos calculados, slicers) y validar con GETPIVOTDATA. | E26: =COUNTIF('E6_Pivots'!$A$1:$BZ$400,"✓") -> 0 | F26: 119 | G26: =IFERROR(E26/F26,0) -> 0
B27: E7_Dinamicas_365 | C27: Matrices dinámicas | D27: FILTER, UNIQUE, SORT, XLOOKUP de varias columnas, TEXTJOIN, LET, SEQUENCE. | E27: =COUNTIF('E7_Dinamicas_365'!$A$1:$BZ$400,"✓") -> 0 | F27: 4 | G27: =IFERROR(E27/F27,0) -> 0
B28: E8_Tendencias | C28: Tendencias y churn | D28: Uso mensual, MoM %, promedio móvil, churn y GRR, pipeline de renovaciones con ARR en riesgo. | E28: =COUNTIF('E8_Tendencias'!$A$1:$BZ$400,"✓") -> 0 | F28: 124 | G28: =IFERROR(E28/F28,0) -> 0
B29: E9_Dashboard_CSM | C29: Dashboard | D29: Tablero para un CSM con lista desplegable, KPIs, top 5 cuentas en riesgo y gráfica. | E29: =COUNTIF('E9_Dashboard_CSM'!$A$1:$BZ$400,"✓") -> 0 | F29: 11 | G29: =IFERROR(E29/F29,0) -> 0
D30: TOTAL | E30: =SUM(E21:E29) -> 0 | F30: =SUM(F21:F29) -> 0 | G30: =IFERROR(E30/F30,0) -> 0
B32: Extras (sin verificación automática)
B33: E10_PowerQuery | D33: Importar y combinar los CSV con Power Query; refrescar.
B34: Entrevista | D34: Preguntas técnicas y de negocio para practicar en voz alta (en inglés).
B35: Diccionario | D35: Qué contiene cada tabla y columna.
B38: Atajos útiles
B39: Ctrl + T | D39: Convertir rango en Tabla
B40: Alt, N, V | D40: Insertar tabla dinámica
B41: F4 | D41: Fijar referencia ($A$1)
B42: Ctrl + Shift + L | D42: Activar filtros
B43: Ctrl + Flecha | D43: Ir al final de los datos
B44: Ctrl + Shift + Flecha | D44: Seleccionar hasta el final
B45: Alt + = | D45: Autosuma
B46: Ctrl + ` | D46: Mostrar fórmulas
B47: F9 (dentro de una fórmula) | D47: Evaluar una parte de la fórmula
B48: Fórmulas > Evaluar fórmula | D48: Depurar fórmulas paso a paso
B49: Ctrl + Alt + F5 | D49: Actualizar todo (pivots / Power Query)
B51: Funciones: inglés → español (Excel las traduce solo)
B52: Inglés | D52: Español
B53: XLOOKUP | D53: BUSCARX
B54: VLOOKUP | D54: BUSCARV
B55: HLOOKUP | D55: BUSCARH
B56: INDEX | D56: INDICE
B57: MATCH | D57: COINCIDIR
B58: XMATCH | D58: COINCIDIRX
B59: SUMIFS | D59: SUMAR.SI.CONJUNTO
B60: COUNTIFS | D60: CONTAR.SI.CONJUNTO
B61: AVERAGEIFS | D61: PROMEDIO.SI.CONJUNTO
B62: MAXIFS / MINIFS | D62: MAX.SI.CONJUNTO / MIN.SI.CONJUNTO
B63: SUMPRODUCT | D63: SUMAPRODUCTO
... B79: GETPIVOTDATA | D79: IMPORTARDATOSDINAMICOS

Sheet Diccionario
A1: Diccionario de datos
A2: Antes de analizar, entiende la granularidad de cada tabla (¿una fila = qué?) y cuáles son las llaves para relacionarlas.
A5: Tabla | B5: Hoja | C5: Columna | D5: Descripción | E5: Filas
A6: tbl_Accounts | B6: Accounts | D6: Maestro de cuentas (1 fila por cliente) | E6: 150
C7: AccountID | D7: ID único de la cuenta (llave primaria)
C8: AccountName | D8: Nombre del cliente
C9: Segment | D9: Enterprise / Mid-Market / SMB
C10: Region | D10: Región comercial
C11: Industry | D11: Industria
C12: Product | D12: Producto principal contratado
C13: CSM_ID | D13: CSM asignado (llave hacia tbl_CSMs)
C14: ARR_USD | D14: Ingreso recurrente anual
C15: LicensedSeats | D15: Licencias contratadas
C16: ContractStart | D16: Inicio de contrato
C17: RenewalDate | D17: Próxima renovación (o fecha de churn si Status = Churned)
C18: Status | D18: Active / Churned
... C20: ContractualReporting | D20: Si el contrato obliga a enviar reportes de uso (Monthly/Quarterly/None)
A21: tbl_CSMs | B21: CSMs | D21: Customer Success Managers | E21: 8
C22: CSM_ID | D22: ID del CSM
C23: CSM_Name | D23: Nombre
C24: Email | D24: Correo
C25: Team | D25: Segmento que atiende
C26: Manager | D26: Líder
A27: tbl_Usage | B27: Usage_Monthly | D27: Uso del producto por cuenta y mes (12 meses) | E27: 1748
C28: AccountID | D28: Cuenta
C29: Month | D29: Primer día del mes
C30: ActiveUsers | D30: Usuarios activos en el mes
C31: Logins | D31: Inicios de sesión
C32: ReportsRun | D32: Reportes ejecutados dentro del producto
C33: FeaturesAdopted | D33: Funcionalidades clave usadas (1-10)
C34: AvgSessionMin | D34: Duración media de sesión
A35: tbl_Tickets | B35: Support_Tickets | D35: Tickets de soporte (último año) | E35: 774
C36: TicketID | D36: ID
C37: AccountID | D37: Cuenta
C38: OpenedDate | D38: Apertura
C39: ClosedDate | D39: Cierre (vacío = abierto)
C40: Priority | D40: P1 (crítico) a P4
C41: Category | D41: Tipo
C42: CSAT | D42: Satisfacción 1-5 (vacío = sin respuesta)
A43: tbl_NPS | B43: NPS | D43: Respuestas de encuesta NPS (algunas > 12 meses) | E43: 178
C44: SurveyID | D44: ID
C45: AccountID | D45: Cuenta
C46: ResponseDate | D46: Fecha
C47: Score | D47: 0-10. Promotor 9-10, Pasivo 7-8, Detractor 0-6
A48: tbl_Reports | B48: Report_Catalog | D48: Inventario de reportes que mantiene CS Ops | E48: 36
C49: ReportID | D49: ID
C50: ReportName | D50: Nombre
C51: Type | D51: Standard / Custom / Contractual
C52: Audience | D52: Para quién es
C53: Frequency | D53: Cada cuánto se actualiza/envía
C54: Source | D54: Sistema origen
C55: Owner | D55: Analista dueño
C56: CreatedDate | D56: Creación
C57: LastModified | D57: Última modificación
C58: Recipients | D58: Personas en la lista de distribución
C59: MaintHrsPerMonth | D59: Horas al mes para mantenerlo
A60: tbl_ReportLog | B60: Report_Usage_Log | D60: Log de consultas de reportes (últimos 180 días) | E60: 3631
C61: LogID | D61: ID
C62: Date | D62: Fecha
C63: ReportID | D63: Reporte
C64: UserEmail | D64: Usuario
C65: UserRole | D65: Rol del usuario
C66: Action | D66: View / Export / Subscribe
C67: DurationSec | D67: Segundos en el reporte
A69: Relaciones: tbl_Accounts[AccountID] 1→N tbl_Usage / tbl_Tickets / tbl_NPS · tbl_CSMs[CSM_ID] 1→N tbl_Accounts · tbl_Reports[ReportID] 1→N tbl_ReportLog

Sheet E1_Lookups
A1: E1 · Lookups: traer datos de otras tablas
A2: Objetivo: un CSM te manda una lista de IDs (copiada de un correo, con espacios y minúsculas) y necesita nombre, segmento, CSM, ARR, tier, uso del último mes y días para la renovación. Practica las 3 familias de búsqueda y cuándo usar cada una.
A3: Contexto: es el trabajo diario de CS Ops — enriquecer listas con datos del CRM. XLOOKUP es el estándar hoy, pero en entrevistas y archivos heredados verás VLOOKUP e INDEX/MATCH.
A5: AccountID (lista del CSM) | B5: AccountName | C5: Segment | D5: CSM_Name | E5: ARR_USD | F5: Tier (aprox.) | G5: Tier (XLOOKUP) | H5: ActiveUsers último registro | I5: Días a renovación | K5: ✓B | L5: ✓C | M5: ✓D | N5: ✓E | O5: ✓F | P5: ✓G | Q5: ✓H | R5: ✓I | T5: Min ARR | U5: Tier
A6: Dato dado (ojo: espacios y minúsculas) | B6: VLOOKUP(TRIM(A7), tbl_Accounts, 2, FALSE) + IFERROR → "No encontrado" | C6: INDEX(tbl_Accounts[Segment], MATCH(TRIM(A7), tbl_Accounts[AccountID], 0)) + IFERROR → "No encontrado" | D6: XLOOKUP anidado: primero el CSM_ID en tbl_Accounts y luego el nombre en tbl_CSMs. IFERROR → "No encontrado" | E6: XLOOKUP con if_not_found = 0 | F6: Si ARR=0 → ""; si no VLOOKUP(E7, $T$7:$U$10, 2, TRUE) (búsqueda aproximada) | G6: Igual pero con XLOOKUP(E7, $T$7:$T$10, $U$7:$U$10, , -1) | H6: XLOOKUP con search_mode -1 (de abajo hacia arriba) en tbl_Usage → último mes con datos. if_not_found → "No encontrado" | I6: IFERROR(XLOOKUP(...RenewalDate) - AsOfDate, "") | T6: Tabla de tiers: ordenada ascendente (requisito de la búsqueda aproximada)
A7: ACC-0010 | K7: =IF(ISBLANK(B7),"",IF(IFERROR(EXACT(B7,'_key'!$A$1),FALSE),"✓","✗")) -> 0 | L7: =IF(ISBLANK(C7),"",IF(IFERROR(EXACT(C7,'_key'!$A$2),FALSE),"✓","✗")) -> 0 | M7: =IF(ISBLANK(D7),"",IF(IFERROR(EXACT(D7,'_key'!$A$3),FALSE),"✓","✗")) -> 0 | N7: =IF(ISBLANK(E7),"",IF(IFERROR(ABS(E7-'_key'!$A$4)<=0.005,FALSE),"✓","✗")) -> 0 | O7: =IF(ISBLANK(F7),"",IF(IFERROR(EXACT(F7,'_key'!$A$5),FALSE),"✓","✗")) -> 0 | P7: =IF(ISBLANK(G7),"",IF(IFERROR(EXACT(G7,'_key'!$A$6),FALSE),"✓","✗")) -> 0 | Q7: =IF(ISBLANK(H7),"",IF(IFERROR(ABS(H7-'_key'!$A$7)<=0.005,FALSE),"✓","✗")) -> 0 | R7: =IF(ISBLANK(I7),"",IF(IFERROR(ABS(I7-'_key'!$A$8)<=0.005,FALSE),"✓","✗")) -> 0 | T7: 0 | U7: Bronze
A8: ACC-0074 | K8: =IF(ISBLANK(B8),"",IF(IFERROR(EXACT(B8,'_key'!$A$9),FALSE),"✓","✗")) -> 0 | L8: =IF(ISBLANK(C8),"",IF(IFERROR(EXACT(C8,'_key'!$A$10),FALSE),"✓","✗")) -> 0 | M8: =IF(ISBLANK(D8),"",IF(IFERROR(EXACT(D8,'_key'!$A$11),FALSE),"✓","✗")) -> 0 | N8: =IF(ISBLANK(E8),"",IF(IFERROR(ABS(E8-'_key'!$A$12)<=0.005,FALSE),"✓","✗")) -> 0 | O8: =IF(ISBLANK(F8),"",IF(IFERROR(EXACT(F8,'_key'!$A$13),FALSE),"✓","✗")) -> 0 | P8: =IF(ISBLANK(G8),"",IF(IFERROR(EXACT(G8,'_key'!$A$14),FALSE),"✓","✗")) -> 0 | Q8: =IF(ISBLANK(H8),"",IF(IFERROR(ABS(H8-'_key'!$A$15)<=0.005,FALSE),"✓","✗")) -> 0 | R8: =IF(ISBLANK(I8),"",IF(IFERROR(ABS(I8-'_key'!$A$16)<=0.005,FALSE),"✓","✗")) -> 0 | T8: 25000 | U8: Silver
A9: ACC-0037 | K9: =IF(ISBLANK(B9),"",IF(IFERROR(EXACT(B9,'_key'!$A$17),FALSE),"✓","✗")) -> 0 | L9: =IF(ISBLANK(C9),"",IF(IFERROR(EXACT(C9,'_key'!$A$18),FALSE),"✓","✗")) -> 0 | M9: =IF(ISBLANK(D9),"",IF(IFERROR(EXACT(D9,'_key'!$A$19),FALSE),"✓","✗")) -> 0 | N9: =IF(ISBLANK(E9),"",IF(IFERROR(ABS(E9-'_key'!$A$20)<=0.005,FALSE),"✓","✗")) -> 0 | O9: =IF(ISBLANK(F9),"",IF(IFERROR(EXACT(F9,'_key'!$A$21),FALSE),"✓","✗")) -> 0 | P9: =IF(ISBLANK(G9),"",IF(IFERROR(EXACT(G9,'_key'!$A$22),FALSE),"✓","✗")) -> 0 | Q9: =IF(ISBLANK(H9),"",IF(IFERROR(ABS(H9-'_key'!$A$23)<=0.005,FALSE),"✓","✗")) -> 0 | R9: =IF(ISBLANK(I9),"",IF(IFERROR(ABS(I9-'_key'!$A$24)<=0.005,FALSE),"✓","✗")) -> 0 | T9: 100000 | U9: Gold
A10: acc-0096 | K10: =IF(ISBLANK(B10),"",IF(IFERROR(EXACT(B10,'_key'!$A$25),FALSE),"✓","✗")) -> 0 | L10: =IF(ISBLANK(C10),"",IF(IFERROR(EXACT(C10,'_key'!$A$26),FALSE),"✓","✗")) -> 0 | M10: =IF(ISBLANK(D10),"",IF(IFERROR(EXACT(D10,'_key'!$A$27),FALSE),"✓","✗")) -> 0 | N10: =IF(ISBLANK(E10),"",IF(IFERROR(ABS(E10-'_key'!$A$28)<=0.005,FALSE),"✓","✗")) -> 0 | O10: =IF(ISBLANK(F10),"",IF(IFERROR(EXACT(F10,'_key'!$A$29),FALSE),"✓","✗")) -> 0 | P10: =IF(ISBLANK(G10),"",IF(IFERROR(EXACT(G10,'_key'!$A$30),FALSE),"✓","✗")) -> 0 | Q10: =IF(ISBLANK(H10),"",IF(IFERROR(ABS(H10-'_key'!$A$31)<=0.005,FALSE),"✓","✗")) -> 0 | R10: =IF(ISBLANK(I10),"",IF(IFERROR(ABS(I10-'_key'!$A$32)<=0.005,FALSE),"✓","✗")) -> 0 | T10: 250000 | U10: Platinum
A11: ACC-0119 | K11: =IF(ISBLANK(B11),"",IF(IFERROR(EXACT(B11,'_key'!$A$33),FALSE),"✓","✗")) -> 0 | L11: =IF(ISBLANK(C11),"",IF(IFERROR(EXACT(C11,'_key'!$A$34),FALSE),"✓","✗")) -> 0 | M11: =IF(ISBLANK(D11),"",IF(IFERROR(EXACT(D11,'_key'!$A$35),FALSE),"✓","✗")) -> 0 | N11: =IF(ISBLANK(E11),"",IF(IFERROR(ABS(E11-'_key'!$A$36)<=0.005,FALSE),"✓","✗")) -> 0 | O11: =IF(ISBLANK(F11),"",IF(IFERROR(EXACT(F11,'_key'!$A$37),FALSE),"✓","✗")) -> 0 | P11: =IF(ISBLANK(G11),"",IF(IFERROR(EXACT(G11,'_key'!$A$38),FALSE),"✓","✗")) -> 0 | Q11: =IF(ISBLANK(H11),"",IF(IFERROR(ABS(H11-'_key'!$A$39)<=0.005,FALSE),"✓","✗")) -> 0 | R11: =IF(ISBLANK(I11),"",IF(IFERROR(ABS(I11-'_key'!$A$40)<=0.005,FALSE),"✓","✗")) -> 0
A12: ACC-0095 | K12: =IF(ISBLANK(B12),"",IF(IFERROR(EXACT(B12,'_key'!$A$41),FALSE),"✓","✗")) -> 0 | L12: =IF(ISBLANK(C12),"",IF(IFERROR(EXACT(C12,'_key'!$A$42),FALSE),"✓","✗")) -> 0 | M12: =IF(ISBLANK(D12),"",IF(IFERROR(EXACT(D12,'_key'!$A$43),FALSE),"✓","✗")) -> 0 | N12: =IF(ISBLANK(E12),"",IF(IFERROR(ABS(E12-'_key'!$A$44)<=0.005,FALSE),"✓","✗")) -> 0 | O12: =IF(ISBLANK(F12),"",IF(IFERROR(EXACT(F12,'_key'!$A$45),FALSE),"✓","✗")) -> 0 | P12: =IF(ISBLANK(G12),"",IF(IFERROR(EXACT(G12,'_key'!$A$46),FALSE),"✓","✗")) -> 0 | Q12: =IF(ISBLANK(H12),"",IF(IFERROR(ABS(H12-'_key'!$A$47)<=0.005,FALSE),"✓","✗")) -> 0 | R12: =IF(ISBLANK(I12),"",IF(IFERROR(ABS(I12-'_key'!$A$48)<=0.005,FALSE),"✓","✗")) -> 0
A13: ACC-0025 | K13: =IF(ISBLANK(B13),"",IF(IFERROR(EXACT(B13,'_key'!$A$49),FALSE),"✓","✗")) -> 0 | L13: =IF(ISBLANK(C13),"",IF(IFERROR(EXACT(C13,'_key'!$A$50),FALSE),"✓","✗")) -> 0 | M13: =IF(ISBLANK(D13),"",IF(IFERROR(EXACT(D13,'_key'!$A$51),FALSE),"✓","✗")) -> 0 | N13: =IF(ISBLANK(E13),"",IF(IFERROR(ABS(E13-'_key'!$A$52)<=0.005,FALSE),"✓","✗")) -> 0 | O13: =IF(ISBLANK(F13),"",IF(IFERROR(EXACT(F13,'_key'!$A$53),FALSE),"✓","✗")) -> 0 | P13: =IF(ISBLANK(G13),"",IF(IFERROR(EXACT(G13,'_key'!$A$54),FALSE),"✓","✗")) -> 0 | Q13: =IF(ISBLANK(H13),"",IF(IFERROR(ABS(H13-'_key'!$A$55)<=0.005,FALSE),"✓","✗")) -> 0 | R13: =IF(ISBLANK(I13),"",IF(IFERROR(ABS(I13-'_key'!$A$56)<=0.005,FALSE),"✓","✗")) -> 0
A14: ACC-9999 | K14: =IF(ISBLANK(B14),"",IF(IFERROR(EXACT(B14,'_key'!$A$57),FALSE),"✓","✗")) -> 0 | L14: =IF(ISBLANK(C14),"",IF(IFERROR(EXACT(C14,'_key'!$A$58),FALSE),"✓","✗")) -> 0 | M14: =IF(ISBLANK(D14),"",IF(IFERROR(EXACT(D14,'_key'!$A$59),FALSE),"✓","✗")) -> 0 | N14: =IF(ISBLANK(E14),"",IF(IFERROR(ABS(E14-'_key'!$A$60)<=0.005,FALSE),"✓","✗")) -> 0 | O14: =IF(ISBLANK(F14),"",IF(IFERROR(EXACT(F14,'_key'!$A$61),FALSE),"✓","✗")) -> 0 | P14: =IF(ISBLANK(G14),"",IF(IFERROR(EXACT(G14,'_key'!$A$62),FALSE),"✓","✗")) -> 0 | Q14: =IF(ISBLANK(H14),"",IF(IFERROR(EXACT(H14,'_key'!$A$63),FALSE),"✓","✗")) -> 0 | R14: =IF(ISBLANK(I14),"",IF(IFERROR(EXACT(I14,'_key'!$A$64),FALSE),"✓","✗")) -> 0
A15: ACC-0117 | K15: =IF(ISBLANK(B15),"",IF(IFERROR(EXACT(B15,'_key'!$A$65),FALSE),"✓","✗")) -> 0 | L15: =IF(ISBLANK(C15),"",IF(IFERROR(EXACT(C15,'_key'!$A$66),FALSE),"✓","✗")) -> 0 | M15: =IF(ISBLANK(D15),"",IF(IFERROR(EXACT(D15,'_key'!$A$67),FALSE),"✓","✗")) -> 0 | N15: =IF(ISBLANK(E15),"",IF(IFERROR(ABS(E15-'_key'!$A$68)<=0.005,FALSE),"✓","✗")) -> 0 | O15: =IF(ISBLANK(F15),"",IF(IFERROR(EXACT(F15,'_key'!$A$69),FALSE),"✓","✗")) -> 0 | P15: =IF(ISBLANK(G15),"",IF(IFERROR(EXACT(G15,'_key'!$A$70),FALSE),"✓","✗")) -> 0 | Q15: =IF(ISBLANK(H15),"",IF(IFERROR(ABS(H15-'_key'!$A$71)<=0.005,FALSE),"✓","✗")) -> 0 | R15: =IF(ISBLANK(I15),"",IF(IFERROR(ABS(I15-'_key'!$A$72)<=0.005,FALSE),"✓","✗")) -> 0
A16: ACC-0128 | K16: =IF(ISBLANK(B16),"",IF(IFERROR(EXACT(B16,'_key'!$A$73),FALSE),"✓","✗")) -> 0 | L16: =IF(ISBLANK(C16),"",IF(IFERROR(EXACT(C16,'_key'!$A$74),FALSE),"✓","✗")) -> 0 | M16: =IF(ISBLANK(D16),"",IF(IFERROR(EXACT(D16,'_key'!$A$75),FALSE),"✓","✗")) -> 0 | N16: =IF(ISBLANK(E16),"",IF(IFERROR(ABS(E16-'_key'!$A$76)<=0.005,FALSE),"✓","✗")) -> 0 | O16: =IF(ISBLANK(F16),"",IF(IFERROR(EXACT(F16,'_key'!$A$77),FALSE),"✓","✗")) -> 0 | P16: =IF(ISBLANK(G16),"",IF(IFERROR(EXACT(G16,'_key'!$A$78),FALSE),"✓","✗")) -> 0 | Q16: =IF(ISBLANK(H16),"",IF(IFERROR(ABS(H16-'_key'!$A$79)<=0.005,FALSE),"✓","✗")) -> 0 | R16: =IF(ISBLANK(I16),"",IF(IFERROR(ABS(I16-'_key'!$A$80)<=0.005,FALSE),"✓","✗")) -> 0
A17: ACC-0005 | K17: =IF(ISBLANK(B17),"",IF(IFERROR(EXACT(B17,'_key'!$A$81),FALSE),"✓","✗")) -> 0 | L17: =IF(ISBLANK(C17),"",IF(IFERROR(EXACT(C17,'_key'!$A$82),FALSE),"✓","✗")) -> 0 | M17: =IF(ISBLANK(D17),"",IF(IFERROR(EXACT(D17,'_key'!$A$83),FALSE),"✓","✗")) -> 0 | N17: =IF(ISBLANK(E17),"",IF(IFERROR(ABS(E17-'_key'!$A$84)<=0.005,FALSE),"✓","✗")) -> 0 | O17: =IF(ISBLANK(F17),"",IF(IFERROR(EXACT(F17,'_key'!$A$85),FALSE),"✓","✗")) -> 0 | P17: =IF(ISBLANK(G17),"",IF(IFERROR(EXACT(G17,'_key'!$A$86),FALSE),"✓","✗")) -> 0 | Q17: =IF(ISBLANK(H17),"",IF(IFERROR(ABS(H17-'_key'!$A$87)<=0.005,FALSE),"✓","✗")) -> 0 | R17: =IF(ISBLANK(I17),"",IF(IFERROR(ABS(I17-'_key'!$A$88)<=0.005,FALSE),"✓","✗")) -> 0
A18: ACC-0141 | K18: =IF(ISBLANK(B18),"",IF(IFERROR(EXACT(B18,'_key'!$A$89),FALSE),"✓","✗")) -> 0 | L18: =IF(ISBLANK(C18),"",IF(IFERROR(EXACT(C18,'_key'!$A$90),FALSE),"✓","✗")) -> 0 | M18: =IF(ISBLANK(D18),"",IF(IFERROR(EXACT(D18,'_key'!$A$91),FALSE),"✓","✗")) -> 0 | N18: =IF(ISBLANK(E18),"",IF(IFERROR(ABS(E18-'_key'!$A$92)<=0.005,FALSE),"✓","✗")) -> 0 | O18: =IF(ISBLANK(F18),"",IF(IFERROR(EXACT(F18,'_key'!$A$93),FALSE),"✓","✗")) -> 0 | P18: =IF(ISBLANK(G18),"",IF(IFERROR(EXACT(G18,'_key'!$A$94),FALSE),"✓","✗")) -> 0 | Q18: =IF(ISBLANK(H18),"",IF(IFERROR(ABS(H18-'_key'!$A$95)<=0.005,FALSE),"✓","✗")) -> 0 | R18: =IF(ISBLANK(I18),"",IF(IFERROR(ABS(I18-'_key'!$A$96)<=0.005,FALSE),"✓","✗")) -> 0
A19: ACC-0132 | K19: =IF(ISBLANK(B19),"",IF(IFERROR(EXACT(B19,'_key'!$A$97),FALSE),"✓","✗")) -> 0 | L19: =IF(ISBLANK(C19),"",IF(IFERROR(EXACT(C19,'_key'!$A$98),FALSE),"✓","✗")) -> 0 | M19: =IF(ISBLANK(D19),"",IF(IFERROR(EXACT(D19,'_key'!$A$99),FALSE),"✓","✗")) -> 0 | N19: =IF(ISBLANK(E19),"",IF(IFERROR(ABS(E19-'_key'!$A$100)<=0.005,FALSE),"✓","✗")) -> 0 | O19: =IF(ISBLANK(F19),"",IF(IFERROR(EXACT(F19,'_key'!$A$101),FALSE),"✓","✗")) -> 0 | P19: =IF(ISBLANK(G19),"",IF(IFERROR(EXACT(G19,'_key'!$A$102),FALSE),"✓","✗")) -> 0 | Q19: =IF(ISBLANK(H19),"",IF(IFERROR(ABS(H19-'_key'!$A$103)<=0.005,FALSE),"✓","✗")) -> 0 | R19: =IF(ISBLANK(I19),"",IF(IFERROR(ABS(I19-'_key'!$A$104)<=0.005,FALSE),"✓","✗")) -> 0
A20: ACC-0111 | K20: =IF(ISBLANK(B20),"",IF(IFERROR(EXACT(B20,'_key'!$A$105),FALSE),"✓","✗")) -> 0 | L20: =IF(ISBLANK(C20),"",IF(IFERROR(EXACT(C20,'_key'!$A$106),FALSE),"✓","✗")) -> 0 | M20: =IF(ISBLANK(D20),"",IF(IFERROR(EXACT(D20,'_key'!$A$107),FALSE),"✓","✗")) -> 0 | N20: =IF(ISBLANK(E20),"",IF(IFERROR(ABS(E20-'_key'!$A$108)<=0.005,FALSE),"✓","✗")) -> 0 | O20: =IF(ISBLANK(F20),"",IF(IFERROR(EXACT(F20,'_key'!$A$109),FALSE),"✓","✗")) -> 0 | P20: =IF(ISBLANK(G20),"",IF(IFERROR(EXACT(G20,'_key'!$A$110),FALSE),"✓","✗")) -> 0 | Q20: =IF(ISBLANK(H20),"",IF(IFERROR(ABS(H20-'_key'!$A$111)<=0.005,FALSE),"✓","✗")) -> 0 | R20: =IF(ISBLANK(I20),"",IF(IFERROR(ABS(I20-'_key'!$A$112)<=0.005,FALSE),"✓","✗")) -> 0
A21: ACC-0148 | K21: =IF(ISBLANK(B21),"",IF(IFERROR(EXACT(B21,'_key'!$A$113),FALSE),"✓","✗")) -> 0 | L21: =IF(ISBLANK(C21),"",IF(IFERROR(EXACT(C21,'_key'!$A$114),FALSE),"✓","✗")) -> 0 | M21: =IF(ISBLANK(D21),"",IF(IFERROR(EXACT(D21,'_key'!$A$115),FALSE),"✓","✗")) -> 0 | N21: =IF(ISBLANK(E21),"",IF(IFERROR(ABS(E21-'_key'!$A$116)<=0.005,FALSE),"✓","✗")) -> 0 | O21: =IF(ISBLANK(F21),"",IF(IFERROR(EXACT(F21,'_key'!$A$117),FALSE),"✓","✗")) -> 0 | P21: =IF(ISBLANK(G21),"",IF(IFERROR(EXACT(G21,'_key'!$A$118),FALSE),"✓","✗")) -> 0 | Q21: =IF(ISBLANK(H21),"",IF(IFERROR(ABS(H21-'_key'!$A$119)<=0.005,FALSE),"✓","✗")) -> 0 | R21: =IF(ISBLANK(I21),"",IF(IFERROR(ABS(I21-'_key'!$A$120)<=0.005,FALSE),"✓","✗")) -> 0
A23: Para pensar (entrevista): ¿por qué VLOOKUP se rompe si alguien inserta una columna en tbl_Accounts? ¿Qué ventajas tiene XLOOKUP (búsqueda a la izquierda, if_not_found, búsqueda inversa, coincidencia aproximada sin ordenar)? ¿Qué pasa con el ID que tiene espacios si no usas TRIM?

Sheet E2_Agregaciones
A1: E2 · Agregaciones condicionales (SUMIFS, COUNTIFS, AVERAGEIFS, MAXIFS, SUMPRODUCT)
A2: Objetivo: responder con fórmulas las preguntas típicas de liderazgo: ¿cuánto ARR activo tenemos por segmento y región? ¿cómo está el book of business de cada CSM? ¿cómo va el backlog de soporte? ¿cuál es nuestro NPS?
A3: Tip: estas mismas preguntas se pueden contestar con una tabla dinámica (E6). Saber hacerlas con fórmulas te permite construir reportes que se actualizan solos y validar los pivots.
A4: 1) ARR activo por Segmento × Región
A5: Segment \ Region | B5: North America | C5: LATAM | D5: EMEA | E5: APAC | F5: Total | J5: Chk | K5: Chk | L5: Chk | M5: Chk | N5: Chk
B6: SUMIFS(tbl_Accounts[ARR_USD], ...[Segment], $A7, ...[Region], B$5, ...[Status], "Active") | C6: Fija fila/columna con $ para arrastrar | F6: SUM de la fila
A7: Enterprise | J7: =IF(ISBLANK(B7),"",IF(IFERROR(ABS(B7-'_key'!$A$121)<=0.005,FALSE),"✓","✗")) -> 0 | K7: =IF(ISBLANK(C7),"",IF(IFERROR(ABS(C7-'_key'!$A$122)<=0.005,FALSE),"✓","✗")) -> 0 | L7: =IF(ISBLANK(D7),"",IF(IFERROR(ABS(D7-'_key'!$A$123)<=0.005,FALSE),"✓","✗")) -> 0 | M7: =IF(ISBLANK(E7),"",IF(IFERROR(ABS(E7-'_key'!$A$124)<=0.005,FALSE),"✓","✗")) -> 0 | N7: =IF(ISBLANK(F7),"",IF(IFERROR(ABS(F7-'_key'!$A$125)<=0.005,FALSE),"✓","✗")) -> 0
A8: Mid-Market | J8: =IF(ISBLANK(B8),"",IF(IFERROR(ABS(B8-'_key'!$A$126)<=0.005,FALSE),"✓","✗")) -> 0 | K8: =IF(ISBLANK(C8),"",IF(IFERROR(ABS(C8-'_key'!$A$127)<=0.005,FALSE),"✓","✗")) -> 0 | L8: =IF(ISBLANK(D8),"",IF(IFERROR(ABS(D8-'_key'!$A$128)<=0.005,FALSE),"✓","✗")) -> 0 | M8: =IF(ISBLANK(E8),"",IF(IFERROR(ABS(E8-'_key'!$A$129)<=0.005,FALSE),"✓","✗")) -> 0 | N8: =IF(ISBLANK(F8),"",IF(IFERROR(ABS(F8-'_key'!$A$130)<=0.005,FALSE),"✓","✗")) -> 0
A9: SMB | J9: =IF(ISBLANK(B9),"",IF(IFERROR(ABS(B9-'_key'!$A$131)<=0.005,FALSE),"✓","✗")) -> 0 | K9: =IF(ISBLANK(C9),"",IF(IFERROR(ABS(C9-'_key'!$A$132)<=0.005,FALSE),"✓","✗")) -> 0 | L9: =IF(ISBLANK(D9),"",IF(IFERROR(ABS(D9-'_key'!$A$133)<=0.005,FALSE),"✓","✗")) -> 0 | M9: =IF(ISBLANK(E9),"",IF(IFERROR(ABS(E9-'_key'!$A$134)<=0.005,FALSE),"✓","✗")) -> 0 | N9: =IF(ISBLANK(F9),"",IF(IFERROR(ABS(F9-'_key'!$A$135)<=0.005,FALSE),"✓","✗")) -> 0
A10: Total | J10: =IF(ISBLANK(B10),"",IF(IFERROR(ABS(B10-'_key'!$A$136)<=0.005,FALSE),"✓","✗")) -> 0 | K10: =IF(ISBLANK(C10),"",IF(IFERROR(ABS(C10-'_key'!$A$137)<=0.005,FALSE),"✓","✗")) -> 0 | L10: =IF(ISBLANK(D10),"",IF(IFERROR(ABS(D10-'_key'!$A$138)<=0.005,FALSE),"✓","✗")) -> 0 | M10: =IF(ISBLANK(E10),"",IF(IFERROR(ABS(E10-'_key'!$A$139)<=0.005,FALSE),"✓","✗")) -> 0 | N10: =IF(ISBLANK(F10),"",IF(IFERROR(ABS(F10-'_key'!$A$140)<=0.005,FALSE),"✓","✗")) -> 0
A13: 2) Book of business por CSM (solo cuentas activas)
A14: CSM_ID | B14: CSM_Name | C14: # Cuentas | D14: ARR | E14: ARR promedio | F14: Cuenta más grande (ARR) | G14: Próxima renovación | H14: % del ARR total | J14: ✓B | K14: ✓C | L14: ✓D | M14: ✓E | N14: ✓F | O14: ✓G | P14: ✓H
A15: Dado | B15: XLOOKUP en tbl_CSMs | C15: COUNTIFS con 2 criterios | D15: SUMIFS | E15: AVERAGEIFS (IFERROR → 0) | F15: MAXIFS | G15: MINIFS sobre RenewalDate | H15: D / SUM($D$...)
A16: CSM-01 | J16: =IF(ISBLANK(B16),"",IF(IFERROR(EXACT(B16,'_key'!$A$141),FALSE),"✓","✗")) -> 0 | K16: =IF(ISBLANK(C16),"",IF(IFERROR(ABS(C16-'_key'!$A$142)<=0.005,FALSE),"✓","✗")) -> 0 | L16: =IF(ISBLANK(D16),"",IF(IFERROR(ABS(D16-'_key'!$A$143)<=0.005,FALSE),"✓","✗")) -> 0 | M16: =IF(ISBLANK(E16),"",IF(IFERROR(ABS(E16-'_key'!$A$144)<=0.005,FALSE),"✓","✗")) -> 0 | N16: =IF(ISBLANK(F16),"",IF(IFERROR(ABS(F16-'_key'!$A$145)<=0.005,FALSE),"✓","✗")) -> 0 | O16: =IF(ISBLANK(G16),"",IF(IFERROR(ABS(G16-'_key'!$A$146)<=0.005,FALSE),"✓","✗")) -> 0 | P16: =IF(ISBLANK(H16),"",IF(IFERROR(ABS(H16-'_key'!$A$147)<=0.0005,FALSE),"✓","✗")) -> 0
A17: CSM-02 | J17: =IF(ISBLANK(B17),"",IF(IFERROR(EXACT(B17,'_key'!$A$148),FALSE),"✓","✗")) -> 0 | K17: =IF(ISBLANK(C17),"",IF(IFERROR(ABS(C17-'_key'!$A$149)<=0.005,FALSE),"✓","✗")) -> 0 | L17: =IF(ISBLANK(D17),"",IF(IFERROR(ABS(D17-'_key'!$A$150)<=0.005,FALSE),"✓","✗")) -> 0 | M17: =IF(ISBLANK(E17),"",IF(IFERROR(ABS(E17-'_key'!$A$151)<=0.005,FALSE),"✓","✗")) -> 0 | N17: =IF(ISBLANK(F17),"",IF(IFERROR(ABS(F17-'_key'!$A$152)<=0.005,FALSE),"✓","✗")) -> 0 | O17: =IF(ISBLANK(G17),"",IF(IFERROR(ABS(G17-'_key'!$A$153)<=0.005,FALSE),"✓","✗")) -> 0 | P17: =IF(ISBLANK(H17),"",IF(IFERROR(ABS(H17-'_key'!$A$154)<=0.0005,FALSE),"✓","✗")) -> 0
A18: CSM-03 | J18: =IF(ISBLANK(B18),"",IF(IFERROR(EXACT(B18,'_key'!$A$155),FALSE),"✓","✗")) -> 0 | K18: =IF(ISBLANK(C18),"",IF(IFERROR(ABS(C18-'_key'!$A$156)<=0.005,FALSE),"✓","✗")) -> 0 | L18: =IF(ISBLANK(D18),"",IF(IFERROR(ABS(D18-'_key'!$A$157)<=0.005,FALSE),"✓","✗")) -> 0 | M18: =IF(ISBLANK(E18),"",IF(IFERROR(ABS(E18-'_key'!$A$158)<=0.005,FALSE),"✓","✗")) -> 0 | N18: =IF(ISBLANK(F18),"",IF(IFERROR(ABS(F18-'_key'!$A$159)<=0.005,FALSE),"✓","✗")) -> 0 | O18: =IF(ISBLANK(G18),"",IF(IFERROR(ABS(G18-'_key'!$A$160)<=0.005,FALSE),"✓","✗")) -> 0 | P18: =IF(ISBLANK(H18),"",IF(IFERROR(ABS(H18-'_key'!$A$161)<=0.0005,FALSE),"✓","✗")) -> 0
A19: CSM-04 | J19: =IF(ISBLANK(B19),"",IF(IFERROR(EXACT(B19,'_key'!$A$162),FALSE),"✓","✗")) -> 0 | K19: =IF(ISBLANK(C19),"",IF(IFERROR(ABS(C19-'_key'!$A$163)<=0.005,FALSE),"✓","✗")) -> 0 | L19: =IF(ISBLANK(D19),"",IF(IFERROR(ABS(D19-'_key'!$A$164)<=0.005,FALSE),"✓","✗")) -> 0 | M19: =IF(ISBLANK(E19),"",IF(IFERROR(ABS(E19-'_key'!$A$165)<=0.005,FALSE),"✓","✗")) -> 0 | N19: =IF(ISBLANK(F19),"",IF(IFERROR(ABS(F19-'_key'!$A$166)<=0.005,FALSE),"✓","✗")) -> 0 | O19: =IF(ISBLANK(G19),"",IF(IFERROR(ABS(G19-'_key'!$A$167)<=0.005,FALSE),"✓","✗")) -> 0 | P19: =IF(ISBLANK(H19),"",IF(IFERROR(ABS(H19-'_key'!$A$168)<=0.0005,FALSE),"✓","✗")) -> 0
A20: CSM-05 | J20: =IF(ISBLANK(B20),"",IF(IFERROR(EXACT(B20,'_key'!$A$169),FALSE),"✓","✗")) -> 0 | K20: =IF(ISBLANK(C20),"",IF(IFERROR(ABS(C20-'_key'!$A$170)<=0.005,FALSE),"✓","✗")) -> 0 | L20: =IF(ISBLANK(D20),"",IF(IFERROR(ABS(D20-'_key'!$A$171)<=0.005,FALSE),"✓","✗")) -> 0 | M20: =IF(ISBLANK(E20),"",IF(IFERROR(ABS(E20-'_key'!$A$172)<=0.005,FALSE),"✓","✗")) -> 0 | N20: =IF(ISBLANK(F20),"",IF(IFERROR(ABS(F20-'_key'!$A$173)<=0.005,FALSE),"✓","✗")) -> 0 | O20: =IF(ISBLANK(G20),"",IF(IFERROR(ABS(G20-'_key'!$A$174)<=0.005,FALSE),"✓","✗")) -> 0 | P20: =IF(ISBLANK(H20),"",IF(IFERROR(ABS(H20-'_key'!$A$175)<=0.0005,FALSE),"✓","✗")) -> 0
A21: CSM-06 | J21: =IF(ISBLANK(B21),"",IF(IFERROR(EXACT(B21,'_key'!$A$176),FALSE),"✓","✗")) -> 0 | K21: =IF(ISBLANK(C21),"",IF(IFERROR(ABS(C21-'_key'!$A$177)<=0.005,FALSE),"✓","✗")) -> 0 | L21: =IF(ISBLANK(D21),"",IF(IFERROR(ABS(D21-'_key'!$A$178)<=0.005,FALSE),"✓","✗")) -> 0 | M21: =IF(ISBLANK(E21),"",IF(IFERROR(ABS(E21-'_key'!$A$179)<=0.005,FALSE),"✓","✗")) -> 0 | N21: =IF(ISBLANK(F21),"",IF(IFERROR(ABS(F21-'_key'!$A$180)<=0.005,FALSE),"✓","✗")) -> 0 | O21: =IF(ISBLANK(G21),"",IF(IFERROR(ABS(G21-'_key'!$A$181)<=0.005,FALSE),"✓","✗")) -> 0 | P21: =IF(ISBLANK(H21),"",IF(IFERROR(ABS(H21-'_key'!$A$182)<=0.0005,FALSE),"✓","✗")) -> 0
A22: CSM-07 | J22: =IF(ISBLANK(B22),"",IF(IFERROR(EXACT(B22,'_key'!$A$183),FALSE),"✓","✗")) -> 0 | K22: =IF(ISBLANK(C22),"",IF(IFERROR(ABS(C22-'_key'!$A$184)<=0.005,FALSE),"✓","✗")) -> 0 | L22: =IF(ISBLANK(D22),"",IF(IFERROR(ABS(D22-'_key'!$A$185)<=0.005,FALSE),"✓","✗")) -> 0 | M22: =IF(ISBLANK(E22),"",IF(IFERROR(ABS(E22-'_key'!$A$186)<=0.005,FALSE),"✓","✗")) -> 0 | N22: =IF(ISBLANK(F22),"",IF(IFERROR(ABS(F22-'_key'!$A$187)<=0.005,FALSE),"✓","✗")) -> 0 | O22: =IF(ISBLANK(G22),"",IF(IFERROR(ABS(G22-'_key'!$A$188)<=0.005,FALSE),"✓","✗")) -> 0 | P22: =IF(ISBLANK(H22),"",IF(IFERROR(ABS(H22-'_key'!$A$189)<=0.0005,FALSE),"✓","✗")) -> 0
A23: CSM-08 | J23: =IF(ISBLANK(B23),"",IF(IFERROR(EXACT(B23,'_key'!$A$190),FALSE),"✓","✗")) -> 0 | K23: =IF(ISBLANK(C23),"",IF(IFERROR(ABS(C23-'_key'!$A$191)<=0.005,FALSE),"✓","✗")) -> 0 | L23: =IF(ISBLANK(D23),"",IF(IFERROR(ABS(D23-'_key'!$A$192)<=0.005,FALSE),"✓","✗")) -> 0 | M23: =IF(ISBLANK(E23),"",IF(IFERROR(ABS(E23-'_key'!$A$193)<=0.005,FALSE),"✓","✗")) -> 0 | N23: =IF(ISBLANK(F23),"",IF(IFERROR(ABS(F23-'_key'!$A$194)<=0.005,FALSE),"✓","✗")) -> 0 | O23: =IF(ISBLANK(G23),"",IF(IFERROR(ABS(G23-'_key'!$A$195)<=0.005,FALSE),"✓","✗")) -> 0 | P23: =IF(ISBLANK(H23),"",IF(IFERROR(ABS(H23-'_key'!$A$196)<=0.0005,FALSE),"✓","✗")) -> 0
A26: 3) Soporte por prioridad (todos los tickets del año)
A27: Priority | B27: Total tickets | C27: Abiertos | D27: % abiertos | E27: Días prom. de resolución | F27: CSAT promedio | J27: ✓B | K27: ✓C | L27: ✓D | M27: ✓E | N27: ✓F
A28: Dado | B28: COUNTIFS | C28: COUNTIFS con ClosedDate = "" (vacío) | D28: C / B | E28: SUMPRODUCT((Priority=A)*(ClosedDate<>"")*(ClosedDate-OpenedDate)) / COUNTIFS(..., ClosedDate, "<>") | F28: AVERAGEIFS (ignora vacíos) + IFERROR
A29: P1 | J29: =IF(ISBLANK(B29),"",IF(IFERROR(ABS(B29-'_key'!$A$197)<=0.005,FALSE),"✓","✗")) -> 0 | K29: =IF(ISBLANK(C29),"",IF(IFERROR(ABS(C29-'_key'!$A$198)<=0.005,FALSE),"✓","✗")) -> 0 | L29: =IF(ISBLANK(D29),"",IF(IFERROR(ABS(D29-'_key'!$A$199)<=0.0005,FALSE),"✓","✗")) -> 0 | M29: =IF(ISBLANK(E29),"",IF(IFERROR(ABS(E29-'_key'!$A$200)<=0.05,FALSE),"✓","✗")) -> 0 | N29: =IF(ISBLANK(F29),"",IF(IFERROR(ABS(F29-'_key'!$A$201)<=0.005,FALSE),"✓","✗")) -> 0
A30: P2 | J30: =IF(ISBLANK(B30),"",IF(IFERROR(ABS(B30-'_key'!$A$202)<=0.005,FALSE),"✓","✗")) -> 0 | K30: =IF(ISBLANK(C30),"",IF(IFERROR(ABS(C30-'_key'!$A$203)<=0.005,FALSE),"✓","✗")) -> 0 | L30: =IF(ISBLANK(D30),"",IF(IFERROR(ABS(D30-'_key'!$A$204)<=0.0005,FALSE),"✓","✗")) -> 0 | M30: =IF(ISBLANK(E30),"",IF(IFERROR(ABS(E30-'_key'!$A$205)<=0.05,FALSE),"✓","✗")) -> 0 | N30: =IF(ISBLANK(F30),"",IF(IFERROR(ABS(F30-'_key'!$A$206)<=0.005,FALSE),"✓","✗")) -> 0
A31: P3 | J31: =IF(ISBLANK(B31),"",IF(IFERROR(ABS(B31-'_key'!$A$207)<=0.005,FALSE),"✓","✗")) -> 0 | K31: =IF(ISBLANK(C31),"",IF(IFERROR(ABS(C31-'_key'!$A$208)<=0.005,FALSE),"✓","✗")) -> 0 | L31: =IF(ISBLANK(D31),"",IF(IFERROR(ABS(D31-'_key'!$A$209)<=0.0005,FALSE),"✓","✗")) -> 0 | M31: =IF(ISBLANK(E31),"",IF(IFERROR(ABS(E31-'_key'!$A$210)<=0.05,FALSE),"✓","✗")) -> 0 | N31: =IF(ISBLANK(F31),"",IF(IFERROR(ABS(F31-'_key'!$A$211)<=0.005,FALSE),"✓","✗")) -> 0
A32: P4 | J32: =IF(ISBLANK(B32),"",IF(IFERROR(ABS(B32-'_key'!$A$212)<=0.005,FALSE),"✓","✗")) -> 0 | K32: =IF(ISBLANK(C32),"",IF(IFERROR(ABS(C32-'_key'!$A$213)<=0.005,FALSE),"✓","✗")) -> 0 | L32: =IF(ISBLANK(D32),"",IF(IFERROR(ABS(D32-'_key'!$A$214)<=0.0005,FALSE),"✓","✗")) -> 0 | M32: =IF(ISBLANK(E32),"",IF(IFERROR(ABS(E32-'_key'!$A$215)<=0.05,FALSE),"✓","✗")) -> 0 | N32: =IF(ISBLANK(F32),"",IF(IFERROR(ABS(F32-'_key'!$A$216)<=0.005,FALSE),"✓","✗")) -> 0
A35: 4) NPS global (todas las respuestas)
A36: Métrica | B36: Valor | C36: Pista
A37: Promotores (9-10) | C37: COUNTIF >=9 | J37: =IF(ISBLANK(B37),"",IF(IFERROR(ABS(B37-'_key'!$A$217)<=0.05,FALSE),"✓","✗")) -> 0
A38: Pasivos (7-8) | C38: COUNTIFS con 2 criterios sobre la misma columna | J38: =IF(ISBLANK(B38),"",IF(IFERROR(ABS(B38-'_key'!$A$218)<=0.05,FALSE),"✓","✗")) -> 0
A39: Detractores (0-6) | C39: COUNTIF <=6 | J39: =IF(ISBLANK(B39),"",IF(IFERROR(ABS(B39-'_key'!$A$219)<=0.05,FALSE),"✓","✗")) -> 0
A40: Total respuestas | C40: SUM | J40: =IF(ISBLANK(B40),"",IF(IFERROR(ABS(B40-'_key'!$A$220)<=0.05,FALSE),"✓","✗")) -> 0
A41: NPS | C41: (%Promotores − %Detractores) × 100. Rango −100 a 100 | J41: =IF(ISBLANK(B41),"",IF(IFERROR(ABS(B41-'_key'!$A$221)<=0.05,FALSE),"✓","✗")) -> 0

Sheet E3_Health_Score
A1: E3 · Customer Health Score
A2: Objetivo: calcular para cada cuenta activa un health score de 0-100 combinando adopción (uso de licencias), tendencia de uso, tickets críticos abiertos y NPS; clasificar Green/Yellow/Red y marcar las cuentas en rojo que renuevan en ≤180 días. Los pesos están en la fila 4 (deben sumar 100%).
A3: Contexto: es lo que pide la vacante — 'build and refine health-score and KPI frameworks'. En la entrevista explica POR QUÉ elegiste cada métrica y peso, y qué validarías con los CSMs (¿las cuentas Red realmente están en riesgo?).
N4: Pesos → | O4: 0.35 | P4: 0.25 | Q4: 0.2 | R4: 0.2 | S4: =SUM(O4:R4) -> 1 | T4: =IF(ROUND(S4,4)=1,"Pesos OK","Los pesos deben sumar 100%") -> Pesos OK | AF4: Resumen (usa los nombres definidos HS_Cat, HS_ARR, ...)
A6: AccountID | B6: AccountName | C6: Segment | D6: CSM_ID | E6: ARR_USD | F6: LicensedSeats | G6: ActiveUsers (LastMonth) | H6: Seat Utilization | I6: Logins últimos 3m | J6: Logins 3m previos | K6: Tendencia uso % | L6: Tickets P1/P2 abiertos | M6: NPS prom. 12m | N6: Días a renovación | O6: Score Adopción | P6: Score Tendencia | Q6: Score Soporte | R6: Score NPS | S6: HEALTH SCORE | T6: Categoría | U6: Alerta | V6: Rank (1 = peor) | X6: ✓H | Y6: ✓K | Z6: ✓L | AA6: ✓M | AB6: ✓S | AC6: ✓T | AD6: ✓V | AF6: Categoría | AG6: # Cuentas | AH6: ARR | AI6: Chk
A7: Dado | B7: XLOOKUP | C7: XLOOKUP | D7: XLOOKUP | E7: XLOOKUP | F7: XLOOKUP | G7: SUMIFS(tbl_Usage[ActiveUsers], ...[AccountID], A8, ...[Month], LastMonth) | H7: IFERROR(ROUND(G8/F8, 4), 0) | I7: SUMIFS(...[Logins], ..., [Month], ">="&EDATE(LastMonth,-2)) | J7: Meses −5 a −3: ">="&EDATE(LastMonth,-5) y "<"&EDATE(LastMonth,-2) | K7: IFERROR(ROUND(I8/J8-1, 4), 0) | L7: SUM(COUNTIFS(...[AccountID],A8, ...[ClosedDate],"", ...[Priority],{"P1","P2"})) | M7: IFERROR(AVERAGEIFS(tbl_NPS[Score], ..., [ResponseDate], ">"&EDATE(AsOfDate,-12)), "") | N7: XLOOKUP(RenewalDate) − AsOfDate | O7: IFS: ≥80%→100, ≥60%→75, ≥40%→50, ≥20%→25, si no 0 | P7: IFS: ≥10%→100, ≥0%→75, ≥−10%→50, ≥−25%→25, si no 0 | Q7: IFS: 0→100, 1→60, ≤3→30, si no 0 | R7: Sin NPS ("")→50; IFS: ≥9→100, ≥7→70, ≥5→40, si no 10 | S7: ROUND(SUMPRODUCT(O8:R8, $O$4:$R$4), 1) | T7: IFS: ≥75 Green, ≥50 Yellow, si no Red | U7: Red y renovación ≤180 días → "⚠ Riesgo renovación", si no "" | V7: RANK.EQ(S8, $S$8:$S$n, 1) | AF7: Green | AI7: =IF(ISBLANK(AG7),"",IF(IFERROR(ABS(AG7-'_key'!$A$1188)<=0.005,FALSE),"✓","✗")) -> 0
A8: ACC-0002 | X8: =IF(ISBLANK(H8),"",IF(IFERROR(ABS(H8-'_key'!$A$222)<=5e-05,FALSE),"✓","✗")) -> 0 | Y8: =IF(ISBLANK(K8),"",IF(IFERROR(ABS(K8-'_key'!$A$223)<=5e-05,FALSE),"✓","✗")) -> 0 | Z8: =IF(ISBLANK(L8),"",IF(IFERROR(ABS(L8-'_key'!$A$224)<=0.005,FALSE),"✓","✗")) -> 0 | AA8: =IF(ISBLANK(M8),"",IF(IFERROR(ABS(M8-'_key'!$A$225)<=0.005,FALSE),"✓","✗")) -> 0 | AB8: =IF(ISBLANK(S8),"",IF(IFERROR(ABS(S8-'_key'!$A$226)<=0.01,FALSE),"✓","✗")) -> 0 | AC8: =IF(ISBLANK(T8),"",IF(IFERROR(EXACT(T8,'_key'!$A$227),FALSE),"✓","✗")) -> 0 | AD8: =IF(ISBLANK(V8),"",IF(IFERROR(ABS(V8-'_key'!$A$228)<=0.005,FALSE),"✓","✗")) -> 0 | AF8: Yellow | AI8: =IF(ISBLANK(AG8),"",IF(IFERROR(ABS(AG8-'_key'!$A$1190)<=0.005,FALSE),"✓","✗")) -> 0
A9: ACC-0003 | X9: =IF(ISBLANK(H9),"",IF(IFERROR(ABS(H9-'_key'!$A$229)<=5e-05,FALSE),"✓","✗")) -> 0 | Y9: =IF(ISBLANK(K9),"",IF(IFERROR(ABS(K9-'_key'!$A$230)<=5e-05,FALSE),"✓","✗")) -> 0 | Z9: =IF(ISBLANK(L9),"",IF(IFERROR(ABS(L9-'_key'!$A$231)<=0.005,FALSE),"✓","✗")) -> 0 | AA9: =IF(ISBLANK(M9),"",IF(IFERROR(ABS(M9-'_key'!$A$232)<=0.005,FALSE),"✓","✗")) -> 0 | AB9: =IF(ISBLANK(S9),"",IF(IFERROR(ABS(S9-'_key'!$A$233)<=0.01,FALSE),"✓","✗")) -> 0 | AC9: =IF(ISBLANK(T9),"",IF(IFERROR(EXACT(T9,'_key'!$A$234),FALSE),"✓","✗")) -> 0 | AD9: =IF(ISBLANK(V9),"",IF(IFERROR(ABS(V9-'_key'!$A$235)<=0.005,FALSE),"✓","✗")) -> 0 | AF9: Red | AI9: =IF(ISBLANK(AG9),"",IF(IFERROR(ABS(AG9-'_key'!$A$1192)<=0.005,FALSE),"✓","✗")) -> 0
A10: ACC-0004 | X10: =IF(ISBLANK(H10),"",IF(IFERROR(ABS(H10-'_key'!$A$236)<=5e-05,FALSE),"✓","✗")) -> 0 | Y10: =IF(ISBLANK(K10),"",IF(IFERROR(ABS(K10-'_key'!$A$237)<=5e-05,FALSE),"✓","✗")) -> 0 | Z10: =IF(ISBLANK(L10),"",IF(IFERROR(ABS(L10-'_key'!$A$238)<=0.005,FALSE),"✓","✗")) -> 0 | AA10: =IF(ISBLANK(M10),"",IF(IFERROR(ABS(M10-'_key'!$A$239)<=0.005,FALSE),"✓","✗")) -> 0 | AB10: =IF(ISBLANK(S10),"",IF(IFERROR(ABS(S10-'_key'!$A$240)<=0.01,FALSE),"✓","✗")) -> 0 | AC10: =IF(ISBLANK(T10),"",IF(IFERROR(EXACT(T10,'_key'!$A$241),FALSE),"✓","✗")) -> 0 | AD10: =IF(ISBLANK(V10),"",IF(IFERROR(ABS(V10-'_key'!$A$242)<=0.005,FALSE),"✓","✗")) -> 0
A11: ACC-0005 | X11: =IF(ISBLANK(H11),"",IF(IFERROR(ABS(H11-'_key'!$A$243)<=5e-05,FALSE),"✓","✗")) -> 0 | Y11: =IF(ISBLANK(K11),"",IF(IFERROR(ABS(K11-'_key'!$A$244)<=5e-05,FALSE),"✓","✗")) -> 0 | Z11: =IF(ISBLANK(L11),"",IF(IFERROR(ABS(L11-'_key'!$A$245)<=0.005,FALSE),"✓","✗")) -> 0 | AA11: =IF(ISBLANK(M11),"",IF(IFERROR(ABS(M11-'_key'!$A$246)<=0.005,FALSE),"✓","✗")) -> 0 | AB11: =IF(ISBLANK(S11),"",IF(IFERROR(ABS(S11-'_key'!$A$247)<=0.01,FALSE),"✓","✗")) -> 0 | AC11: =IF(ISBLANK(T11),"",IF(IFERROR(EXACT(T11,'_key'!$A$248),FALSE),"✓","✗")) -> 0 | AD11: =IF(ISBLANK(V11),"",IF(IFERROR(ABS(V11-'_key'!$A$249)<=0.005,FALSE),"✓","✗")) -> 0 | AF11: Health score promedio | AI11: =IF(ISBLANK(AH11),"",IF(IFERROR(ABS(AH11-'_key'!$A$1194)<=0.05,FALSE),"✓","✗")) -> 0
A12: ACC-0006 | X12: =IF(ISBLANK(H12),"",IF(IFERROR(ABS(H12-'_key'!$A$250)<=5e-05,FALSE),"✓","✗")) -> 0 | Y12: =IF(ISBLANK(K12),"",IF(IFERROR(ABS(K12-'_key'!$A$251)<=5e-05,FALSE),"✓","✗")) -> 0 | Z12: =IF(ISBLANK(L12),"",IF(IFERROR(ABS(L12-'_key'!$A$252)<=0.005,FALSE),"✓","✗")) -> 0 | AA12: =IF(ISBLANK(M12),"",IF(IFERROR(ABS(M12-'_key'!$A$253)<=0.005,FALSE),"✓","✗")) -> 0 | AB12: =IF(ISBLANK(S12),"",IF(IFERROR(ABS(S12-'_key'!$A$254)<=0.01,FALSE),"✓","✗")) -> 0 | AC12: =IF(ISBLANK(T12),"",IF(IFERROR(EXACT(T12,'_key'!$A$255),FALSE),"✓","✗")) -> 0 | AD12: =IF(ISBLANK(V12),"",IF(IFERROR(ABS(V12-'_key'!$A$256)<=0.005,FALSE),"✓","✗")) -> 0 | AF12: ARR ponderado por health (prom.) | AI12: =IF(ISBLANK(AH12),"",IF(IFERROR(ABS(AH12-'_key'!$A$1195)<=0.05,FALSE),"✓","✗")) -> 0
A13: ACC-0007 | X13: =IF(ISBLANK(H13),"",IF(IFERROR(ABS(H13-'_key'!$A$257)<=5e-05,FALSE),"✓","✗")) -> 0 | Y13: =IF(ISBLANK(K13),"",IF(IFERROR(ABS(K13-'_key'!$A$258)<=5e-05,FALSE),"✓","✗")) -> 0 | Z13: =IF(ISBLANK(L13),"",IF(IFERROR(ABS(L13-'_key'!$A$259)<=0.005,FALSE),"✓","✗")) -> 0 | AA13: =IF(ISBLANK(M13),"",IF(IFERROR(ABS(M13-'_key'!$A$260)<=0.005,FALSE),"✓","✗")) -> 0 | AB13: =IF(ISBLANK(S13),"",IF(IFERROR(ABS(S13-'_key'!$A$261)<=0.01,FALSE),"✓","✗")) -> 0 | AC13: =IF(ISBLANK(T13),"",IF(IFERROR(EXACT(T13,'_key'!$A$262),FALSE),"✓","✗")) -> 0 | AD13: =IF(ISBLANK(V13),"",IF(IFERROR(ABS(V13-'_key'!$A$263)<=0.005,FALSE),"✓","✗")) -> 0 | AF13: # Cuentas con alerta de renovación | AI13: =IF(ISBLANK(AH13),"",IF(IFERROR(ABS(AH13-'_key'!$A$1196)<=0.05,FALSE),"✓","✗")) -> 0
A14: ACC-0008 | X14: =IF(ISBLANK(H14),"",IF(IFERROR(ABS(H14-'_key'!$A$264)<=5e-05,FALSE),"✓","✗")) -> 0 | Y14: =IF(ISBLANK(K14),"",IF(IFERROR(ABS(K14-'_key'!$A$265)<=5e-05,FALSE),"✓","✗")) -> 0 | Z14: =IF(ISBLANK(L14),"",IF(IFERROR(ABS(L14-'_key'!$A$266)<=0.005,FALSE),"✓","✗")) -> 0 | AA14: =IF(ISBLANK(M14),"",IF(IFERROR(EXACT(M14,'_key'!$A$267),FALSE),"✓","✗")) -> 0 | AB14: =IF(ISBLANK(S14),"",IF(IFERROR(ABS(S14-'_key'!$A$268)<=0.01,FALSE),"✓","✗")) -> 0 | AC14: =IF(ISBLANK(T14),"",IF(IFERROR(EXACT(T14,'_key'!$A$269),FALSE),"✓","✗")) -> 0 | AD14: =IF(ISBLANK(V14),"",IF(IFERROR(ABS(V14-'_key'!$A$270)<=0.005,FALSE),"✓","✗")) -> 0 | AF14: ARR en riesgo (Red, ≤180 días) | AI14: =IF(ISBLANK(AH14),"",IF(IFERROR(ABS(AH14-'_key'!$A$1197)<=0.05,FALSE),"✓","✗")) -> 0
A15: ACC-0009 | X15: =IF(ISBLANK(H15),"",IF(IFERROR(ABS(H15-'_key'!$A$271)<=5e-05,FALSE),"✓","✗")) -> 0 | Y15: =IF(ISBLANK(K15),"",IF(IFERROR(ABS(K15-'_key'!$A$272)<=5e-05,FALSE),"✓","✗")) -> 0 | Z15: =IF(ISBLANK(L15),"",IF(IFERROR(ABS(L15-'_key'!$A$273)<=0.005,FALSE),"✓","✗")) -> 0 | AA15: =IF(ISBLANK(M15),"",IF(IFERROR(ABS(M15-'_key'!$A$274)<=0.005,FALSE),"✓","✗")) -> 0 | AB15: =IF(ISBLANK(S15),"",IF(IFERROR(ABS(S15-'_key'!$A$275)<=0.01,FALSE),"✓","✗")) -> 0 | AC15: =IF(ISBLANK(T15),"",IF(IFERROR(EXACT(T15,'_key'!$A$276),FALSE),"✓","✗")) -> 0 | AD15: =IF(ISBLANK(V15),"",IF(IFERROR(ABS(V15-'_key'!$A$277)<=0.005,FALSE),"✓","✗")) -> 0
A16: ACC-0010 | X16: =IF(ISBLANK(H16),"",IF(IFERROR(ABS(H16-'_key'!$A$278)<=5e-05,FALSE),"✓","✗")) -> 0 | Y16: =IF(ISBLANK(K16),"",IF(IFERROR(ABS(K16-'_key'!$A$279)<=5e-05,FALSE),"✓","✗")) -> 0 | Z16: =IF(ISBLANK(L16),"",IF(IFERROR(ABS(L16-'_key'!$A$280)<=0.005,FALSE),"✓","✗")) -> 0 | AA16: =IF(ISBLANK(M16),"",IF(IFERROR(ABS(M16-'_key'!$A$281)<=0.005,FALSE),"✓","✗")) -> 0 | AB16: =IF(ISBLANK(S16),"",IF(IFERROR(ABS(S16-'_key'!$A$282)<=0.01,FALSE),"✓","✗")) -> 0 | AC16: =IF(ISBLANK(T16),"",IF(IFERROR(EXACT(T16,'_key'!$A$283),FALSE),"✓","✗")) -> 0 | AD16: =IF(ISBLANK(V16),"",IF(IFERROR(ABS(V16-'_key'!$A$284)<=0.005,FALSE),"✓","✗")) -> 0 | AF16: ✓ de la columna ARR (G/Y/R) → | AI16: =IF(ISBLANK(AH7),"",IF(IFERROR(ABS(AH7-'_key'!$A$1189)<=0.005,FALSE),"✓","✗")) -> 0
A17: ACC-0011 | X17: =IF(ISBLANK(H17),"",IF(IFERROR(ABS(H17-'_key'!$A$285)<=5e-05,FALSE),"✓","✗")) -> 0 | Y17: =IF(ISBLANK(K17),"",IF(IFERROR(ABS(K17-'_key'!$A$286)<=5e-05,FALSE),"✓","✗")) -> 0 | Z17: =IF(ISBLANK(L17),"",IF(IFERROR(ABS(L17-'_key'!$A$287)<=0.005,FALSE),"✓","✗")) -> 0 | AA17: =IF(ISBLANK(M17),"",IF(IFERROR(EXACT(M17,'_key'!$A$288),FALSE),"✓","✗")) -> 0 | AB17: =IF(ISBLANK(S17),"",IF(IFERROR(ABS(S17-'_key'!$A$289)<=0.01,FALSE),"✓","✗")) -> 0 | AC17: =IF(ISBLANK(T17),"",IF(IFERROR(EXACT(T17,'_key'!$A$290),FALSE),"✓","✗")) -> 0 | AD17: =IF(ISBLANK(V17),"",IF(IFERROR(ABS(V17-'_key'!$A$291)<=0.005,FALSE),"✓","✗")) -> 0 | AI17: =IF(ISBLANK(AH8),"",IF(IFERROR(ABS(AH8-'_key'!$A$1191)<=0.005,FALSE),"✓","✗")) -> 0
A18: ACC-0012 | X18: =IF(ISBLANK(H18),"",IF(IFERROR(ABS(H18-'_key'!$A$292)<=5e-05,FALSE),"✓","✗")) -> 0 | Y18: =IF(ISBLANK(K18),"",IF(IFERROR(ABS(K18-'_key'!$A$293)<=5e-05,FALSE),"✓","✗")) -> 0 | Z18: =IF(ISBLANK(L18),"",IF(IFERROR(ABS(L18-'_key'!$A$294)<=0.005,FALSE),"✓","✗")) -> 0 | AA18: =IF(ISBLANK(M18),"",IF(IFERROR(ABS(M18-'_key'!$A$295)<=0.005,FALSE),"✓","✗")) -> 0 | AB18: =IF(ISBLANK(S18),"",IF(IFERROR(ABS(S18-'_key'!$A$296)<=0.01,FALSE),"✓","✗")) -> 0 | AC18: =IF(ISBLANK(T18),"",IF(IFERROR(EXACT(T18,'_key'!$A$297),FALSE),"✓","✗")) -> 0 | AD18: =IF(ISBLANK(V18),"",IF(IFERROR(ABS(V18-'_key'!$A$298)<=0.005,FALSE),"✓","✗")) -> 0 | AI18: =IF(ISBLANK(AH9),"",IF(IFERROR(ABS(AH9-'_key'!$A$1193)<=0.005,FALSE),"✓","✗")) -> 0
A19: ACC-0013 | X19: =IF(ISBLANK(H19),"",IF(IFERROR(ABS(H19-'_key'!$A$299)<=5e-05,FALSE),"✓","✗")) -> 0 | Y19: =IF(ISBLANK(K19),"",IF(IFERROR(ABS(K19-'_key'!$A$300)<=5e-05,FALSE),"✓","✗")) -> 0 | Z19: =IF(ISBLANK(L19),"",IF(IFERROR(ABS(L19-'_key'!$A$301)<=0.005,FALSE),"✓","✗")) -> 0 | AA19: =IF(ISBLANK(M19),"",IF(IFERROR(EXACT(M19,'_key'!$A$302),FALSE),"✓","✗")) -> 0 | AB19: =IF(ISBLANK(S19),"",IF(IFERROR(ABS(S19-'_key'!$A$303)<=0.01,FALSE),"✓","✗")) -> 0 | AC19: =IF(ISBLANK(T19),"",IF(IFERROR(EXACT(T19,'_key'!$A$304),FALSE),"✓","✗")) -> 0 | AD19: =IF(ISBLANK(V19),"",IF(IFERROR(ABS(V19-'_key'!$A$305)<=0.005,FALSE),"✓","✗")) -> 0
A20: ACC-0014 | X20: =IF(ISBLANK(H20),"",IF(IFERROR(ABS(H20-'_key'!$A$306)<=5e-05,FALSE),"✓","✗")) -> 0 | Y20: =IF(ISBLANK(K20),"",IF(IFERROR(ABS(K20-'_key'!$A$307)<=5e-05,FALSE),"✓","✗")) -> 0 | Z20: =IF(ISBLANK(L20),"",IF(IFERROR(ABS(L20-'_key'!$A$308)<=0.005,FALSE),"✓","✗")) -> 0 | AA20: =IF(ISBLANK(M20),"",IF(IFERROR(ABS(M20-'_key'!$A$309)<=0.005,FALSE),"✓","✗")) -> 0 | AB20: =IF(ISBLANK(S20),"",IF(IFERROR(ABS(S20-'_key'!$A$310)<=0.01,FALSE),"✓","✗")) -> 0 | AC20: =IF(ISBLANK(T20),"",IF(IFERROR(EXACT(T20,'_key'!$A$311),FALSE),"✓","✗")) -> 0 | AD20: =IF(ISBLANK(V20),"",IF(IFERROR(ABS(V20-'_key'!$A$312)<=0.005,FALSE),"✓","✗")) -> 0
A21: ACC-0015 | X21: =IF(ISBLANK(H21),"",IF(IFERROR(ABS(H21-'_key'!$A$313)<=5e-05,FALSE),"✓","✗")) -> 0 | Y21: =IF(ISBLANK(K21),"",IF(IFERROR(ABS(K21-'_key'!$A$314)<=5e-05,FALSE),"✓","✗")) -> 0 | Z21: =IF(ISBLANK(L21),"",IF(IFERROR(ABS(L21-'_key'!$A$315)<=0.005,FALSE),"✓","✗")) -> 0 | AA21: =IF(ISBLANK(M21),"",IF(IFERROR(ABS(M21-'_key'!$A$316)<=0.005,FALSE),"✓","✗")) -> 0 | AB21: =IF(ISBLANK(S21),"",IF(IFERROR(ABS(S21-'_key'!$A$317)<=0.01,FALSE),"✓","✗")) -> 0 | AC21: =IF(ISBLANK(T21),"",IF(IFERROR(EXACT(T21,'_key'!$A$318),FALSE),"✓","✗")) -> 0 | AD21: =IF(ISBLANK(V21),"",IF(IFERROR(ABS(V21-'_key'!$A$319)<=0.005,FALSE),"✓","✗")) -> 0
A22: ACC-0016 | X22: =IF(ISBLANK(H22),"",IF(IFERROR(ABS(H22-'_key'!$A$320)<=5e-05,FALSE),"✓","✗")) -> 0 | Y22: =IF(ISBLANK(K22),"",IF(IFERROR(ABS(K22-'_key'!$A$321)<=5e-05,FALSE),"✓","✗")) -> 0 | Z22: =IF(ISBLANK(L22),"",IF(IFERROR(ABS(L22-'_key'!$A$322)<=0.005,FALSE),"✓","✗")) -> 0 | AA22: =IF(ISBLANK(M22),"",IF(IFERROR(ABS(M22-'_key'!$A$323)<=0.005,FALSE),"✓","✗")) -> 0 | AB22: =IF(ISBLANK(S22),"",IF(IFERROR(ABS(S22-'_key'!$A$324)<=0.01,FALSE),"✓","✗")) -> 0 | AC22: =IF(ISBLANK(T22),"",IF(IFERROR(EXACT(T22,'_key'!$A$325),FALSE),"✓","✗")) -> 0 | AD22: =IF(ISBLANK(V22),"",IF(IFERROR(ABS(V22-'_key'!$A$326)<=0.005,FALSE),"✓","✗")) -> 0
A23: ACC-0017 | X23: =IF(ISBLANK(H23),"",IF(IFERROR(ABS(H23-'_key'!$A$327)<=5e-05,FALSE),"✓","✗")) -> 0 | Y23: =IF(ISBLANK(K23),"",IF(IFERROR(ABS(K23-'_key'!$A$328)<=5e-05,FALSE),"✓","✗")) -> 0 | Z23: =IF(ISBLANK(L23),"",IF(IFERROR(ABS(L23-'_key'!$A$329)<=0.005,FALSE),"✓","✗")) -> 0 | AA23: =IF(ISBLANK(M23),"",IF(IFERROR(ABS(M23-'_key'!$A$330)<=0.005,FALSE),"✓","✗")) -> 0 | AB23: =IF(ISBLANK(S23),"",IF(IFERROR(ABS(S23-'_key'!$A$331)<=0.01,FALSE),"✓","✗")) -> 0 | AC23: =IF(ISBLANK(T23),"",IF(IFERROR(EXACT(T23,'_key'!$A$332),FALSE),"✓","✗")) -> 0 | AD23: =IF(ISBLANK(V23),"",IF(IFERROR(ABS(V23-'_key'!$A$333)<=0.005,FALSE),"✓","✗")) -> 0
A24: ACC-0018 | X24: =IF(ISBLANK(H24),"",IF(IFERROR(ABS(H24-'_key'!$A$334)<=5e-05,FALSE),"✓","✗")) -> 0 | Y24: =IF(ISBLANK(K24),"",IF(IFERROR(ABS(K24-'_key'!$A$335)<=5e-05,FALSE),"✓","✗")) -> 0 | Z24: =IF(ISBLANK(L24),"",IF(IFERROR(ABS(L24-'_key'!$A$336)<=0.005,FALSE),"✓","✗")) -> 0 | AA24: =IF(ISBLANK(M24),"",IF(IFERROR(ABS(M24-'_key'!$A$337)<=0.005,FALSE),"✓","✗")) -> 0 | AB24: =IF(ISBLANK(S24),"",IF(IFERROR(ABS(S24-'_key'!$A$338)<=0.01,FALSE),"✓","✗")) -> 0 | AC24: =IF(ISBLANK(T24),"",IF(IFERROR(EXACT(T24,'_key'!$A$339),FALSE),"✓","✗")) -> 0 | AD24: =IF(ISBLANK(V24),"",IF(IFERROR(ABS(V24-'_key'!$A$340)<=0.005,FALSE),"✓","✗")) -> 0
A25: ACC-0019 | X25: =IF(ISBLANK(H25),"",IF(IFERROR(ABS(H25-'_key'!$A$341)<=5e-05,FALSE),"✓","✗")) -> 0 | Y25: =IF(ISBLANK(K25),"",IF(IFERROR(ABS(K25-'_key'!$A$342)<=5e-05,FALSE),"✓","✗")) -> 0 | Z25: =IF(ISBLANK(L25),"",IF(IFERROR(ABS(L25-'_key'!$A$343)<=0.005,FALSE),"✓","✗")) -> 0 | AA25: =IF(ISBLANK(M25),"",IF(IFERROR(ABS(M25-'_key'!$A$344)<=0.005,FALSE),"✓","✗")) -> 0 | AB25: =IF(ISBLANK(S25),"",IF(IFERROR(ABS(S25-'_key'!$A$345)<=0.01,FALSE),"✓","✗")) -> 0 | AC25: =IF(ISBLANK(T25),"",IF(IFERROR(EXACT(T25,'_key'!$A$346),FALSE),"✓","✗")) -> 0 | AD25: =IF(ISBLANK(V25),"",IF(IFERROR(ABS(V25-'_key'!$A$347)<=0.005,FALSE),"✓","✗")) -> 0
A26: ACC-0020 | X26: =IF(ISBLANK(H26),"",IF(IFERROR(ABS(H26-'_key'!$A$348)<=5e-05,FALSE),"✓","✗")) -> 0 | Y26: =IF(ISBLANK(K26),"",IF(IFERROR(ABS(K26-'_key'!$A$349)<=5e-05,FALSE),"✓","✗")) -> 0 | Z26: =IF(ISBLANK(L26),"",IF(IFERROR(ABS(L26-'_key'!$A$350)<=0.005,FALSE),"✓","✗")) -> 0 | AA26: =IF(ISBLANK(M26),"",IF(IFERROR(EXACT(M26,'_key'!$A$351),FALSE),"✓","✗")) -> 0 | AB26: =IF(ISBLANK(S26),"",IF(IFERROR(ABS(S26-'_key'!$A$352)<=0.01,FALSE),"✓","✗")) -> 0 | AC26: =IF(ISBLANK(T26),"",IF(IFERROR(EXACT(T26,'_key'!$A$353),FALSE),"✓","✗")) -> 0 | AD26: =IF(ISBLANK(V26),"",IF(IFERROR(ABS(V26-'_key'!$A$354)<=0.005,FALSE),"✓","✗")) -> 0
A27: ACC-0021 | X27: =IF(ISBLANK(H27),"",IF(IFERROR(ABS(H27-'_key'!$A$355)<=5e-05,FALSE),"✓","✗")) -> 0 | Y27: =IF(ISBLANK(K27),"",IF(IFERROR(ABS(K27-'_key'!$A$356)<=5e-05,FALSE),"✓","✗")) -> 0 | Z27: =IF(ISBLANK(L27),"",IF(IFERROR(ABS(L27-'_key'!$A$357)<=0.005,FALSE),"✓","✗")) -> 0 | AA27: =IF(ISBLANK(M27),"",IF(IFERROR(ABS(M27-'_key'!$A$358)<=0.005,FALSE),"✓","✗")) -> 0 | AB27: =IF(ISBLANK(S27),"",IF(IFERROR(ABS(S27-'_key'!$A$359)<=0.01,FALSE),"✓","✗")) -> 0 | AC27: =IF(ISBLANK(T27),"",IF(IFERROR(EXACT(T27,'_key'!$A$360),FALSE),"✓","✗")) -> 0 | AD27: =IF(ISBLANK(V27),"",IF(IFERROR(ABS(V27-'_key'!$A$361)<=0.005,FALSE),"✓","✗")) -> 0
A28: ACC-0022 | X28: =IF(ISBLANK(H28),"",IF(IFERROR(ABS(H28-'_key'!$A$362)<=5e-05,FALSE),"✓","✗")) -> 0 | Y28: =IF(ISBLANK(K28),"",IF(IFERROR(ABS(K28-'_key'!$A$363)<=5e-05,FALSE),"✓","✗")) -> 0 | Z28: =IF(ISBLANK(L28),"",IF(IFERROR(ABS(L28-'_key'!$A$364)<=0.005,FALSE),"✓","✗")) -> 0 | AA28: =IF(ISBLANK(M28),"",IF(IFERROR(ABS(M28-'_key'!$A$365)<=0.005,FALSE),"✓","✗")) -> 0 | AB28: =IF(ISBLANK(S28),"",IF(IFERROR(ABS(S28-'_key'!$A$366)<=0.01,FALSE),"✓","✗")) -> 0 | AC28: =IF(ISBLANK(T28),"",IF(IFERROR(EXACT(T28,'_key'!$A$367),FALSE),"✓","✗")) -> 0 | AD28: =IF(ISBLANK(V28),"",IF(IFERROR(ABS(V28-'_key'!$A$368)<=0.005,FALSE),"✓","✗")) -> 0
A29: ACC-0024 | X29: =IF(ISBLANK(H29),"",IF(IFERROR(ABS(H29-'_key'!$A$369)<=5e-05,FALSE),"✓","✗")) -> 0 | Y29: =IF(ISBLANK(K29),"",IF(IFERROR(ABS(K29-'_key'!$A$370)<=5e-05,FALSE),"✓","✗")) -> 0 | Z29: =IF(ISBLANK(L29),"",IF(IFERROR(ABS(L29-'_key'!$A$371)<=0.005,FALSE),"✓","✗")) -> 0 | AA29: =IF(ISBLANK(M29),"",IF(IFERROR(ABS(M29-'_key'!$A$372)<=0.005,FALSE),"✓","✗")) -> 0 | AB29: =IF(ISBLANK(S29),"",IF(IFERROR(ABS(S29-'_key'!$A$373)<=0.01,FALSE),"✓","✗")) -> 0 | AC29: =IF(ISBLANK(T29),"",IF(IFERROR(EXACT(T29,'_key'!$A$374),FALSE),"✓","✗")) -> 0 | AD29: =IF(ISBLANK(V29),"",IF(IFERROR(ABS(V29-'_key'!$A$375)<=0.005,FALSE),"✓","✗")) -> 0
A30: ACC-0025 | X30: =IF(ISBLANK(H30),"",IF(IFERROR(ABS(H30-'_key'!$A$376)<=5e-05,FALSE),"✓","✗")) -> 0 | Y30: =IF(ISBLANK(K30),"",IF(IFERROR(ABS(K30-'_key'!$A$377)<=5e-05,FALSE),"✓","✗")) -> 0 | Z30: =IF(ISBLANK(L30),"",IF(IFERROR(ABS(L30-'_key'!$A$378)<=0.005,FALSE),"✓","✗")) -> 0 | AA30: =IF(ISBLANK(M30),"",IF(IFERROR(ABS(M30-'_key'!$A$379)<=0.005,FALSE),"✓","✗")) -> 0 | AB30: =IF(ISBLANK(S30),"",IF(IFERROR(ABS(S30-'_key'!$A$380)<=0.01,FALSE),"✓","✗")) -> 0 | AC30: =IF(ISBLANK(T30),"",IF(IFERROR(EXACT(T30,'_key'!$A$381),FALSE),"✓","✗")) -> 0 | AD30: =IF(ISBLANK(V30),"",IF(IFERROR(ABS(V30-'_key'!$A$382)<=0.005,FALSE),"✓","✗")) -> 0
A31: ACC-0026 | X31: =IF(ISBLANK(H31),"",IF(IFERROR(ABS(H31-'_key'!$A$383)<=5e-05,FALSE),"✓","✗")) -> 0 | Y31: =IF(ISBLANK(K31),"",IF(IFERROR(ABS(K31-'_key'!$A$384)<=5e-05,FALSE),"✓","✗")) -> 0 | Z31: =IF(ISBLANK(L31),"",IF(IFERROR(ABS(L31-'_key'!$A$385)<=0.005,FALSE),"✓","✗")) -> 0 | AA31: =IF(ISBLANK(M31),"",IF(IFERROR(ABS(M31-'_key'!$A$386)<=0.005,FALSE),"✓","✗")) -> 0 | AB31: =IF(ISBLANK(S31),"",IF(IFERROR(ABS(S31-'_key'!$A$387)<=0.01,FALSE),"✓","✗")) -> 0 | AC31: =IF(ISBLANK(T31),"",IF(IFERROR(EXACT(T31,'_key'!$A$388),FALSE),"✓","✗")) -> 0 | AD31: =IF(ISBLANK(V31),"",IF(IFERROR(ABS(V31-'_key'!$A$389)<=0.005,FALSE),"✓","✗")) -> 0
A32: ACC-0027 | X32: =IF(ISBLANK(H32),"",IF(IFERROR(ABS(H32-'_key'!$A$390)<=5e-05,FALSE),"✓","✗")) -> 0 | Y32: =IF(ISBLANK(K32),"",IF(IFERROR(ABS(K32-'_key'!$A$391)<=5e-05,FALSE),"✓","✗")) -> 0 | Z32: =IF(ISBLANK(L32),"",IF(IFERROR(ABS(L32-'_key'!$A$392)<=0.005,FALSE),"✓","✗")) -> 0 | AA32: =IF(ISBLANK(M32),"",IF(IFERROR(EXACT(M32,'_key'!$A$393),FALSE),"✓","✗")) -> 0 | AB32: =IF(ISBLANK(S32),"",IF(IFERROR(ABS(S32-'_key'!$A$394)<=0.01,FALSE),"✓","✗")) -> 0 | AC32: =IF(ISBLANK(T32),"",IF(IFERROR(EXACT(T32,'_key'!$A$395),FALSE),"✓","✗")) -> 0 | AD32: =IF(ISBLANK(V32),"",IF(IFERROR(ABS(V32-'_key'!$A$396)<=0.005,FALSE),"✓","✗")) -> 0
A33: ACC-0029 | X33: =IF(ISBLANK(H33),"",IF(IFERROR(ABS(H33-'_key'!$A$397)<=5e-05,FALSE),"✓","✗")) -> 0 | Y33: =IF(ISBLANK(K33),"",IF(IFERROR(ABS(K33-'_key'!$A$398)<=5e-05,FALSE),"✓","✗")) -> 0 | Z33: =IF(ISBLANK(L33),"",IF(IFERROR(ABS(L33-'_key'!$A$399)<=0.005,FALSE),"✓","✗")) -> 0 | AA33: =IF(ISBLANK(M33),"",IF(IFERROR(ABS(M33-'_key'!$A$400)<=0.005,FALSE),"✓","✗")) -> 0 | AB33: =IF(ISBLANK(S33),"",IF(IFERROR(ABS(S33-'_key'!$A$401)<=0.01,FALSE),"✓","✗")) -> 0 | AC33: =IF(ISBLANK(T33),"",IF(IFERROR(EXACT(T33,'_key'!$A$402),FALSE),"✓","✗")) -> 0 | AD33: =IF(ISBLANK(V33),"",IF(IFERROR(ABS(V33-'_key'!$A$403)<=0.005,FALSE),"✓","✗")) -> 0
A34: ACC-0030 | X34: =IF(ISBLANK(H34),"",IF(IFERROR(ABS(H34-'_key'!$A$404)<=5e-05,FALSE),"✓","✗")) -> 0 | Y34: =IF(ISBLANK(K34),"",IF(IFERROR(ABS(K34-'_key'!$A$405)<=5e-05,FALSE),"✓","✗")) -> 0 | Z34: =IF(ISBLANK(L34),"",IF(IFERROR(ABS(L34-'_key'!$A$406)<=0.005,FALSE),"✓","✗")) -> 0 | AA34: =IF(ISBLANK(M34),"",IF(IFERROR(ABS(M34-'_key'!$A$407)<=0.005,FALSE),"✓","✗")) -> 0 | AB34: =IF(ISBLANK(S34),"",IF(IFERROR(ABS(S34-'_key'!$A$408)<=0.01,FALSE),"✓","✗")) -> 0 | AC34: =IF(ISBLANK(T34),"",IF(IFERROR(EXACT(T34,'_key'!$A$409),FALSE),"✓","✗")) -> 0 | AD34: =IF(ISBLANK(V34),"",IF(IFERROR(ABS(V34-'_key'!$A$410)<=0.005,FALSE),"✓","✗")) -> 0
A35: ACC-0031 | X35: =IF(ISBLANK(H35),"",IF(IFERROR(ABS(H35-'_key'!$A$411)<=5e-05,FALSE),"✓","✗")) -> 0 | Y35: =IF(ISBLANK(K35),"",IF(IFERROR(ABS(K35-'_key'!$A$412)<=5e-05,FALSE),"✓","✗")) -> 0 | Z35: =IF(ISBLANK(L35),"",IF(IFERROR(ABS(L35-'_key'!$A$413)<=0.005,FALSE),"✓","✗")) -> 0 | AA35: =IF(ISBLANK(M35),"",IF(IFERROR(EXACT(M35,'_key'!$A$414),FALSE),"✓","✗")) -> 0 | AB35: =IF(ISBLANK(S35),"",IF(IFERROR(ABS(S35-'_key'!$A$415)<=0.01,FALSE),"✓","✗")) -> 0 | AC35: =IF(ISBLANK(T35),"",IF(IFERROR(EXACT(T35,'_key'!$A$416),FALSE),"✓","✗")) -> 0 | AD35: =IF(ISBLANK(V35),"",IF(IFERROR(ABS(V35-'_key'!$A$417)<=0.005,FALSE),"✓","✗")) -> 0
A36: ACC-0032 | X36: =IF(ISBLANK(H36),"",IF(IFERROR(ABS(H36-'_key'!$A$418)<=5e-05,FALSE),"✓","✗")) -> 0 | Y36: =IF(ISBLANK(K36),"",IF(IFERROR(ABS(K36-'_key'!$A$419)<=5e-05,FALSE),"✓","✗")) -> 0 | Z36: =IF(ISBLANK(L36),"",IF(IFERROR(ABS(L36-'_key'!$A$420)<=0.005,FALSE),"✓","✗")) -> 0 | AA36: =IF(ISBLANK(M36),"",IF(IFERROR(ABS(M36-'_key'!$A$421)<=0.005,FALSE),"✓","✗")) -> 0 | AB36: =IF(ISBLANK(S36),"",IF(IFERROR(ABS(S36-'_key'!$A$422)<=0.01,FALSE),"✓","✗")) -> 0 | AC36: =IF(ISBLANK(T36),"",IF(IFERROR(EXACT(T36,'_key'!$A$423),FALSE),"✓","✗")) -> 0 | AD36: =IF(ISBLANK(V36),"",IF(IFERROR(ABS(V36-'_key'!$A$424)<=0.005,FALSE),"✓","✗")) -> 0
A37: ACC-0033 | X37: =IF(ISBLANK(H37),"",IF(IFERROR(ABS(H37-'_key'!$A$425)<=5e-05,FALSE),"✓","✗")) -> 0 | Y37: =IF(ISBLANK(K37),"",IF(IFERROR(ABS(K37-'_key'!$A$426)<=5e-05,FALSE),"✓","✗")) -> 0 | Z37: =IF(ISBLANK(L37),"",IF(IFERROR(ABS(L37-'_key'!$A$427)<=0.005,FALSE),"✓","✗")) -> 0 | AA37: =IF(ISBLANK(M37),"",IF(IFERROR(EXACT(M37,'_key'!$A$428),FALSE),"✓","✗")) -> 0 | AB37: =IF(ISBLANK(S37),"",IF(IFERROR(ABS(S37-'_key'!$A$429)<=0.01,FALSE),"✓","✗")) -> 0 | AC37: =IF(ISBLANK(T37),"",IF(IFERROR(EXACT(T37,'_key'!$A$430),FALSE),"✓","✗")) -> 0 | AD37: =IF(ISBLANK(V37),"",IF(IFERROR(ABS(V37-'_key'!$A$431)<=0.005,FALSE),"✓","✗")) -> 0
A38: ACC-0034 | X38: =IF(ISBLANK(H38),"",IF(IFERROR(ABS(H38-'_key'!$A$432)<=5e-05,FALSE),"✓","✗")) -> 0 | Y38: =IF(ISBLANK(K38),"",IF(IFERROR(ABS(K38-'_key'!$A$433)<=5e-05,FALSE),"✓","✗")) -> 0 | Z38: =IF(ISBLANK(L38),"",IF(IFERROR(ABS(L38-'_key'!$A$434)<=0.005,FALSE),"✓","✗")) -> 0 | AA38: =IF(ISBLANK(M38),"",IF(IFERROR(ABS(M38-'_key'!$A$435)<=0.005,FALSE),"✓","✗")) -> 0 | AB38: =IF(ISBLANK(S38),"",IF(IFERROR(ABS(S38-'_key'!$A$436)<=0.01,FALSE),"✓","✗")) -> 0 | AC38: =IF(ISBLANK(T38),"",IF(IFERROR(EXACT(T38,'_key'!$A$437),FALSE),"✓","✗")) -> 0 | AD38: =IF(ISBLANK(V38),"",IF(IFERROR(ABS(V38-'_key'!$A$438)<=0.005,FALSE),"✓","✗")) -> 0
A39: ACC-0035 | X39: =IF(ISBLANK(H39),"",IF(IFERROR(ABS(H39-'_key'!$A$439)<=5e-05,FALSE),"✓","✗")) -> 0 | Y39: =IF(ISBLANK(K39),"",IF(IFERROR(ABS(K39-'_key'!$A$440)<=5e-05,FALSE),"✓","✗")) -> 0 | Z39: =IF(ISBLANK(L39),"",IF(IFERROR(ABS(L39-'_key'!$A$441)<=0.005,FALSE),"✓","✗")) -> 0 | AA39: =IF(ISBLANK(M39),"",IF(IFERROR(EXACT(M39,'_key'!$A$442),FALSE),"✓","✗")) -> 0 | AB39: =IF(ISBLANK(S39),"",IF(IFERROR(ABS(S39-'_key'!$A$443)<=0.01,FALSE),"✓","✗")) -> 0 | AC39: =IF(ISBLANK(T39),"",IF(IFERROR(EXACT(T39,'_key'!$A$444),FALSE),"✓","✗")) -> 0 | AD39: =IF(ISBLANK(V39),"",IF(IFERROR(ABS(V39-'_key'!$A$445)<=0.005,FALSE),"✓","✗")) -> 0
A40: ACC-0036 | X40: =IF(ISBLANK(H40),"",IF(IFERROR(ABS(H40-'_key'!$A$446)<=5e-05,FALSE),"✓","✗")) -> 0 | Y40: =IF(ISBLANK(K40),"",IF(IFERROR(ABS(K40-'_key'!$A$447)<=5e-05,FALSE),"✓","✗")) -> 0 | Z40: =IF(ISBLANK(L40),"",IF(IFERROR(ABS(L40-'_key'!$A$448)<=0.005,FALSE),"✓","✗")) -> 0 | AA40: =IF(ISBLANK(M40),"",IF(IFERROR(EXACT(M40,'_key'!$A$449),FALSE),"✓","✗")) -> 0 | AB40: =IF(ISBLANK(S40),"",IF(IFERROR(ABS(S40-'_key'!$A$450)<=0.01,FALSE),"✓","✗")) -> 0 | AC40: =IF(ISBLANK(T40),"",IF(IFERROR(EXACT(T40,'_key'!$A$451),FALSE),"✓","✗")) -> 0 | AD40: =IF(ISBLANK(V40),"",IF(IFERROR(ABS(V40-'_key'!$A$452)<=0.005,FALSE),"✓","✗")) -> 0
A41: ACC-0037 | X41: =IF(ISBLANK(H41),"",IF(IFERROR(ABS(H41-'_key'!$A$453)<=5e-05,FALSE),"✓","✗")) -> 0 | Y41: =IF(ISBLANK(K41),"",IF(IFERROR(ABS(K41-'_key'!$A$454)<=5e-05,FALSE),"✓","✗")) -> 0 | Z41: =IF(ISBLANK(L41),"",IF(IFERROR(ABS(L41-'_key'!$A$455)<=0.005,FALSE),"✓","✗")) -> 0 | AA41: =IF(ISBLANK(M41),"",IF(IFERROR(EXACT(M41,'_key'!$A$456),FALSE),"✓","✗")) -> 0 | AB41: =IF(ISBLANK(S41),"",IF(IFERROR(ABS(S41-'_key'!$A$457)<=0.01,FALSE),"✓","✗")) -> 0 | AC41: =IF(ISBLANK(T41),"",IF(IFERROR(EXACT(T41,'_key'!$A$458),FALSE),"✓","✗")) -> 0 | AD41: =IF(ISBLANK(V41),"",IF(IFERROR(ABS(V41-'_key'!$A$459)<=0.005,FALSE),"✓","✗")) -> 0
A42: ACC-0038 | X42: =IF(ISBLANK(H42),"",IF(IFERROR(ABS(H42-'_key'!$A$460)<=5e-05,FALSE),"✓","✗")) -> 0 | Y42: =IF(ISBLANK(K42),"",IF(IFERROR(ABS(K42-'_key'!$A$461)<=5e-05,FALSE),"✓","✗")) -> 0 | Z42: =IF(ISBLANK(L42),"",IF(IFERROR(ABS(L42-'_key'!$A$462)<=0.005,FALSE),"✓","✗")) -> 0 | AA42: =IF(ISBLANK(M42),"",IF(IFERROR(ABS(M42-'_key'!$A$463)<=0.005,FALSE),"✓","✗")) -> 0 | AB42: =IF(ISBLANK(S42),"",IF(IFERROR(ABS(S42-'_key'!$A$464)<=0.01,FALSE),"✓","✗")) -> 0 | AC42: =IF(ISBLANK(T42),"",IF(IFERROR(EXACT(T42,'_key'!$A$465),FALSE),"✓","✗")) -> 0 | AD42: =IF(ISBLANK(V42),"",IF(IFERROR(ABS(V42-'_key'!$A$466)<=0.005,FALSE),"✓","✗")) -> 0
A43: ACC-0039 | X43: =IF(ISBLANK(H43),"",IF(IFERROR(ABS(H43-'_key'!$A$467)<=5e-05,FALSE),"✓","✗")) -> 0 | Y43: =IF(ISBLANK(K43),"",IF(IFERROR(ABS(K43-'_key'!$A$468)<=5e-05,FALSE),"✓","✗")) -> 0 | Z43: =IF(ISBLANK(L43),"",IF(IFERROR(ABS(L43-'_key'!$A$469)<=0.005,FALSE),"✓","✗")) -> 0 | AA43: =IF(ISBLANK(M43),"",IF(IFERROR(ABS(M43-'_key'!$A$470)<=0.005,FALSE),"✓","✗")) -> 0 | AB43: =IF(ISBLANK(S43),"",IF(IFERROR(ABS(S43-'_key'!$A$471)<=0.01,FALSE),"✓","✗")) -> 0 | AC43: =IF(ISBLANK(T43),"",IF(IFERROR(EXACT(T43,'_key'!$A$472),FALSE),"✓","✗")) -> 0 | AD43: =IF(ISBLANK(V43),"",IF(IFERROR(ABS(V43-'_key'!$A$473)<=0.005,FALSE),"✓","✗")) -> 0
A44: ACC-0040 | X44: =IF(ISBLANK(H44),"",IF(IFERROR(ABS(H44-'_key'!$A$474)<=5e-05,FALSE),"✓","✗")) -> 0 | Y44: =IF(ISBLANK(K44),"",IF(IFERROR(ABS(K44-'_key'!$A$475)<=5e-05,FALSE),"✓","✗")) -> 0 | Z44: =IF(ISBLANK(L44),"",IF(IFERROR(ABS(L44-'_key'!$A$476)<=0.005,FALSE),"✓","✗")) -> 0 | AA44: =IF(ISBLANK(M44),"",IF(IFERROR(ABS(M44-'_key'!$A$477)<=0.005,FALSE),"✓","✗")) -> 0 | AB44: =IF(ISBLANK(S44),"",IF(IFERROR(ABS(S44-'_key'!$A$478)<=0.01,FALSE),"✓","✗")) -> 0 | AC44: =IF(ISBLANK(T44),"",IF(IFERROR(EXACT(T44,'_key'!$A$479),FALSE),"✓","✗")) -> 0 | AD44: =IF(ISBLANK(V44),"",IF(IFERROR(ABS(V44-'_key'!$A$480)<=0.005,FALSE),"✓","✗")) -> 0
A45: ACC-0041 | X45: =IF(ISBLANK(H45),"",IF(IFERROR(ABS(H45-'_key'!$A$481)<=5e-05,FALSE),"✓","✗")) -> 0 | Y45: =IF(ISBLANK(K45),"",IF(IFERROR(ABS(K45-'_key'!$A$482)<=5e-05,FALSE),"✓","✗")) -> 0 | Z45: =IF(ISBLANK(L45),"",IF(IFERROR(ABS(L45-'_key'!$A$483)<=0.005,FALSE),"✓","✗")) -> 0 | AA45: =IF(ISBLANK(M45),"",IF(IFERROR(EXACT(M45,'_key'!$A$484),FALSE),"✓","✗")) -> 0 | AB45: =IF(ISBLANK(S45),"",IF(IFERROR(ABS(S45-'_key'!$A$485)<=0.01,FALSE),"✓","✗")) -> 0 | AC45: =IF(ISBLANK(T45),"",IF(IFERROR(EXACT(T45,'_key'!$A$486),FALSE),"✓","✗")) -> 0 | AD45: =IF(ISBLANK(V45),"",IF(IFERROR(ABS(V45-'_key'!$A$487)<=0.005,FALSE),"✓","✗")) -> 0
A46: ACC-0042 | X46: =IF(ISBLANK(H46),"",IF(IFERROR(ABS(H46-'_key'!$A$488)<=5e-05,FALSE),"✓","✗")) -> 0 | Y46: =IF(ISBLANK(K46),"",IF(IFERROR(ABS(K46-'_key'!$A$489)<=5e-05,FALSE),"✓","✗")) -> 0 | Z46: =IF(ISBLANK(L46),"",IF(IFERROR(ABS(L46-'_key'!$A$490)<=0.005,FALSE),"✓","✗")) -> 0 | AA46: =IF(ISBLANK(M46),"",IF(IFERROR(EXACT(M46,'_key'!$A$491),FALSE),"✓","✗")) -> 0 | AB46: =IF(ISBLANK(S46),"",IF(IFERROR(ABS(S46-'_key'!$A$492)<=0.01,FALSE),"✓","✗")) -> 0 | AC46: =IF(ISBLANK(T46),"",IF(IFERROR(EXACT(T46,'_key'!$A$493),FALSE),"✓","✗")) -> 0 | AD46: =IF(ISBLANK(V46),"",IF(IFERROR(ABS(V46-'_key'!$A$494)<=0.005,FALSE),"✓","✗")) -> 0
A47: ACC-0043 | X47: =IF(ISBLANK(H47),"",IF(IFERROR(ABS(H47-'_key'!$A$495)<=5e-05,FALSE),"✓","✗")) -> 0 | Y47: =IF(ISBLANK(K47),"",IF(IFERROR(ABS(K47-'_key'!$A$496)<=5e-05,FALSE),"✓","✗")) -> 0 | Z47: =IF(ISBLANK(L47),"",IF(IFERROR(ABS(L47-'_key'!$A$497)<=0.005,FALSE),"✓","✗")) -> 0 | AA47: =IF(ISBLANK(M47),"",IF(IFERROR(ABS(M47-'_key'!$A$498)<=0.005,FALSE),"✓","✗")) -> 0 | AB47: =IF(ISBLANK(S47),"",IF(IFERROR(ABS(S47-'_key'!$A$499)<=0.01,FALSE),"✓","✗")) -> 0 | AC47: =IF(ISBLANK(T47),"",IF(IFERROR(EXACT(T47,'_key'!$A$500),FALSE),"✓","✗")) -> 0 | AD47: =IF(ISBLANK(V47),"",IF(IFERROR(ABS(V47-'_key'!$A$501)<=0.005,FALSE),"✓","✗")) -> 0
A48: ACC-0044 | X48: =IF(ISBLANK(H48),"",IF(IFERROR(ABS(H48-'_key'!$A$502)<=5e-05,FALSE),"✓","✗")) -> 0 | Y48: =IF(ISBLANK(K48),"",IF(IFERROR(ABS(K48-'_key'!$A$503)<=5e-05,FALSE),"✓","✗")) -> 0 | Z48: =IF(ISBLANK(L48),"",IF(IFERROR(ABS(L48-'_key'!$A$504)<=0.005,FALSE),"✓","✗")) -> 0 | AA48: =IF(ISBLANK(M48),"",IF(IFERROR(ABS(M48-'_key'!$A$505)<=0.005,FALSE),"✓","✗")) -> 0 | AB48: =IF(ISBLANK(S48),"",IF(IFERROR(ABS(S48-'_key'!$A$506)<=0.01,FALSE),"✓","✗")) -> 0 | AC48: =IF(ISBLANK(T48),"",IF(IFERROR(EXACT(T48,'_key'!$A$507),FALSE),"✓","✗")) -> 0 | AD48: =IF(ISBLANK(V48),"",IF(IFERROR(ABS(V48-'_key'!$A$508)<=0.005,FALSE),"✓","✗")) -> 0
A49: ACC-0045 | X49: =IF(ISBLANK(H49),"",IF(IFERROR(ABS(H49-'_key'!$A$509)<=5e-05,FALSE),"✓","✗")) -> 0 | Y49: =IF(ISBLANK(K49),"",IF(IFERROR(ABS(K49-'_key'!$A$510)<=5e-05,FALSE),"✓","✗")) -> 0 | Z49: =IF(ISBLANK(L49),"",IF(IFERROR(ABS(L49-'_key'!$A$511)<=0.005,FALSE),"✓","✗")) -> 0 | AA49: =IF(ISBLANK(M49),"",IF(IFERROR(ABS(M49-'_key'!$A$512)<=0.005,FALSE),"✓","✗")) -> 0 | AB49: =IF(ISBLANK(S49),"",IF(IFERROR(ABS(S49-'_key'!$A$513)<=0.01,FALSE),"✓","✗")) -> 0 | AC49: =IF(ISBLANK(T49),"",IF(IFERROR(EXACT(T49,'_key'!$A$514),FALSE),"✓","✗")) -> 0 | AD49: =IF(ISBLANK(V49),"",IF(IFERROR(ABS(V49-'_key'!$A$515)<=0.005,FALSE),"✓","✗")) -> 0
A50: ACC-0046 | X50: =IF(ISBLANK(H50),"",IF(IFERROR(ABS(H50-'_key'!$A$516)<=5e-05,FALSE),"✓","✗")) -> 0 | Y50: =IF(ISBLANK(K50),"",IF(IFERROR(ABS(K50-'_key'!$A$517)<=5e-05,FALSE),"✓","✗")) -> 0 | Z50: =IF(ISBLANK(L50),"",IF(IFERROR(ABS(L50-'_key'!$A$518)<=0.005,FALSE),"✓","✗")) -> 0 | AA50: =IF(ISBLANK(M50),"",IF(IFERROR(ABS(M50-'_key'!$A$519)<=0.005,FALSE),"✓","✗")) -> 0 | AB50: =IF(ISBLANK(S50),"",IF(IFERROR(ABS(S50-'_key'!$A$520)<=0.01,FALSE),"✓","✗")) -> 0 | AC50: =IF(ISBLANK(T50),"",IF(IFERROR(EXACT(T50,'_key'!$A$521),FALSE),"✓","✗")) -> 0 | AD50: =IF(ISBLANK(V50),"",IF(IFERROR(ABS(V50-'_key'!$A$522)<=0.005,FALSE),"✓","✗")) -> 0
A51: ACC-0047 | X51: =IF(ISBLANK(H51),"",IF(IFERROR(ABS(H51-'_key'!$A$523)<=5e-05,FALSE),"✓","✗")) -> 0 | Y51: =IF(ISBLANK(K51),"",IF(IFERROR(ABS(K51-'_key'!$A$524)<=5e-05,FALSE),"✓","✗")) -> 0 | Z51: =IF(ISBLANK(L51),"",IF(IFERROR(ABS(L51-'_key'!$A$525)<=0.005,FALSE),"✓","✗")) -> 0 | AA51: =IF(ISBLANK(M51),"",IF(IFERROR(EXACT(M51,'_key'!$A$526),FALSE),"✓","✗")) -> 0 | AB51: =IF(ISBLANK(S51),"",IF(IFERROR(ABS(S51-'_key'!$A$527)<=0.01,FALSE),"✓","✗")) -> 0 | AC51: =IF(ISBLANK(T51),"",IF(IFERROR(EXACT(T51,'_key'!$A$528),FALSE),"✓","✗")) -> 0 | AD51: =IF(ISBLANK(V51),"",IF(IFERROR(ABS(V51-'_key'!$A$529)<=0.005,FALSE),"✓","✗")) -> 0
A52: ACC-0048 | X52: =IF(ISBLANK(H52),"",IF(IFERROR(ABS(H52-'_key'!$A$530)<=5e-05,FALSE),"✓","✗")) -> 0 | Y52: =IF(ISBLANK(K52),"",IF(IFERROR(ABS(K52-'_key'!$A$531)<=5e-05,FALSE),"✓","✗")) -> 0 | Z52: =IF(ISBLANK(L52),"",IF(IFERROR(ABS(L52-'_key'!$A$532)<=0.005,FALSE),"✓","✗")) -> 0 | AA52: =IF(ISBLANK(M52),"",IF(IFERROR(ABS(M52-'_key'!$A$533)<=0.005,FALSE),"✓","✗")) -> 0 | AB52: =IF(ISBLANK(S52),"",IF(IFERROR(ABS(S52-'_key'!$A$534)<=0.01,FALSE),"✓","✗")) -> 0 | AC52: =IF(ISBLANK(T52),"",IF(IFERROR(EXACT(T52,'_key'!$A$535),FALSE),"✓","✗")) -> 0 | AD52: =IF(ISBLANK(V52),"",IF(IFERROR(ABS(V52-'_key'!$A$536)<=0.005,FALSE),"✓","✗")) -> 0
A53: ACC-0049 | X53: =IF(ISBLANK(H53),"",IF(IFERROR(ABS(H53-'_key'!$A$537)<=5e-05,FALSE),"✓","✗")) -> 0 | Y53: =IF(ISBLANK(K53),"",IF(IFERROR(ABS(K53-'_key'!$A$538)<=5e-05,FALSE),"✓","✗")) -> 0 | Z53: =IF(ISBLANK(L53),"",IF(IFERROR(ABS(L53-'_key'!$A$539)<=0.005,FALSE),"✓","✗")) -> 0 | AA53: =IF(ISBLANK(M53),"",IF(IFERROR(ABS(M53-'_key'!$A$540)<=0.005,FALSE),"✓","✗")) -> 0 | AB53: =IF(ISBLANK(S53),"",IF(IFERROR(ABS(S53-'_key'!$A$541)<=0.01,FALSE),"✓","✗")) -> 0 | AC53: =IF(ISBLANK(T53),"",IF(IFERROR(EXACT(T53,'_key'!$A$542),FALSE),"✓","✗")) -> 0 | AD53: =IF(ISBLANK(V53),"",IF(IFERROR(ABS(V53-'_key'!$A$543)<=0.005,FALSE),"✓","✗")) -> 0
A54: ACC-0050 | X54: =IF(ISBLANK(H54),"",IF(IFERROR(ABS(H54-'_key'!$A$544)<=5e-05,FALSE),"✓","✗")) -> 0 | Y54: =IF(ISBLANK(K54),"",IF(IFERROR(ABS(K54-'_key'!$A$545)<=5e-05,FALSE),"✓","✗")) -> 0 | Z54: =IF(ISBLANK(L54),"",IF(IFERROR(ABS(L54-'_key'!$A$546)<=0.005,FALSE),"✓","✗")) -> 0 | AA54: =IF(ISBLANK(M54),"",IF(IFERROR(EXACT(M54,'_key'!$A$547),FALSE),"✓","✗")) -> 0 | AB54: =IF(ISBLANK(S54),"",IF(IFERROR(ABS(S54-'_key'!$A$548)<=0.01,FALSE),"✓","✗")) -> 0 | AC54: =IF(ISBLANK(T54),"",IF(IFERROR(EXACT(T54,'_key'!$A$549),FALSE),"✓","✗")) -> 0 | AD54: =IF(ISBLANK(V54),"",IF(IFERROR(ABS(V54-'_key'!$A$550)<=0.005,FALSE),"✓","✗")) -> 0
A55: ACC-0051 | X55: =IF(ISBLANK(H55),"",IF(IFERROR(ABS(H55-'_key'!$A$551)<=5e-05,FALSE),"✓","✗")) -> 0 | Y55: =IF(ISBLANK(K55),"",IF(IFERROR(ABS(K55-'_key'!$A$552)<=5e-05,FALSE),"✓","✗")) -> 0 | Z55: =IF(ISBLANK(L55),"",IF(IFERROR(ABS(L55-'_key'!$A$553)<=0.005,FALSE),"✓","✗")) -> 0 | AA55: =IF(ISBLANK(M55),"",IF(IFERROR(ABS(M55-'_key'!$A$554)<=0.005,FALSE),"✓","✗")) -> 0 | AB55: =IF(ISBLANK(S55),"",IF(IFERROR(ABS(S55-'_key'!$A$555)<=0.01,FALSE),"✓","✗")) -> 0 | AC55: =IF(ISBLANK(T55),"",IF(IFERROR(EXACT(T55,'_key'!$A$556),FALSE),"✓","✗")) -> 0 | AD55: =IF(ISBLANK(V55),"",IF(IFERROR(ABS(V55-'_key'!$A$557)<=0.005,FALSE),"✓","✗")) -> 0
A56: ACC-0052 | X56: =IF(ISBLANK(H56),"",IF(IFERROR(ABS(H56-'_key'!$A$558)<=5e-05,FALSE),"✓","✗")) -> 0 | Y56: =IF(ISBLANK(K56),"",IF(IFERROR(ABS(K56-'_key'!$A$559)<=5e-05,FALSE),"✓","✗")) -> 0 | Z56: =IF(ISBLANK(L56),"",IF(IFERROR(ABS(L56-'_key'!$A$560)<=0.005,FALSE),"✓","✗")) -> 0 | AA56: =IF(ISBLANK(M56),"",IF(IFERROR(ABS(M56-'_key'!$A$561)<=0.005,FALSE),"✓","✗")) -> 0 | AB56: =IF(ISBLANK(S56),"",IF(IFERROR(ABS(S56-'_key'!$A$562)<=0.01,FALSE),"✓","✗")) -> 0 | AC56: =IF(ISBLANK(T56),"",IF(IFERROR(EXACT(T56,'_key'!$A$563),FALSE),"✓","✗")) -> 0 | AD56: =IF(ISBLANK(V56),"",IF(IFERROR(ABS(V56-'_key'!$A$564)<=0.005,FALSE),"✓","✗")) -> 0
A57: ACC-0053 | X57: =IF(ISBLANK(H57),"",IF(IFERROR(ABS(H57-'_key'!$A$565)<=5e-05,FALSE),"✓","✗")) -> 0 | Y57: =IF(ISBLANK(K57),"",IF(IFERROR(ABS(K57-'_key'!$A$566)<=5e-05,FALSE),"✓","✗")) -> 0 | Z57: =IF(ISBLANK(L57),"",IF(IFERROR(ABS(L57-'_key'!$A$567)<=0.005,FALSE),"✓","✗")) -> 0 | AA57: =IF(ISBLANK(M57),"",IF(IFERROR(ABS(M57-'_key'!$A$568)<=0.005,FALSE),"✓","✗")) -> 0 | AB57: =IF(ISBLANK(S57),"",IF(IFERROR(ABS(S57-'_key'!$A$569)<=0.01,FALSE),"✓","✗")) -> 0 | AC57: =IF(ISBLANK(T57),"",IF(IFERROR(EXACT(T57,'_key'!$A$570),FALSE),"✓","✗")) -> 0 | AD57: =IF(ISBLANK(V57),"",IF(IFERROR(ABS(V57-'_key'!$A$571)<=0.005,FALSE),"✓","✗")) -> 0
A58: ACC-0054 | X58: =IF(ISBLANK(H58),"",IF(IFERROR(ABS(H58-'_key'!$A$572)<=5e-05,FALSE),"✓","✗")) -> 0 | Y58: =IF(ISBLANK(K58),"",IF(IFERROR(ABS(K58-'_key'!$A$573)<=5e-05,FALSE),"✓","✗")) -> 0 | Z58: =IF(ISBLANK(L58),"",IF(IFERROR(ABS(L58-'_key'!$A$574)<=0.005,FALSE),"✓","✗")) -> 0 | AA58: =IF(ISBLANK(M58),"",IF(IFERROR(EXACT(M58,'_key'!$A$575),FALSE),"✓","✗")) -> 0 | AB58: =IF(ISBLANK(S58),"",IF(IFERROR(ABS(S58-'_key'!$A$576)<=0.01,FALSE),"✓","✗")) -> 0 | AC58: =IF(ISBLANK(T58),"",IF(IFERROR(EXACT(T58,'_key'!$A$577),FALSE),"✓","✗")) -> 0 | AD58: =IF(ISBLANK(V58),"",IF(IFERROR(ABS(V58-'_key'!$A$578)<=0.005,FALSE),"✓","✗")) -> 0
A59: ACC-0055 | X59: =IF(ISBLANK(H59),"",IF(IFERROR(ABS(H59-'_key'!$A$579)<=5e-05,FALSE),"✓","✗")) -> 0 | Y59: =IF(ISBLANK(K59),"",IF(IFERROR(ABS(K59-'_key'!$A$580)<=5e-05,FALSE),"✓","✗")) -> 0 | Z59: =IF(ISBLANK(L59),"",IF(IFERROR(ABS(L59-'_key'!$A$581)<=0.005,FALSE),"✓","✗")) -> 0 | AA59: =IF(ISBLANK(M59),"",IF(IFERROR(ABS(M59-'_key'!$A$582)<=0.005,FALSE),"✓","✗")) -> 0 | AB59: =IF(ISBLANK(S59),"",IF(IFERROR(ABS(S59-'_key'!$A$583)<=0.01,FALSE),"✓","✗")) -> 0 | AC59: =IF(ISBLANK(T59),"",IF(IFERROR(EXACT(T59,'_key'!$A$584),FALSE),"✓","✗")) -> 0 | AD59: =IF(ISBLANK(V59),"",IF(IFERROR(ABS(V59-'_key'!$A$585)<=0.005,FALSE),"✓","✗")) -> 0
A60: ACC-0056 | X60: =IF(ISBLANK(H60),"",IF(IFERROR(ABS(H60-'_key'!$A$586)<=5e-05,FALSE),"✓","✗")) -> 0 | Y60: =IF(ISBLANK(K60),"",IF(IFERROR(ABS(K60-'_key'!$A$587)<=5e-05,FALSE),"✓","✗")) -> 0 | Z60: =IF(ISBLANK(L60),"",IF(IFERROR(ABS(L60-'_key'!$A$588)<=0.005,FALSE),"✓","✗")) -> 0 | AA60: =IF(ISBLANK(M60),"",IF(IFERROR(ABS(M60-'_key'!$A$589)<=0.005,FALSE),"✓","✗")) -> 0 | AB60: =IF(ISBLANK(S60),"",IF(IFERROR(ABS(S60-'_key'!$A$590)<=0.01,FALSE),"✓","✗")) -> 0 | AC60: =IF(ISBLANK(T60),"",IF(IFERROR(EXACT(T60,'_key'!$A$591),FALSE),"✓","✗")) -> 0 | AD60: =IF(ISBLANK(V60),"",IF(IFERROR(ABS(V60-'_key'!$A$592)<=0.005,FALSE),"✓","✗")) -> 0
A61: ACC-0057 | X61: =IF(ISBLANK(H61),"",IF(IFERROR(ABS(H61-'_key'!$A$593)<=5e-05,FALSE),"✓","✗")) -> 0 | Y61: =IF(ISBLANK(K61),"",IF(IFERROR(ABS(K61-'_key'!$A$594)<=5e-05,FALSE),"✓","✗")) -> 0 | Z61: =IF(ISBLANK(L61),"",IF(IFERROR(ABS(L61-'_key'!$A$595)<=0.005,FALSE),"✓","✗")) -> 0 | AA61: =IF(ISBLANK(M61),"",IF(IFERROR(EXACT(M61,'_key'!$A$596),FALSE),"✓","✗")) -> 0 | AB61: =IF(ISBLANK(S61),"",IF(IFERROR(ABS(S61-'_key'!$A$597)<=0.01,FALSE),"✓","✗")) -> 0 | AC61: =IF(ISBLANK(T61),"",IF(IFERROR(EXACT(T61,'_key'!$A$598),FALSE),"✓","✗")) -> 0 | AD61: =IF(ISBLANK(V61),"",IF(IFERROR(ABS(V61-'_key'!$A$599)<=0.005,FALSE),"✓","✗")) -> 0
A62: ACC-0058 | X62: =IF(ISBLANK(H62),"",IF(IFERROR(ABS(H62-'_key'!$A$600)<=5e-05,FALSE),"✓","✗")) -> 0 | Y62: =IF(ISBLANK(K62),"",IF(IFERROR(ABS(K62-'_key'!$A$601)<=5e-05,FALSE),"✓","✗")) -> 0 | Z62: =IF(ISBLANK(L62),"",IF(IFERROR(ABS(L62-'_key'!$A$602)<=0.005,FALSE),"✓","✗")) -> 0 | AA62: =IF(ISBLANK(M62),"",IF(IFERROR(ABS(M62-'_key'!$A$603)<=0.005,FALSE),"✓","✗")) -> 0 | AB62: =IF(ISBLANK(S62),"",IF(IFERROR(ABS(S62-'_key'!$A$604)<=0.01,FALSE),"✓","✗")) -> 0 | AC62: =IF(ISBLANK(T62),"",IF(IFERROR(EXACT(T62,'_key'!$A$605),FALSE),"✓","✗")) -> 0 | AD62: =IF(ISBLANK(V62),"",IF(IFERROR(ABS(V62-'_key'!$A$606)<=0.005,FALSE),"✓","✗")) -> 0
A63: ACC-0059 | X63: =IF(ISBLANK(H63),"",IF(IFERROR(ABS(H63-'_key'!$A$607)<=5e-05,FALSE),"✓","✗")) -> 0 | Y63: =IF(ISBLANK(K63),"",IF(IFERROR(ABS(K63-'_key'!$A$608)<=5e-05,FALSE),"✓","✗")) -> 0 | Z63: =IF(ISBLANK(L63),"",IF(IFERROR(ABS(L63-'_key'!$A$609)<=0.005,FALSE),"✓","✗")) -> 0 | AA63: =IF(ISBLANK(M63),"",IF(IFERROR(ABS(M63-'_key'!$A$610)<=0.005,FALSE),"✓","✗")) -> 0 | AB63: =IF(ISBLANK(S63),"",IF(IFERROR(ABS(S63-'_key'!$A$611)<=0.01,FALSE),"✓","✗")) -> 0 | AC63: =IF(ISBLANK(T63),"",IF(IFERROR(EXACT(T63,'_key'!$A$612),FALSE),"✓","✗")) -> 0 | AD63: =IF(ISBLANK(V63),"",IF(IFERROR(ABS(V63-'_key'!$A$613)<=0.005,FALSE),"✓","✗")) -> 0
A64: ACC-0060 | X64: =IF(ISBLANK(H64),"",IF(IFERROR(ABS(H64-'_key'!$A$614)<=5e-05,FALSE),"✓","✗")) -> 0 | Y64: =IF(ISBLANK(K64),"",IF(IFERROR(ABS(K64-'_key'!$A$615)<=5e-05,FALSE),"✓","✗")) -> 0 | Z64: =IF(ISBLANK(L64),"",IF(IFERROR(ABS(L64-'_key'!$A$616)<=0.005,FALSE),"✓","✗")) -> 0 | AA64: =IF(ISBLANK(M64),"",IF(IFERROR(ABS(M64-'_key'!$A$617)<=0.005,FALSE),"✓","✗")) -> 0 | AB64: =IF(ISBLANK(S64),"",IF(IFERROR(ABS(S64-'_key'!$A$618)<=0.01,FALSE),"✓","✗")) -> 0 | AC64: =IF(ISBLANK(T64),"",IF(IFERROR(EXACT(T64,'_key'!$A$619),FALSE),"✓","✗")) -> 0 | AD64: =IF(ISBLANK(V64),"",IF(IFERROR(ABS(V64-'_key'!$A$620)<=0.005,FALSE),"✓","✗")) -> 0
A65: ACC-0061 | X65: =IF(ISBLANK(H65),"",IF(IFERROR(ABS(H65-'_key'!$A$621)<=5e-05,FALSE),"✓","✗")) -> 0 | Y65: =IF(ISBLANK(K65),"",IF(IFERROR(ABS(K65-'_key'!$A$622)<=5e-05,FALSE),"✓","✗")) -> 0 | Z65: =IF(ISBLANK(L65),"",IF(IFERROR(ABS(L65-'_key'!$A$623)<=0.005,FALSE),"✓","✗")) -> 0 | AA65: =IF(ISBLANK(M65),"",IF(IFERROR(EXACT(M65,'_key'!$A$624),FALSE),"✓","✗")) -> 0 | AB65: =IF(ISBLANK(S65),"",IF(IFERROR(ABS(S65-'_key'!$A$625)<=0.01,FALSE),"✓","✗")) -> 0 | AC65: =IF(ISBLANK(T65),"",IF(IFERROR(EXACT(T65,'_key'!$A$626),FALSE),"✓","✗")) -> 0 | AD65: =IF(ISBLANK(V65),"",IF(IFERROR(ABS(V65-'_key'!$A$627)<=0.005,FALSE),"✓","✗")) -> 0
A66: ACC-0062 | X66: =IF(ISBLANK(H66),"",IF(IFERROR(ABS(H66-'_key'!$A$628)<=5e-05,FALSE),"✓","✗")) -> 0 | Y66: =IF(ISBLANK(K66),"",IF(IFERROR(ABS(K66-'_key'!$A$629)<=5e-05,FALSE),"✓","✗")) -> 0 | Z66: =IF(ISBLANK(L66),"",IF(IFERROR(ABS(L66-'_key'!$A$630)<=0.005,FALSE),"✓","✗")) -> 0 | AA66: =IF(ISBLANK(M66),"",IF(IFERROR(ABS(M66-'_key'!$A$631)<=0.005,FALSE),"✓","✗")) -> 0 | AB66: =IF(ISBLANK(S66),"",IF(IFERROR(ABS(S66-'_key'!$A$632)<=0.01,FALSE),"✓","✗")) -> 0 | AC66: =IF(ISBLANK(T66),"",IF(IFERROR(EXACT(T66,'_key'!$A$633),FALSE),"✓","✗")) -> 0 | AD66: =IF(ISBLANK(V66),"",IF(IFERROR(ABS(V66-'_key'!$A$634)<=0.005,FALSE),"✓","✗")) -> 0
A67: ACC-0063 | X67: =IF(ISBLANK(H67),"",IF(IFERROR(ABS(H67-'_key'!$A$635)<=5e-05,FALSE),"✓","✗")) -> 0 | Y67: =IF(ISBLANK(K67),"",IF(IFERROR(ABS(K67-'_key'!$A$636)<=5e-05,FALSE),"✓","✗")) -> 0 | Z67: =IF(ISBLANK(L67),"",IF(IFERROR(ABS(L67-'_key'!$A$637)<=0.005,FALSE),"✓","✗")) -> 0 | AA67: =IF(ISBLANK(M67),"",IF(IFERROR(EXACT(M67,'_key'!$A$638),FALSE),"✓","✗")) -> 0 | AB67: =IF(ISBLANK(S67),"",IF(IFERROR(ABS(S67-'_key'!$A$639)<=0.01,FALSE),"✓","✗")) -> 0 | AC67: =IF(ISBLANK(T67),"",IF(IFERROR(EXACT(T67,'_key'!$A$640),FALSE),"✓","✗")) -> 0 | AD67: =IF(ISBLANK(V67),"",IF(IFERROR(ABS(V67-'_key'!$A$641)<=0.005,FALSE),"✓","✗")) -> 0
A68: ACC-0064 | X68: =IF(ISBLANK(H68),"",IF(IFERROR(ABS(H68-'_key'!$A$642)<=5e-05,FALSE),"✓","✗")) -> 0 | Y68: =IF(ISBLANK(K68),"",IF(IFERROR(ABS(K68-'_key'!$A$643)<=5e-05,FALSE),"✓","✗")) -> 0 | Z68: =IF(ISBLANK(L68),"",IF(IFERROR(ABS(L68-'_key'!$A$644)<=0.005,FALSE),"✓","✗")) -> 0 | AA68: =IF(ISBLANK(M68),"",IF(IFERROR(ABS(M68-'_key'!$A$645)<=0.005,FALSE),"✓","✗")) -> 0 | AB68: =IF(ISBLANK(S68),"",IF(IFERROR(ABS(S68-'_key'!$A$646)<=0.01,FALSE),"✓","✗")) -> 0 | AC68: =IF(ISBLANK(T68),"",IF(IFERROR(EXACT(T68,'_key'!$A$647),FALSE),"✓","✗")) -> 0 | AD68: =IF(ISBLANK(V68),"",IF(IFERROR(ABS(V68-'_key'!$A$648)<=0.005,FALSE),"✓","✗")) -> 0
A69: ACC-0065 | X69: =IF(ISBLANK(H69),"",IF(IFERROR(ABS(H69-'_key'!$A$649)<=5e-05,FALSE),"✓","✗")) -> 0 | Y69: =IF(ISBLANK(K69),"",IF(IFERROR(ABS(K69-'_key'!$A$650)<=5e-05,FALSE),"✓","✗")) -> 0 | Z69: =IF(ISBLANK(L69),"",IF(IFERROR(ABS(L69-'_key'!$A$651)<=0.005,FALSE),"✓","✗")) -> 0 | AA69: =IF(ISBLANK(M69),"",IF(IFERROR(ABS(M69-'_key'!$A$652)<=0.005,FALSE),"✓","✗")) -> 0 | AB69: =IF(ISBLANK(S69),"",IF(IFERROR(ABS(S69-'_key'!$A$653)<=0.01,FALSE),"✓","✗")) -> 0 | AC69: =IF(ISBLANK(T69),"",IF(IFERROR(EXACT(T69,'_key'!$A$654),FALSE),"✓","✗")) -> 0 | AD69: =IF(ISBLANK(V69),"",IF(IFERROR(ABS(V69-'_key'!$A$655)<=0.005,FALSE),"✓","✗")) -> 0
A70: ACC-0066 | X70: =IF(ISBLANK(H70),"",IF(IFERROR(ABS(H70-'_key'!$A$656)<=5e-05,FALSE),"✓","✗")) -> 0 | Y70: =IF(ISBLANK(K70),"",IF(IFERROR(ABS(K70-'_key'!$A$657)<=5e-05,FALSE),"✓","✗")) -> 0 | Z70: =IF(ISBLANK(L70),"",IF(IFERROR(ABS(L70-'_key'!$A$658)<=0.005,FALSE),"✓","✗")) -> 0 | AA70: =IF(ISBLANK(M70),"",IF(IFERROR(EXACT(M70,'_key'!$A$659),FALSE),"✓","✗")) -> 0 | AB70: =IF(ISBLANK(S70),"",IF(IFERROR(ABS(S70-'_key'!$A$660)<=0.01,FALSE),"✓","✗")) -> 0 | AC70: =IF(ISBLANK(T70),"",IF(IFERROR(EXACT(T70,'_key'!$A$661),FALSE),"✓","✗")) -> 0 | AD70: =IF(ISBLANK(V70),"",IF(IFERROR(ABS(V70-'_key'!$A$662)<=0.005,FALSE),"✓","✗")) -> 0
A71: ACC-0067 | X71: =IF(ISBLANK(H71),"",IF(IFERROR(ABS(H71-'_key'!$A$663)<=5e-05,FALSE),"✓","✗")) -> 0 | Y71: =IF(ISBLANK(K71),"",IF(IFERROR(ABS(K71-'_key'!$A$664)<=5e-05,FALSE),"✓","✗")) -> 0 | Z71: =IF(ISBLANK(L71),"",IF(IFERROR(ABS(L71-'_key'!$A$665)<=0.005,FALSE),"✓","✗")) -> 0 | AA71: =IF(ISBLANK(M71),"",IF(IFERROR(EXACT(M71,'_key'!$A$666),FALSE),"✓","✗")) -> 0 | AB71: =IF(ISBLANK(S71),"",IF(IFERROR(ABS(S71-'_key'!$A$667)<=0.01,FALSE),"✓","✗")) -> 0 | AC71: =IF(ISBLANK(T71),"",IF(IFERROR(EXACT(T71,'_key'!$A$668),FALSE),"✓","✗")) -> 0 | AD71: =IF(ISBLANK(V71),"",IF(IFERROR(ABS(V71-'_key'!$A$669)<=0.005,FALSE),"✓","✗")) -> 0
A72: ACC-0068 | X72: =IF(ISBLANK(H72),"",IF(IFERROR(ABS(H72-'_key'!$A$670)<=5e-05,FALSE),"✓","✗")) -> 0 | Y72: =IF(ISBLANK(K72),"",IF(IFERROR(ABS(K72-'_key'!$A$671)<=5e-05,FALSE),"✓","✗")) -> 0 | Z72: =IF(ISBLANK(L72),"",IF(IFERROR(ABS(L72-'_key'!$A$672)<=0.005,FALSE),"✓","✗")) -> 0 | AA72: =IF(ISBLANK(M72),"",IF(IFERROR(ABS(M72-'_key'!$A$673)<=0.005,FALSE),"✓","✗")) -> 0 | AB72: =IF(ISBLANK(S72),"",IF(IFERROR(ABS(S72-'_key'!$A$674)<=0.01,FALSE),"✓","✗")) -> 0 | AC72: =IF(ISBLANK(T72),"",IF(IFERROR(EXACT(T72,'_key'!$A$675),FALSE),"✓","✗")) -> 0 | AD72: =IF(ISBLANK(V72),"",IF(IFERROR(ABS(V72-'_key'!$A$676)<=0.005,FALSE),"✓","✗")) -> 0
A73: ACC-0069 | X73: =IF(ISBLANK(H73),"",IF(IFERROR(ABS(H73-'_key'!$A$677)<=5e-05,FALSE),"✓","✗")) -> 0 | Y73: =IF(ISBLANK(K73),"",IF(IFERROR(ABS(K73-'_key'!$A$678)<=5e-05,FALSE),"✓","✗")) -> 0 | Z73: =IF(ISBLANK(L73),"",IF(IFERROR(ABS(L73-'_key'!$A$679)<=0.005,FALSE),"✓","✗")) -> 0 | AA73: =IF(ISBLANK(M73),"",IF(IFERROR(ABS(M73-'_key'!$A$680)<=0.005,FALSE),"✓","✗")) -> 0 | AB73: =IF(ISBLANK(S73),"",IF(IFERROR(ABS(S73-'_key'!$A$681)<=0.01,FALSE),"✓","✗")) -> 0 | AC73: =IF(ISBLANK(T73),"",IF(IFERROR(EXACT(T73,'_key'!$A$682),FALSE),"✓","✗")) -> 0 | AD73: =IF(ISBLANK(V73),"",IF(IFERROR(ABS(V73-'_key'!$A$683)<=0.005,FALSE),"✓","✗")) -> 0
A74: ACC-0070 | X74: =IF(ISBLANK(H74),"",IF(IFERROR(ABS(H74-'_key'!$A$684)<=5e-05,FALSE),"✓","✗")) -> 0 | Y74: =IF(ISBLANK(K74),"",IF(IFERROR(ABS(K74-'_key'!$A$685)<=5e-05,FALSE),"✓","✗")) -> 0 | Z74: =IF(ISBLANK(L74),"",IF(IFERROR(ABS(L74-'_key'!$A$686)<=0.005,FALSE),"✓","✗")) -> 0 | AA74: =IF(ISBLANK(M74),"",IF(IFERROR(ABS(M74-'_key'!$A$687)<=0.005,FALSE),"✓","✗")) -> 0 | AB74: =IF(ISBLANK(S74),"",IF(IFERROR(ABS(S74-'_key'!$A$688)<=0.01,FALSE),"✓","✗")) -> 0 | AC74: =IF(ISBLANK(T74),"",IF(IFERROR(EXACT(T74,'_key'!$A$689),FALSE),"✓","✗")) -> 0 | AD74: =IF(ISBLANK(V74),"",IF(IFERROR(ABS(V74-'_key'!$A$690)<=0.005,FALSE),"✓","✗")) -> 0
A75: ACC-0071 | X75: =IF(ISBLANK(H75),"",IF(IFERROR(ABS(H75-'_key'!$A$691)<=5e-05,FALSE),"✓","✗")) -> 0 | Y75: =IF(ISBLANK(K75),"",IF(IFERROR(ABS(K75-'_key'!$A$692)<=5e-05,FALSE),"✓","✗")) -> 0 | Z75: =IF(ISBLANK(L75),"",IF(IFERROR(ABS(L75-'_key'!$A$693)<=0.005,FALSE),"✓","✗")) -> 0 | AA75: =IF(ISBLANK(M75),"",IF(IFERROR(ABS(M75-'_key'!$A$694)<=0.005,FALSE),"✓","✗")) -> 0 | AB75: =IF(ISBLANK(S75),"",IF(IFERROR(ABS(S75-'_key'!$A$695)<=0.01,FALSE),"✓","✗")) -> 0 | AC75: =IF(ISBLANK(T75),"",IF(IFERROR(EXACT(T75,'_key'!$A$696),FALSE),"✓","✗")) -> 0 | AD75: =IF(ISBLANK(V75),"",IF(IFERROR(ABS(V75-'_key'!$A$697)<=0.005,FALSE),"✓","✗")) -> 0
A76: ACC-0072 | X76: =IF(ISBLANK(H76),"",IF(IFERROR(ABS(H76-'_key'!$A$698)<=5e-05,FALSE),"✓","✗")) -> 0 | Y76: =IF(ISBLANK(K76),"",IF(IFERROR(ABS(K76-'_key'!$A$699)<=5e-05,FALSE),"✓","✗")) -> 0 | Z76: =IF(ISBLANK(L76),"",IF(IFERROR(ABS(L76-'_key'!$A$700)<=0.005,FALSE),"✓","✗")) -> 0 | AA76: =IF(ISBLANK(M76),"",IF(IFERROR(ABS(M76-'_key'!$A$701)<=0.005,FALSE),"✓","✗")) -> 0 | AB76: =IF(ISBLANK(S76),"",IF(IFERROR(ABS(S76-'_key'!$A$702)<=0.01,FALSE),"✓","✗")) -> 0 | AC76: =IF(ISBLANK(T76),"",IF(IFERROR(EXACT(T76,'_key'!$A$703),FALSE),"✓","✗")) -> 0 | AD76: =IF(ISBLANK(V76),"",IF(IFERROR(ABS(V76-'_key'!$A$704)<=0.005,FALSE),"✓","✗")) -> 0
A77: ACC-0073 | X77: =IF(ISBLANK(H77),"",IF(IFERROR(ABS(H77-'_key'!$A$705)<=5e-05,FALSE),"✓","✗")) -> 0 | Y77: =IF(ISBLANK(K77),"",IF(IFERROR(ABS(K77-'_key'!$A$706)<=5e-05,FALSE),"✓","✗")) -> 0 | Z77: =IF(ISBLANK(L77),"",IF(IFERROR(ABS(L77-'_key'!$A$707)<=0.005,FALSE),"✓","✗")) -> 0 | AA77: =IF(ISBLANK(M77),"",IF(IFERROR(EXACT(M77,'_key'!$A$708),FALSE),"✓","✗")) -> 0 | AB77: =IF(ISBLANK(S77),"",IF(IFERROR(ABS(S77-'_key'!$A$709)<=0.01,FALSE),"✓","✗")) -> 0 | AC77: =IF(ISBLANK(T77),"",IF(IFERROR(EXACT(T77,'_key'!$A$710),FALSE),"✓","✗")) -> 0 | AD77: =IF(ISBLANK(V77),"",IF(IFERROR(ABS(V77-'_key'!$A$711)<=0.005,FALSE),"✓","✗")) -> 0
A78: ACC-0076 | X78: =IF(ISBLANK(H78),"",IF(IFERROR(ABS(H78-'_key'!$A$712)<=5e-05,FALSE),"✓","✗")) -> 0 | Y78: =IF(ISBLANK(K78),"",IF(IFERROR(ABS(K78-'_key'!$A$713)<=5e-05,FALSE),"✓","✗")) -> 0 | Z78: =IF(ISBLANK(L78),"",IF(IFERROR(ABS(L78-'_key'!$A$714)<=0.005,FALSE),"✓","✗")) -> 0 | AA78: =IF(ISBLANK(M78),"",IF(IFERROR(ABS(M78-'_key'!$A$715)<=0.005,FALSE),"✓","✗")) -> 0 | AB78: =IF(ISBLANK(S78),"",IF(IFERROR(ABS(S78-'_key'!$A$716)<=0.01,FALSE),"✓","✗")) -> 0 | AC78: =IF(ISBLANK(T78),"",IF(IFERROR(EXACT(T78,'_key'!$A$717),FALSE),"✓","✗")) -> 0 | AD78: =IF(ISBLANK(V78),"",IF(IFERROR(ABS(V78-'_key'!$A$718)<=0.005,FALSE),"✓","✗")) -> 0
A79: ACC-0078 | X79: =IF(ISBLANK(H79),"",IF(IFERROR(ABS(H79-'_key'!$A$719)<=5e-05,FALSE),"✓","✗")) -> 0 | Y79: =IF(ISBLANK(K79),"",IF(IFERROR(ABS(K79-'_key'!$A$720)<=5e-05,FALSE),"✓","✗")) -> 0 | Z79: =IF(ISBLANK(L79),"",IF(IFERROR(ABS(L79-'_key'!$A$721)<=0.005,FALSE),"✓","✗")) -> 0 | AA79: =IF(ISBLANK(M79),"",IF(IFERROR(ABS(M79-'_key'!$A$722)<=0.005,FALSE),"✓","✗")) -> 0 | AB79: =IF(ISBLANK(S79),"",IF(IFERROR(ABS(S79-'_key'!$A$723)<=0.01,FALSE),"✓","✗")) -> 0 | AC79: =IF(ISBLANK(T79),"",IF(IFERROR(EXACT(T79,'_key'!$A$724),FALSE),"✓","✗")) -> 0 | AD79: =IF(ISBLANK(V79),"",IF(IFERROR(ABS(V79-'_key'!$A$725)<=0.005,FALSE),"✓","✗")) -> 0
A80: ACC-0079 | X80: =IF(ISBLANK(H80),"",IF(IFERROR(ABS(H80-'_key'!$A$726)<=5e-05,FALSE),"✓","✗")) -> 0 | Y80: =IF(ISBLANK(K80),"",IF(IFERROR(ABS(K80-'_key'!$A$727)<=5e-05,FALSE),"✓","✗")) -> 0 | Z80: =IF(ISBLANK(L80),"",IF(IFERROR(ABS(L80-'_key'!$A$728)<=0.005,FALSE),"✓","✗")) -> 0 | AA80: =IF(ISBLANK(M80),"",IF(IFERROR(ABS(M80-'_key'!$A$729)<=0.005,FALSE),"✓","✗")) -> 0 | AB80: =IF(ISBLANK(S80),"",IF(IFERROR(ABS(S80-'_key'!$A$730)<=0.01,FALSE),"✓","✗")) -> 0 | AC80: =IF(ISBLANK(T80),"",IF(IFERROR(EXACT(T80,'_key'!$A$731),FALSE),"✓","✗")) -> 0 | AD80: =IF(ISBLANK(V80),"",IF(IFERROR(ABS(V80-'_key'!$A$732)<=0.005,FALSE),"✓","✗")) -> 0
A81: ACC-0080 | X81: =IF(ISBLANK(H81),"",IF(IFERROR(ABS(H81-'_key'!$A$733)<=5e-05,FALSE),"✓","✗")) -> 0 | Y81: =IF(ISBLANK(K81),"",IF(IFERROR(ABS(K81-'_key'!$A$734)<=5e-05,FALSE),"✓","✗")) -> 0 | Z81: =IF(ISBLANK(L81),"",IF(IFERROR(ABS(L81-'_key'!$A$735)<=0.005,FALSE),"✓","✗")) -> 0 | AA81: =IF(ISBLANK(M81),"",IF(IFERROR(ABS(M81-'_key'!$A$736)<=0.005,FALSE),"✓","✗")) -> 0 | AB81: =IF(ISBLANK(S81),"",IF(IFERROR(ABS(S81-'_key'!$A$737)<=0.01,FALSE),"✓","✗")) -> 0 | AC81: =IF(ISBLANK(T81),"",IF(IFERROR(EXACT(T81,'_key'!$A$738),FALSE),"✓","✗")) -> 0 | AD81: =IF(ISBLANK(V81),"",IF(IFERROR(ABS(V81-'_key'!$A$739)<=0.005,FALSE),"✓","✗")) -> 0
A82: ACC-0081 | X82: =IF(ISBLANK(H82),"",IF(IFERROR(ABS(H82-'_key'!$A$740)<=5e-05,FALSE),"✓","✗")) -> 0 | Y82: =IF(ISBLANK(K82),"",IF(IFERROR(ABS(K82-'_key'!$A$741)<=5e-05,FALSE),"✓","✗")) -> 0 | Z82: =IF(ISBLANK(L82),"",IF(IFERROR(ABS(L82-'_key'!$A$742)<=0.005,FALSE),"✓","✗")) -> 0 | AA82: =IF(ISBLANK(M82),"",IF(IFERROR(ABS(M82-'_key'!$A$743)<=0.005,FALSE),"✓","✗")) -> 0 | AB82: =IF(ISBLANK(S82),"",IF(IFERROR(ABS(S82-'_key'!$A$744)<=0.01,FALSE),"✓","✗")) -> 0 | AC82: =IF(ISBLANK(T82),"",IF(IFERROR(EXACT(T82,'_key'!$A$745),FALSE),"✓","✗")) -> 0 | AD82: =IF(ISBLANK(V82),"",IF(IFERROR(ABS(V82-'_key'!$A$746)<=0.005,FALSE),"✓","✗")) -> 0
A83: ACC-0083 | X83: =IF(ISBLANK(H83),"",IF(IFERROR(ABS(H83-'_key'!$A$747)<=5e-05,FALSE),"✓","✗")) -> 0 | Y83: =IF(ISBLANK(K83),"",IF(IFERROR(ABS(K83-'_key'!$A$748)<=5e-05,FALSE),"✓","✗")) -> 0 | Z83: =IF(ISBLANK(L83),"",IF(IFERROR(ABS(L83-'_key'!$A$749)<=0.005,FALSE),"✓","✗")) -> 0 | AA83: =IF(ISBLANK(M83),"",IF(IFERROR(ABS(M83-'_key'!$A$750)<=0.005,FALSE),"✓","✗")) -> 0 | AB83: =IF(ISBLANK(S83),"",IF(IFERROR(ABS(S83-'_key'!$A$751)<=0.01,FALSE),"✓","✗")) -> 0 | AC83: =IF(ISBLANK(T83),"",IF(IFERROR(EXACT(T83,'_key'!$A$752),FALSE),"✓","✗")) -> 0 | AD83: =IF(ISBLANK(V83),"",IF(IFERROR(ABS(V83-'_key'!$A$753)<=0.005,FALSE),"✓","✗")) -> 0
A84: ACC-0084 | X84: =IF(ISBLANK(H84),"",IF(IFERROR(ABS(H84-'_key'!$A$754)<=5e-05,FALSE),"✓","✗")) -> 0 | Y84: =IF(ISBLANK(K84),"",IF(IFERROR(ABS(K84-'_key'!$A$755)<=5e-05,FALSE),"✓","✗")) -> 0 | Z84: =IF(ISBLANK(L84),"",IF(IFERROR(ABS(L84-'_key'!$A$756)<=0.005,FALSE),"✓","✗")) -> 0 | AA84: =IF(ISBLANK(M84),"",IF(IFERROR(EXACT(M84,'_key'!$A$757),FALSE),"✓","✗")) -> 0 | AB84: =IF(ISBLANK(S84),"",IF(IFERROR(ABS(S84-'_key'!$A$758)<=0.01,FALSE),"✓","✗")) -> 0 | AC84: =IF(ISBLANK(T84),"",IF(IFERROR(EXACT(T84,'_key'!$A$759),FALSE),"✓","✗")) -> 0 | AD84: =IF(ISBLANK(V84),"",IF(IFERROR(ABS(V84-'_key'!$A$760)<=0.005,FALSE),"✓","✗")) -> 0
A85: ACC-0085 | X85: =IF(ISBLANK(H85),"",IF(IFERROR(ABS(H85-'_key'!$A$761)<=5e-05,FALSE),"✓","✗")) -> 0 | Y85: =IF(ISBLANK(K85),"",IF(IFERROR(ABS(K85-'_key'!$A$762)<=5e-05,FALSE),"✓","✗")) -> 0 | Z85: =IF(ISBLANK(L85),"",IF(IFERROR(ABS(L85-'_key'!$A$763)<=0.005,FALSE),"✓","✗")) -> 0 | AA85: =IF(ISBLANK(M85),"",IF(IFERROR(EXACT(M85,'_key'!$A$764),FALSE),"✓","✗")) -> 0 | AB85: =IF(ISBLANK(S85),"",IF(IFERROR(ABS(S85-'_key'!$A$765)<=0.01,FALSE),"✓","✗")) -> 0 | AC85: =IF(ISBLANK(T85),"",IF(IFERROR(EXACT(T85,'_key'!$A$766),FALSE),"✓","✗")) -> 0 | AD85: =IF(ISBLANK(V85),"",IF(IFERROR(ABS(V85-'_key'!$A$767)<=0.005,FALSE),"✓","✗")) -> 0
A86: ACC-0086 | X86: =IF(ISBLANK(H86),"",IF(IFERROR(ABS(H86-'_key'!$A$768)<=5e-05,FALSE),"✓","✗")) -> 0 | Y86: =IF(ISBLANK(K86),"",IF(IFERROR(ABS(K86-'_key'!$A$769)<=5e-05,FALSE),"✓","✗")) -> 0 | Z86: =IF(ISBLANK(L86),"",IF(IFERROR(ABS(L86-'_key'!$A$770)<=0.005,FALSE),"✓","✗")) -> 0 | AA86: =IF(ISBLANK(M86),"",IF(IFERROR(EXACT(M86,'_key'!$A$771),FALSE),"✓","✗")) -> 0 | AB86: =IF(ISBLANK(S86),"",IF(IFERROR(ABS(S86-'_key'!$A$772)<=0.01,FALSE),"✓","✗")) -> 0 | AC86: =IF(ISBLANK(T86),"",IF(IFERROR(EXACT(T86,'_key'!$A$773),FALSE),"✓","✗")) -> 0 | AD86: =IF(ISBLANK(V86),"",IF(IFERROR(ABS(V86-'_key'!$A$774)<=0.005,FALSE),"✓","✗")) -> 0
A87: ACC-0087 | X87: =IF(ISBLANK(H87),"",IF(IFERROR(ABS(H87-'_key'!$A$775)<=5e-05,FALSE),"✓","✗")) -> 0 | Y87: =IF(ISBLANK(K87),"",IF(IFERROR(ABS(K87-'_key'!$A$776)<=5e-05,FALSE),"✓","✗")) -> 0 | Z87: =IF(ISBLANK(L87),"",IF(IFERROR(ABS(L87-'_key'!$A$777)<=0.005,FALSE),"✓","✗")) -> 0 | AA87: =IF(ISBLANK(M87),"",IF(IFERROR(EXACT(M87,'_key'!$A$778),FALSE),"✓","✗")) -> 0 | AB87: =IF(ISBLANK(S87),"",IF(IFERROR(ABS(S87-'_key'!$A$779)<=0.01,FALSE),"✓","✗")) -> 0 | AC87: =IF(ISBLANK(T87),"",IF(IFERROR(EXACT(T87,'_key'!$A$780),FALSE),"✓","✗")) -> 0 | AD87: =IF(ISBLANK(V87),"",IF(IFERROR(ABS(V87-'_key'!$A$781)<=0.005,FALSE),"✓","✗")) -> 0
A88: ACC-0088 | X88: =IF(ISBLANK(H88),"",IF(IFERROR(ABS(H88-'_key'!$A$782)<=5e-05,FALSE),"✓","✗")) -> 0 | Y88: =IF(ISBLANK(K88),"",IF(IFERROR(ABS(K88-'_key'!$A$783)<=5e-05,FALSE),"✓","✗")) -> 0 | Z88: =IF(ISBLANK(L88),"",IF(IFERROR(ABS(L88-'_key'!$A$784)<=0.005,FALSE),"✓","✗")) -> 0 | AA88: =IF(ISBLANK(M88),"",IF(IFERROR(ABS(M88-'_key'!$A$785)<=0.005,FALSE),"✓","✗")) -> 0 | AB88: =IF(ISBLANK(S88),"",IF(IFERROR(ABS(S88-'_key'!$A$786)<=0.01,FALSE),"✓","✗")) -> 0 | AC88: =IF(ISBLANK(T88),"",IF(IFERROR(EXACT(T88,'_key'!$A$787),FALSE),"✓","✗")) -> 0 | AD88: =IF(ISBLANK(V88),"",IF(IFERROR(ABS(V88-'_key'!$A$788)<=0.005,FALSE),"✓","✗")) -> 0
A89: ACC-0089 | X89: =IF(ISBLANK(H89),"",IF(IFERROR(ABS(H89-'_key'!$A$789)<=5e-05,FALSE),"✓","✗")) -> 0 | Y89: =IF(ISBLANK(K89),"",IF(IFERROR(ABS(K89-'_key'!$A$790)<=5e-05,FALSE),"✓","✗")) -> 0 | Z89: =IF(ISBLANK(L89),"",IF(IFERROR(ABS(L89-'_key'!$A$791)<=0.005,FALSE),"✓","✗")) -> 0 | AA89: =IF(ISBLANK(M89),"",IF(IFERROR(ABS(M89-'_key'!$A$792)<=0.005,FALSE),"✓","✗")) -> 0 | AB89: =IF(ISBLANK(S89),"",IF(IFERROR(ABS(S89-'_key'!$A$793)<=0.01,FALSE),"✓","✗")) -> 0 | AC89: =IF(ISBLANK(T89),"",IF(IFERROR(EXACT(T89,'_key'!$A$794),FALSE),"✓","✗")) -> 0 | AD89: =IF(ISBLANK(V89),"",IF(IFERROR(ABS(V89-'_key'!$A$795)<=0.005,FALSE),"✓","✗")) -> 0
A90: ACC-0091 | X90: =IF(ISBLANK(H90),"",IF(IFERROR(ABS(H90-'_key'!$A$796)<=5e-05,FALSE),"✓","✗")) -> 0 | Y90: =IF(ISBLANK(K90),"",IF(IFERROR(ABS(K90-'_key'!$A$797)<=5e-05,FALSE),"✓","✗")) -> 0 | Z90: =IF(ISBLANK(L90),"",IF(IFERROR(ABS(L90-'_key'!$A$798)<=0.005,FALSE),"✓","✗")) -> 0 | AA90: =IF(ISBLANK(M90),"",IF(IFERROR(EXACT(M90,'_key'!$A$799),FALSE),"✓","✗")) -> 0 | AB90: =IF(ISBLANK(S90),"",IF(IFERROR(ABS(S90-'_key'!$A$800)<=0.01,FALSE),"✓","✗")) -> 0 | AC90: =IF(ISBLANK(T90),"",IF(IFERROR(EXACT(T90,'_key'!$A$801),FALSE),"✓","✗")) -> 0 | AD90: =IF(ISBLANK(V90),"",IF(IFERROR(ABS(V90-'_key'!$A$802)<=0.005,FALSE),"✓","✗")) -> 0
A91: ACC-0092 | X91: =IF(ISBLANK(H91),"",IF(IFERROR(ABS(H91-'_key'!$A$803)<=5e-05,FALSE),"✓","✗")) -> 0 | Y91: =IF(ISBLANK(K91),"",IF(IFERROR(ABS(K91-'_key'!$A$804)<=5e-05,FALSE),"✓","✗")) -> 0 | Z91: =IF(ISBLANK(L91),"",IF(IFERROR(ABS(L91-'_key'!$A$805)<=0.005,FALSE),"✓","✗")) -> 0 | AA91: =IF(ISBLANK(M91),"",IF(IFERROR(ABS(M91-'_key'!$A$806)<=0.005,FALSE),"✓","✗")) -> 0 | AB91: =IF(ISBLANK(S91),"",IF(IFERROR(ABS(S91-'_key'!$A$807)<=0.01,FALSE),"✓","✗")) -> 0 | AC91: =IF(ISBLANK(T91),"",IF(IFERROR(EXACT(T91,'_key'!$A$808),FALSE),"✓","✗")) -> 0 | AD91: =IF(ISBLANK(V91),"",IF(IFERROR(ABS(V91-'_key'!$A$809)<=0.005,FALSE),"✓","✗")) -> 0
A92: ACC-0093 | X92: =IF(ISBLANK(H92),"",IF(IFERROR(ABS(H92-'_key'!$A$810)<=5e-05,FALSE),"✓","✗")) -> 0 | Y92: =IF(ISBLANK(K92),"",IF(IFERROR(ABS(K92-'_key'!$A$811)<=5e-05,FALSE),"✓","✗")) -> 0 | Z92: =IF(ISBLANK(L92),"",IF(IFERROR(ABS(L92-'_key'!$A$812)<=0.005,FALSE),"✓","✗")) -> 0 | AA92: =IF(ISBLANK(M92),"",IF(IFERROR(EXACT(M92,'_key'!$A$813),FALSE),"✓","✗")) -> 0 | AB92: =IF(ISBLANK(S92),"",IF(IFERROR(ABS(S92-'_key'!$A$814)<=0.01,FALSE),"✓","✗")) -> 0 | AC92: =IF(ISBLANK(T92),"",IF(IFERROR(EXACT(T92,'_key'!$A$815),FALSE),"✓","✗")) -> 0 | AD92: =IF(ISBLANK(V92),"",IF(IFERROR(ABS(V92-'_key'!$A$816)<=0.005,FALSE),"✓","✗")) -> 0
A93: ACC-0094 | X93: =IF(ISBLANK(H93),"",IF(IFERROR(ABS(H93-'_key'!$A$817)<=5e-05,FALSE),"✓","✗")) -> 0 | Y93: =IF(ISBLANK(K93),"",IF(IFERROR(ABS(K93-'_key'!$A$818)<=5e-05,FALSE),"✓","✗")) -> 0 | Z93: =IF(ISBLANK(L93),"",IF(IFERROR(ABS(L93-'_key'!$A$819)<=0.005,FALSE),"✓","✗")) -> 0 | AA93: =IF(ISBLANK(M93),"",IF(IFERROR(ABS(M93-'_key'!$A$820)<=0.005,FALSE),"✓","✗")) -> 0 | AB93: =IF(ISBLANK(S93),"",IF(IFERROR(ABS(S93-'_key'!$A$821)<=0.01,FALSE),"✓","✗")) -> 0 | AC93: =IF(ISBLANK(T93),"",IF(IFERROR(EXACT(T93,'_key'!$A$822),FALSE),"✓","✗")) -> 0 | AD93: =IF(ISBLANK(V93),"",IF(IFERROR(ABS(V93-'_key'!$A$823)<=0.005,FALSE),"✓","✗")) -> 0
A94: ACC-0095 | X94: =IF(ISBLANK(H94),"",IF(IFERROR(ABS(H94-'_key'!$A$824)<=5e-05,FALSE),"✓","✗")) -> 0 | Y94: =IF(ISBLANK(K94),"",IF(IFERROR(ABS(K94-'_key'!$A$825)<=5e-05,FALSE),"✓","✗")) -> 0 | Z94: =IF(ISBLANK(L94),"",IF(IFERROR(ABS(L94-'_key'!$A$826)<=0.005,FALSE),"✓","✗")) -> 0 | AA94: =IF(ISBLANK(M94),"",IF(IFERROR(ABS(M94-'_key'!$A$827)<=0.005,FALSE),"✓","✗")) -> 0 | AB94: =IF(ISBLANK(S94),"",IF(IFERROR(ABS(S94-'_key'!$A$828)<=0.01,FALSE),"✓","✗")) -> 0 | AC94: =IF(ISBLANK(T94),"",IF(IFERROR(EXACT(T94,'_key'!$A$829),FALSE),"✓","✗")) -> 0 | AD94: =IF(ISBLANK(V94),"",IF(IFERROR(ABS(V94-'_key'!$A$830)<=0.005,FALSE),"✓","✗")) -> 0
A95: ACC-0096 | X95: =IF(ISBLANK(H95),"",IF(IFERROR(ABS(H95-'_key'!$A$831)<=5e-05,FALSE),"✓","✗")) -> 0 | Y95: =IF(ISBLANK(K95),"",IF(IFERROR(ABS(K95-'_key'!$A$832)<=5e-05,FALSE),"✓","✗")) -> 0 | Z95: =IF(ISBLANK(L95),"",IF(IFERROR(ABS(L95-'_key'!$A$833)<=0.005,FALSE),"✓","✗")) -> 0 | AA95: =IF(ISBLANK(M95),"",IF(IFERROR(ABS(M95-'_key'!$A$834)<=0.005,FALSE),"✓","✗")) -> 0 | AB95: =IF(ISBLANK(S95),"",IF(IFERROR(ABS(S95-'_key'!$A$835)<=0.01,FALSE),"✓","✗")) -> 0 | AC95: =IF(ISBLANK(T95),"",IF(IFERROR(EXACT(T95,'_key'!$A$836),FALSE),"✓","✗")) -> 0 | AD95: =IF(ISBLANK(V95),"",IF(IFERROR(ABS(V95-'_key'!$A$837)<=0.005,FALSE),"✓","✗")) -> 0
A96: ACC-0097 | X96: =IF(ISBLANK(H96),"",IF(IFERROR(ABS(H96-'_key'!$A$838)<=5e-05,FALSE),"✓","✗")) -> 0 | Y96: =IF(ISBLANK(K96),"",IF(IFERROR(ABS(K96-'_key'!$A$839)<=5e-05,FALSE),"✓","✗")) -> 0 | Z96: =IF(ISBLANK(L96),"",IF(IFERROR(ABS(L96-'_key'!$A$840)<=0.005,FALSE),"✓","✗")) -> 0 | AA96: =IF(ISBLANK(M96),"",IF(IFERROR(ABS(M96-'_key'!$A$841)<=0.005,FALSE),"✓","✗")) -> 0 | AB96: =IF(ISBLANK(S96),"",IF(IFERROR(ABS(S96-'_key'!$A$842)<=0.01,FALSE),"✓","✗")) -> 0 | AC96: =IF(ISBLANK(T96),"",IF(IFERROR(EXACT(T96,'_key'!$A$843),FALSE),"✓","✗")) -> 0 | AD96: =IF(ISBLANK(V96),"",IF(IFERROR(ABS(V96-'_key'!$A$844)<=0.005,FALSE),"✓","✗")) -> 0
A97: ACC-0098 | X97: =IF(ISBLANK(H97),"",IF(IFERROR(ABS(H97-'_key'!$A$845)<=5e-05,FALSE),"✓","✗")) -> 0 | Y97: =IF(ISBLANK(K97),"",IF(IFERROR(ABS(K97-'_key'!$A$846)<=5e-05,FALSE),"✓","✗")) -> 0 | Z97: =IF(ISBLANK(L97),"",IF(IFERROR(ABS(L97-'_key'!$A$847)<=0.005,FALSE),"✓","✗")) -> 0 | AA97: =IF(ISBLANK(M97),"",IF(IFERROR(ABS(M97-'_key'!$A$848)<=0.005,FALSE),"✓","✗")) -> 0 | AB97: =IF(ISBLANK(S97),"",IF(IFERROR(ABS(S97-'_key'!$A$849)<=0.01,FALSE),"✓","✗")) -> 0 | AC97: =IF(ISBLANK(T97),"",IF(IFERROR(EXACT(T97,'_key'!$A$850),FALSE),"✓","✗")) -> 0 | AD97: =IF(ISBLANK(V97),"",IF(IFERROR(ABS(V97-'_key'!$A$851)<=0.005,FALSE),"✓","✗")) -> 0
A98: ACC-0099 | X98: =IF(ISBLANK(H98),"",IF(IFERROR(ABS(H98-'_key'!$A$852)<=5e-05,FALSE),"✓","✗")) -> 0 | Y98: =IF(ISBLANK(K98),"",IF(IFERROR(ABS(K98-'_key'!$A$853)<=5e-05,FALSE),"✓","✗")) -> 0 | Z98: =IF(ISBLANK(L98),"",IF(IFERROR(ABS(L98-'_key'!$A$854)<=0.005,FALSE),"✓","✗")) -> 0 | AA98: =IF(ISBLANK(M98),"",IF(IFERROR(EXACT(M98,'_key'!$A$855),FALSE),"✓","✗")) -> 0 | AB98: =IF(ISBLANK(S98),"",IF(IFERROR(ABS(S98-'_key'!$A$856)<=0.01,FALSE),"✓","✗")) -> 0 | AC98: =IF(ISBLANK(T98),"",IF(IFERROR(EXACT(T98,'_key'!$A$857),FALSE),"✓","✗")) -> 0 | AD98: =IF(ISBLANK(V98),"",IF(IFERROR(ABS(V98-'_key'!$A$858)<=0.005,FALSE),"✓","✗")) -> 0
A99: ACC-0100 | X99: =IF(ISBLANK(H99),"",IF(IFERROR(ABS(H99-'_key'!$A$859)<=5e-05,FALSE),"✓","✗")) -> 0 | Y99: =IF(ISBLANK(K99),"",IF(IFERROR(ABS(K99-'_key'!$A$860)<=5e-05,FALSE),"✓","✗")) -> 0 | Z99: =IF(ISBLANK(L99),"",IF(IFERROR(ABS(L99-'_key'!$A$861)<=0.005,FALSE),"✓","✗")) -> 0 | AA99: =IF(ISBLANK(M99),"",IF(IFERROR(EXACT(M99,'_key'!$A$862),FALSE),"✓","✗")) -> 0 | AB99: =IF(ISBLANK(S99),"",IF(IFERROR(ABS(S99-'_key'!$A$863)<=0.01,FALSE),"✓","✗")) -> 0 | AC99: =IF(ISBLANK(T99),"",IF(IFERROR(EXACT(T99,'_key'!$A$864),FALSE),"✓","✗")) -> 0 | AD99: =IF(ISBLANK(V99),"",IF(IFERROR(ABS(V99-'_key'!$A$865)<=0.005,FALSE),"✓","✗")) -> 0
A100: ACC-0101 | X100: =IF(ISBLANK(H100),"",IF(IFERROR(ABS(H100-'_key'!$A$866)<=5e-05,FALSE),"✓","✗")) -> 0 | Y100: =IF(ISBLANK(K100),"",IF(IFERROR(ABS(K100-'_key'!$A$867)<=5e-05,FALSE),"✓","✗")) -> 0 | Z100: =IF(ISBLANK(L100),"",IF(IFERROR(ABS(L100-'_key'!$A$868)<=0.005,FALSE),"✓","✗")) -> 0 | AA100: =IF(ISBLANK(M100),"",IF(IFERROR(EXACT(M100,'_key'!$A$869),FALSE),"✓","✗")) -> 0 | AB100: =IF(ISBLANK(S100),"",IF(IFERROR(ABS(S100-'_key'!$A$870)<=0.01,FALSE),"✓","✗")) -> 0 | AC100: =IF(ISBLANK(T100),"",IF(IFERROR(EXACT(T100,'_key'!$A$871),FALSE),"✓","✗")) -> 0 | AD100: =IF(ISBLANK(V100),"",IF(IFERROR(ABS(V100-'_key'!$A$872)<=0.005,FALSE),"✓","✗")) -> 0
A101: ACC-0102 | X101: =IF(ISBLANK(H101),"",IF(IFERROR(ABS(H101-'_key'!$A$873)<=5e-05,FALSE),"✓","✗")) -> 0 | Y101: =IF(ISBLANK(K101),"",IF(IFERROR(ABS(K101-'_key'!$A$874)<=5e-05,FALSE),"✓","✗")) -> 0 | Z101: =IF(ISBLANK(L101),"",IF(IFERROR(ABS(L101-'_key'!$A$875)<=0.005,FALSE),"✓","✗")) -> 0 | AA101: =IF(ISBLANK(M101),"",IF(IFERROR(ABS(M101-'_key'!$A$876)<=0.005,FALSE),"✓","✗")) -> 0 | AB101: =IF(ISBLANK(S101),"",IF(IFERROR(ABS(S101-'_key'!$A$877)<=0.01,FALSE),"✓","✗")) -> 0 | AC101: =IF(ISBLANK(T101),"",IF(IFERROR(EXACT(T101,'_key'!$A$878),FALSE),"✓","✗")) -> 0 | AD101: =IF(ISBLANK(V101),"",IF(IFERROR(ABS(V101-'_key'!$A$879)<=0.005,FALSE),"✓","✗")) -> 0
...

Sheet E4_Auditoria_Reportes
A1: E4 · Auditoría del uso de reportes
A2: Objetivo: con el log de uso (Report_Usage_Log) y el inventario (Report_Catalog) mide cuánto se usa realmente cada reporte, cuánto cuesta mantenerlo y genera una recomendación: Retirar, Consolidar, Automatizar o Mantener. Luego resume cuántas horas se liberarían.
A3: Contexto: la vacante pide 'analizar y auditar' los reportes actuales para saber qué mejorar, quitar o agregar. Fíjate en reportes duplicados (Login v1 vs v2, 'Copy of...'), reportes ad hoc que se piden tanto que conviene automatizarlos y reportes contractuales que nadie abre (¿se envían por otro lado?).
W4: Resumen para liderazgo
A5: ReportID | B5: ReportName | C5: Type | D5: Frequency | E5: Views (180d) | F5: Exports (180d) | G5: Usuarios únicos | H5: Último uso | I5: Días sin uso | J5: Views últimos 90d | K5: Horas mant./mes | L5: Costo por vista (USD) | M5: Recomendación | O5: ✓E | P5: ✓F | Q5: ✓G | R5: ✓H | S5: ✓J | T5: ✓L | U5: ✓M | W5: Recomendación | X5: # Reportes | Y5: Horas/mes | Z5: Chk
A6: Dado | B6: XLOOKUP | C6: XLOOKUP | D6: XLOOKUP | E6: COUNTIFS(tbl_ReportLog[ReportID], A7, ...[Action], "View") | F6: Igual con "Export" | G6: IFERROR(ROWS(UNIQUE(FILTER(tbl_ReportLog[UserEmail], tbl_ReportLog[ReportID]=A7))), 0) | H6: Si no hay registros → ""; si no MAXIFS(tbl_ReportLog[Date], ...) | I6: IF(H7="", "", AsOfDate − H7) | J6: COUNTIFS(..., "View", ...[Date], ">"&AsOfDate-90) | K6: XLOOKUP MaintHrsPerMonth | L6: IFERROR(K7*6*CostPerHour/E7, "") | M6: IFS: Contractual→"Mantener (contractual)"; J=0→"Retirar"; J<10→"Consolidar / revisar"; Ad hoc y J≥30→"Automatizar"; si no "Mantener" | X6: COUNTIF($M$7:$M$n, W7) | Y6: SUMIF(..., $K$7:$K$n)
A7: RPT-001 | O7: =IF(ISBLANK(E7),"",IF(IFERROR(ABS(E7-'_key'!$A$1198)<=0.005,FALSE),"✓","✗")) -> 0 | P7: =IF(ISBLANK(F7),"",IF(IFERROR(ABS(F7-'_key'!$A$1199)<=0.005,FALSE),"✓","✗")) -> 0 | Q7: =IF(ISBLANK(G7),"",IF(IFERROR(ABS(G7-'_key'!$A$1200)<=0.005,FALSE),"✓","✗")) -> 0 | R7: =IF(ISBLANK(H7),"",IF(IFERROR(ABS(H7-'_key'!$A$1201)<=0.005,FALSE),"✓","✗")) -> 0 | S7: =IF(ISBLANK(J7),"",IF(IFERROR(ABS(J7-'_key'!$A$1202)<=0.005,FALSE),"✓","✗")) -> 0 | T7: =IF(ISBLANK(L7),"",IF(IFERROR(ABS(L7-'_key'!$A$1203)<=0.01,FALSE),"✓","✗")) -> 0 | U7: =IF(ISBLANK(M7),"",IF(IFERROR(EXACT(M7,'_key'!$A$1204),FALSE),"✓","✗")) -> 0 | W7: Retirar | Z7: =IF(ISBLANK(X7),"",IF(IFERROR(ABS(X7-'_key'!$A$1450)<=0.005,FALSE),"✓","✗")) -> 0
A8: RPT-002 | O8: =IF(ISBLANK(E8),"",IF(IFERROR(ABS(E8-'_key'!$A$1205)<=0.005,FALSE),"✓","✗")) -> 0 | P8: =IF(ISBLANK(F8),"",IF(IFERROR(ABS(F8-'_key'!$A$1206)<=0.005,FALSE),"✓","✗")) -> 0 | Q8: =IF(ISBLANK(G8),"",IF(IFERROR(ABS(G8-'_key'!$A$1207)<=0.005,FALSE),"✓","✗")) -> 0 | R8: =IF(ISBLANK(H8),"",IF(IFERROR(ABS(H8-'_key'!$A$1208)<=0.005,FALSE),"✓","✗")) -> 0 | S8: =IF(ISBLANK(J8),"",IF(IFERROR(ABS(J8-'_key'!$A$1209)<=0.005,FALSE),"✓","✗")) -> 0 | T8: =IF(ISBLANK(L8),"",IF(IFERROR(ABS(L8-'_key'!$A$1210)<=0.01,FALSE),"✓","✗")) -> 0 | U8: =IF(ISBLANK(M8),"",IF(IFERROR(EXACT(M8,'_key'!$A$1211),FALSE),"✓","✗")) -> 0 | W8: Consolidar / revisar | Z8: =IF(ISBLANK(X8),"",IF(IFERROR(ABS(X8-'_key'!$A$1452)<=0.005,FALSE),"✓","✗")) -> 0
A9: RPT-003 | O9: =IF(ISBLANK(E9),"",IF(IFERROR(ABS(E9-'_key'!$A$1212)<=0.005,FALSE),"✓","✗")) -> 0 | P9: =IF(ISBLANK(F9),"",IF(IFERROR(ABS(F9-'_key'!$A$1213)<=0.005,FALSE),"✓","✗")) -> 0 | Q9: =IF(ISBLANK(G9),"",IF(IFERROR(ABS(G9-'_key'!$A$1214)<=0.005,FALSE),"✓","✗")) -> 0 | R9: =IF(ISBLANK(H9),"",IF(IFERROR(ABS(H9-'_key'!$A$1215)<=0.005,FALSE),"✓","✗")) -> 0 | S9: =IF(ISBLANK(J9),"",IF(IFERROR(ABS(J9-'_key'!$A$1216)<=0.005,FALSE),"✓","✗")) -> 0 | T9: =IF(ISBLANK(L9),"",IF(IFERROR(ABS(L9-'_key'!$A$1217)<=0.01,FALSE),"✓","✗")) -> 0 | U9: =IF(ISBLANK(M9),"",IF(IFERROR(EXACT(M9,'_key'!$A$1218),FALSE),"✓","✗")) -> 0 | W9: Automatizar | Z9: =IF(ISBLANK(X9),"",IF(IFERROR(ABS(X9-'_key'!$A$1454)<=0.005,FALSE),"✓","✗")) -> 0
A10: RPT-004 | O10: =IF(ISBLANK(E10),"",IF(IFERROR(ABS(E10-'_key'!$A$1219)<=0.005,FALSE),"✓","✗")) -> 0 | P10: =IF(ISBLANK(F10),"",IF(IFERROR(ABS(F10-'_key'!$A$1220)<=0.005,FALSE),"✓","✗")) -> 0 | Q10: =IF(ISBLANK(G10),"",IF(IFERROR(ABS(G10-'_key'!$A$1221)<=0.005,FALSE),"✓","✗")) -> 0 | R10: =IF(ISBLANK(H10),"",IF(IFERROR(ABS(H10-'_key'!$A$1222)<=0.005,FALSE),"✓","✗")) -> 0 | S10: =IF(ISBLANK(J10),"",IF(IFERROR(ABS(J10-'_key'!$A$1223)<=0.005,FALSE),"✓","✗")) -> 0 | T10: =IF(ISBLANK(L10),"",IF(IFERROR(ABS(L10-'_key'!$A$1224)<=0.01,FALSE),"✓","✗")) -> 0 | U10: =IF(ISBLANK(M10),"",IF(IFERROR(EXACT(M10,'_key'!$A$1225),FALSE),"✓","✗")) -> 0 | W10: Mantener | Z10: =IF(ISBLANK(X10),"",IF(IFERROR(ABS(X10-'_key'!$A$1456)<=0.005,FALSE),"✓","✗")) -> 0
A11: RPT-005 | O11: =IF(ISBLANK(E11),"",IF(IFERROR(ABS(E11-'_key'!$A$1226)<=0.005,FALSE),"✓","✗")) -> 0 | P11: =IF(ISBLANK(F11),"",IF(IFERROR(ABS(F11-'_key'!$A$1227)<=0.005,FALSE),"✓","✗")) -> 0 | Q11: =IF(ISBLANK(G11),"",IF(IFERROR(ABS(G11-'_key'!$A$1228)<=0.005,FALSE),"✓","✗")) -> 0 | R11: =IF(ISBLANK(H11),"",IF(IFERROR(ABS(H11-'_key'!$A$1229)<=0.005,FALSE),"✓","✗")) -> 0 | S11: =IF(ISBLANK(J11),"",IF(IFERROR(ABS(J11-'_key'!$A$1230)<=0.005,FALSE),"✓","✗")) -> 0 | T11: =IF(ISBLANK(L11),"",IF(IFERROR(ABS(L11-'_key'!$A$1231)<=0.01,FALSE),"✓","✗")) -> 0 | U11: =IF(ISBLANK(M11),"",IF(IFERROR(EXACT(M11,'_key'!$A$1232),FALSE),"✓","✗")) -> 0 | W11: Mantener (contractual) | Z11: =IF(ISBLANK(X11),"",IF(IFERROR(ABS(X11-'_key'!$A$1458)<=0.005,FALSE),"✓","✗")) -> 0
A12: RPT-006 | O12: =IF(ISBLANK(E12),"",IF(IFERROR(ABS(E12-'_key'!$A$1233)<=0.005,FALSE),"✓","✗")) -> 0 | P12: =IF(ISBLANK(F12),"",IF(IFERROR(ABS(F12-'_key'!$A$1234)<=0.005,FALSE),"✓","✗")) -> 0 | Q12: =IF(ISBLANK(G12),"",IF(IFERROR(ABS(G12-'_key'!$A$1235)<=0.005,FALSE),"✓","✗")) -> 0 | R12: =IF(ISBLANK(H12),"",IF(IFERROR(ABS(H12-'_key'!$A$1236)<=0.005,FALSE),"✓","✗")) -> 0 | S12: =IF(ISBLANK(J12),"",IF(IFERROR(ABS(J12-'_key'!$A$1237)<=0.005,FALSE),"✓","✗")) -> 0 | T12: =IF(ISBLANK(L12),"",IF(IFERROR(ABS(L12-'_key'!$A$1238)<=0.01,FALSE),"✓","✗")) -> 0 | U12: =IF(ISBLANK(M12),"",IF(IFERROR(EXACT(M12,'_key'!$A$1239),FALSE),"✓","✗")) -> 0 | W12: ✓ de Horas/mes →
A13: RPT-007 | O13: =IF(ISBLANK(E13),"",IF(IFERROR(ABS(E13-'_key'!$A$1240)<=0.005,FALSE),"✓","✗")) -> 0 | P13: =IF(ISBLANK(F13),"",IF(IFERROR(ABS(F13-'_key'!$A$1241)<=0.005,FALSE),"✓","✗")) -> 0 | Q13: =IF(ISBLANK(G13),"",IF(IFERROR(ABS(G13-'_key'!$A$1242)<=0.005,FALSE),"✓","✗")) -> 0 | R13: =IF(ISBLANK(H13),"",IF(IFERROR(ABS(H13-'_key'!$A$1243)<=0.005,FALSE),"✓","✗")) -> 0 | S13: =IF(ISBLANK(J13),"",IF(IFERROR(ABS(J13-'_key'!$A$1244)<=0.005,FALSE),"✓","✗")) -> 0 | T13: =IF(ISBLANK(L13),"",IF(IFERROR(ABS(L13-'_key'!$A$1245)<=0.01,FALSE),"✓","✗")) -> 0 | U13: =IF(ISBLANK(M13),"",IF(IFERROR(EXACT(M13,'_key'!$A$1246),FALSE),"✓","✗")) -> 0 | Z13: =IF(ISBLANK(Y7),"",IF(IFERROR(ABS(Y7-'_key'!$A$1451)<=0.005,FALSE),"✓","✗")) -> 0
A14: RPT-008 | O14: =IF(ISBLANK(E14),"",IF(IFERROR(ABS(E14-'_key'!$A$1247)<=0.005,FALSE),"✓","✗")) -> 0 | P14: =IF(ISBLANK(F14),"",IF(IFERROR(ABS(F14-'_key'!$A$1248)<=0.005,FALSE),"✓","✗")) -> 0 | Q14: =IF(ISBLANK(G14),"",IF(IFERROR(ABS(G14-'_key'!$A$1249)<=0.005,FALSE),"✓","✗")) -> 0 | R14: =IF(ISBLANK(H14),"",IF(IFERROR(EXACT(H14,'_key'!$A$1250),FALSE),"✓","✗")) -> 0 | S14: =IF(ISBLANK(J14),"",IF(IFERROR(ABS(J14-'_key'!$A$1251)<=0.005,FALSE),"✓","✗")) -> 0 | T14: =IF(ISBLANK(L14),"",IF(IFERROR(EXACT(L14,'_key'!$A$1252),FALSE),"✓","✗")) -> 0 | U14: =IF(ISBLANK(M14),"",IF(IFERROR(EXACT(M14,'_key'!$A$1253),FALSE),"✓","✗")) -> 0 | Z14: =IF(ISBLANK(Y8),"",IF(IFERROR(ABS(Y8-'_key'!$A$1453)<=0.005,FALSE),"✓","✗")) -> 0
A15: RPT-009 | O15: =IF(ISBLANK(E15),"",IF(IFERROR(ABS(E15-'_key'!$A$1254)<=0.005,FALSE),"✓","✗")) -> 0 | P15: =IF(ISBLANK(F15),"",IF(IFERROR(ABS(F15-'_key'!$A$1255)<=0.005,FALSE),"✓","✗")) -> 0 | Q15: =IF(ISBLANK(G15),"",IF(IFERROR(ABS(G15-'_key'!$A$1256)<=0.005,FALSE),"✓","✗")) -> 0 | R15: =IF(ISBLANK(H15),"",IF(IFERROR(ABS(H15-'_key'!$A$1257)<=0.005,FALSE),"✓","✗")) -> 0 | S15: =IF(ISBLANK(J15),"",IF(IFERROR(ABS(J15-'_key'!$A$1258)<=0.005,FALSE),"✓","✗")) -> 0 | T15: =IF(ISBLANK(L15),"",IF(IFERROR(ABS(L15-'_key'!$A$1259)<=0.01,FALSE),"✓","✗")) -> 0 | U15: =IF(ISBLANK(M15),"",IF(IFERROR(EXACT(M15,'_key'!$A$1260),FALSE),"✓","✗")) -> 0 | Z15: =IF(ISBLANK(Y9),"",IF(IFERROR(ABS(Y9-'_key'!$A$1455)<=0.005,FALSE),"✓","✗")) -> 0
A16: RPT-010 | O16: =IF(ISBLANK(E16),"",IF(IFERROR(ABS(E16-'_key'!$A$1261)<=0.005,FALSE),"✓","✗")) -> 0 | P16: =IF(ISBLANK(F16),"",IF(IFERROR(ABS(F16-'_key'!$A$1262)<=0.005,FALSE),"✓","✗")) -> 0 | Q16: =IF(ISBLANK(G16),"",IF(IFERROR(ABS(G16-'_key'!$A$1263)<=0.005,FALSE),"✓","✗")) -> 0 | R16: =IF(ISBLANK(H16),"",IF(IFERROR(ABS(H16-'_key'!$A$1264)<=0.005,FALSE),"✓","✗")) -> 0 | S16: =IF(ISBLANK(J16),"",IF(IFERROR(ABS(J16-'_key'!$A$1265)<=0.005,FALSE),"✓","✗")) -> 0 | T16: =IF(ISBLANK(L16),"",IF(IFERROR(ABS(L16-'_key'!$A$1266)<=0.01,FALSE),"✓","✗")) -> 0 | U16: =IF(ISBLANK(M16),"",IF(IFERROR(EXACT(M16,'_key'!$A$1267),FALSE),"✓","✗")) -> 0 | Z16: =IF(ISBLANK(Y10),"",IF(IFERROR(ABS(Y10-'_key'!$A$1457)<=0.005,FALSE),"✓","✗")) -> 0
A17: RPT-011 | O17: =IF(ISBLANK(E17),"",IF(IFERROR(ABS(E17-'_key'!$A$1268)<=0.005,FALSE),"✓","✗")) -> 0 | P17: =IF(ISBLANK(F17),"",IF(IFERROR(ABS(F17-'_key'!$A$1269)<=0.005,FALSE),"✓","✗")) -> 0 | Q17: =IF(ISBLANK(G17),"",IF(IFERROR(ABS(G17-'_key'!$A$1270)<=0.005,FALSE),"✓","✗")) -> 0 | R17: =IF(ISBLANK(H17),"",IF(IFERROR(ABS(H17-'_key'!$A$1271)<=0.005,FALSE),"✓","✗")) -> 0 | S17: =IF(ISBLANK(J17),"",IF(IFERROR(ABS(J17-'_key'!$A$1272)<=0.005,FALSE),"✓","✗")) -> 0 | T17: =IF(ISBLANK(L17),"",IF(IFERROR(ABS(L17-'_key'!$A$1273)<=0.01,FALSE),"✓","✗")) -> 0 | U17: =IF(ISBLANK(M17),"",IF(IFERROR(EXACT(M17,'_key'!$A$1274),FALSE),"✓","✗")) -> 0 | Z17: =IF(ISBLANK(Y11),"",IF(IFERROR(ABS(Y11-'_key'!$A$1459)<=0.005,FALSE),"✓","✗")) -> 0
A18: RPT-012 | O18: =IF(ISBLANK(E18),"",IF(IFERROR(ABS(E18-'_key'!$A$1275)<=0.005,FALSE),"✓","✗")) -> 0 | P18: =IF(ISBLANK(F18),"",IF(IFERROR(ABS(F18-'_key'!$A$1276)<=0.005,FALSE),"✓","✗")) -> 0 | Q18: =IF(ISBLANK(G18),"",IF(IFERROR(ABS(G18-'_key'!$A$1277)<=0.005,FALSE),"✓","✗")) -> 0 | R18: =IF(ISBLANK(H18),"",IF(IFERROR(ABS(H18-'_key'!$A$1278)<=0.005,FALSE),"✓","✗")) -> 0 | S18: =IF(ISBLANK(J18),"",IF(IFERROR(ABS(J18-'_key'!$A$1279)<=0.005,FALSE),"✓","✗")) -> 0 | T18: =IF(ISBLANK(L18),"",IF(IFERROR(ABS(L18-'_key'!$A$1280)<=0.01,FALSE),"✓","✗")) -> 0 | U18: =IF(ISBLANK(M18),"",IF(IFERROR(EXACT(M18,'_key'!$A$1281),FALSE),"✓","✗")) -> 0
A19: RPT-013 | O19: =IF(ISBLANK(E19),"",IF(IFERROR(ABS(E19-'_key'!$A$1282)<=0.005,FALSE),"✓","✗")) -> 0 | P19: =IF(ISBLANK(F19),"",IF(IFERROR(ABS(F19-'_key'!$A$1283)<=0.005,FALSE),"✓","✗")) -> 0 | Q19: =IF(ISBLANK(G19),"",IF(IFERROR(ABS(G19-'_key'!$A$1284)<=0.005,FALSE),"✓","✗")) -> 0 | R19: =IF(ISBLANK(H19),"",IF(IFERROR(ABS(H19-'_key'!$A$1285)<=0.005,FALSE),"✓","✗")) -> 0 | S19: =IF(ISBLANK(J19),"",IF(IFERROR(ABS(J19-'_key'!$A$1286)<=0.005,FALSE),"✓","✗")) -> 0 | T19: =IF(ISBLANK(L19),"",IF(IFERROR(ABS(L19-'_key'!$A$1287)<=0.01,FALSE),"✓","✗")) -> 0 | U19: =IF(ISBLANK(M19),"",IF(IFERROR(EXACT(M19,'_key'!$A$1288),FALSE),"✓","✗")) -> 0 | W19: Ahorro anual si se retiran (USD) | Z19: =IF(ISBLANK(Y19),"",IF(IFERROR(ABS(Y19-'_key'!$A$1460)<=0.005,FALSE),"✓","✗")) -> 0
A20: RPT-014 | O20: =IF(ISBLANK(E20),"",IF(IFERROR(ABS(E20-'_key'!$A$1289)<=0.005,FALSE),"✓","✗")) -> 0 | P20: =IF(ISBLANK(F20),"",IF(IFERROR(ABS(F20-'_key'!$A$1290)<=0.005,FALSE),"✓","✗")) -> 0 | Q20: =IF(ISBLANK(G20),"",IF(IFERROR(ABS(G20-'_key'!$A$1291)<=0.005,FALSE),"✓","✗")) -> 0 | R20: =IF(ISBLANK(H20),"",IF(IFERROR(ABS(H20-'_key'!$A$1292)<=0.005,FALSE),"✓","✗")) -> 0 | S20: =IF(ISBLANK(J20),"",IF(IFERROR(ABS(J20-'_key'!$A$1293)<=0.005,FALSE),"✓","✗")) -> 0 | T20: =IF(ISBLANK(L20),"",IF(IFERROR(ABS(L20-'_key'!$A$1294)<=0.01,FALSE),"✓","✗")) -> 0 | U20: =IF(ISBLANK(M20),"",IF(IFERROR(EXACT(M20,'_key'!$A$1295),FALSE),"✓","✗")) -> 0 | W20: % reportes sin views en 90 días | Z20: =IF(ISBLANK(Y20),"",IF(IFERROR(ABS(Y20-'_key'!$A$1461)<=0.0005,FALSE),"✓","✗")) -> 0
A21: RPT-015 | O21: =IF(ISBLANK(E21),"",IF(IFERROR(ABS(E21-'_key'!$A$1296)<=0.005,FALSE),"✓","✗")) -> 0 | P21: =IF(ISBLANK(F21),"",IF(IFERROR(ABS(F21-'_key'!$A$1297)<=0.005,FALSE),"✓","✗")) -> 0 | Q21: =IF(ISBLANK(G21),"",IF(IFERROR(ABS(G21-'_key'!$A$1298)<=0.005,FALSE),"✓","✗")) -> 0 | R21: =IF(ISBLANK(H21),"",IF(IFERROR(ABS(H21-'_key'!$A$1299)<=0.005,FALSE),"✓","✗")) -> 0 | S21: =IF(ISBLANK(J21),"",IF(IFERROR(ABS(J21-'_key'!$A$1300)<=0.005,FALSE),"✓","✗")) -> 0 | T21: =IF(ISBLANK(L21),"",IF(IFERROR(ABS(L21-'_key'!$A$1301)<=0.01,FALSE),"✓","✗")) -> 0 | U21: =IF(ISBLANK(M21),"",IF(IFERROR(EXACT(M21,'_key'!$A$1302),FALSE),"✓","✗")) -> 0
A22: RPT-016 | O22: =IF(ISBLANK(E22),"",IF(IFERROR(ABS(E22-'_key'!$A$1303)<=0.005,FALSE),"✓","✗")) -> 0 | P22: =IF(ISBLANK(F22),"",IF(IFERROR(ABS(F22-'_key'!$A$1304)<=0.005,FALSE),"✓","✗")) -> 0 | Q22: =IF(ISBLANK(G22),"",IF(IFERROR(ABS(G22-'_key'!$A$1305)<=0.005,FALSE),"✓","✗")) -> 0 | R22: =IF(ISBLANK(H22),"",IF(IFERROR(ABS(H22-'_key'!$A$1306)<=0.005,FALSE),"✓","✗")) -> 0 | S22: =IF(ISBLANK(J22),"",IF(IFERROR(ABS(J22-'_key'!$A$1307)<=0.005,FALSE),"✓","✗")) -> 0 | T22: =IF(ISBLANK(L22),"",IF(IFERROR(ABS(L22-'_key'!$A$1308)<=0.01,FALSE),"✓","✗")) -> 0 | U22: =IF(ISBLANK(M22),"",IF(IFERROR(EXACT(M22,'_key'!$A$1309),FALSE),"✓","✗")) -> 0 | W22: ¿Quién consume los reportes? (views por rol)
A23: RPT-017 | O23: =IF(ISBLANK(E23),"",IF(IFERROR(ABS(E23-'_key'!$A$1310)<=0.005,FALSE),"✓","✗")) -> 0 | P23: =IF(ISBLANK(F23),"",IF(IFERROR(ABS(F23-'_key'!$A$1311)<=0.005,FALSE),"✓","✗")) -> 0 | Q23: =IF(ISBLANK(G23),"",IF(IFERROR(ABS(G23-'_key'!$A$1312)<=0.005,FALSE),"✓","✗")) -> 0 | R23: =IF(ISBLANK(H23),"",IF(IFERROR(ABS(H23-'_key'!$A$1313)<=0.005,FALSE),"✓","✗")) -> 0 | S23: =IF(ISBLANK(J23),"",IF(IFERROR(ABS(J23-'_key'!$A$1314)<=0.005,FALSE),"✓","✗")) -> 0 | T23: =IF(ISBLANK(L23),"",IF(IFERROR(ABS(L23-'_key'!$A$1315)<=0.01,FALSE),"✓","✗")) -> 0 | U23: =IF(ISBLANK(M23),"",IF(IFERROR(EXACT(M23,'_key'!$A$1316),FALSE),"✓","✗")) -> 0 | W23: UserRole | X23: Views | Y23: % del total | Z23: Chk
A24: RPT-018 | O24: =IF(ISBLANK(E24),"",IF(IFERROR(ABS(E24-'_key'!$A$1317)<=0.005,FALSE),"✓","✗")) -> 0 | P24: =IF(ISBLANK(F24),"",IF(IFERROR(ABS(F24-'_key'!$A$1318)<=0.005,FALSE),"✓","✗")) -> 0 | Q24: =IF(ISBLANK(G24),"",IF(IFERROR(ABS(G24-'_key'!$A$1319)<=0.005,FALSE),"✓","✗")) -> 0 | R24: =IF(ISBLANK(H24),"",IF(IFERROR(ABS(H24-'_key'!$A$1320)<=0.005,FALSE),"✓","✗")) -> 0 | S24: =IF(ISBLANK(J24),"",IF(IFERROR(ABS(J24-'_key'!$A$1321)<=0.005,FALSE),"✓","✗")) -> 0 | T24: =IF(ISBLANK(L24),"",IF(IFERROR(ABS(L24-'_key'!$A$1322)<=0.01,FALSE),"✓","✗")) -> 0 | U24: =IF(ISBLANK(M24),"",IF(IFERROR(EXACT(M24,'_key'!$A$1323),FALSE),"✓","✗")) -> 0 | X24: COUNTIFS(...[UserRole], W24, ...[Action], "View") | Y24: X / SUM(X)
A25: RPT-019 | O25: =IF(ISBLANK(E25),"",IF(IFERROR(ABS(E25-'_key'!$A$1324)<=0.005,FALSE),"✓","✗")) -> 0 | P25: =IF(ISBLANK(F25),"",IF(IFERROR(ABS(F25-'_key'!$A$1325)<=0.005,FALSE),"✓","✗")) -> 0 | Q25: =IF(ISBLANK(G25),"",IF(IFERROR(ABS(G25-'_key'!$A$1326)<=0.005,FALSE),"✓","✗")) -> 0 | R25: =IF(ISBLANK(H25),"",IF(IFERROR(ABS(H25-'_key'!$A$1327)<=0.005,FALSE),"✓","✗")) -> 0 | S25: =IF(ISBLANK(J25),"",IF(IFERROR(ABS(J25-'_key'!$A$1328)<=0.005,FALSE),"✓","✗")) -> 0 | T25: =IF(ISBLANK(L25),"",IF(IFERROR(ABS(L25-'_key'!$A$1329)<=0.01,FALSE),"✓","✗")) -> 0 | U25: =IF(ISBLANK(M25),"",IF(IFERROR(EXACT(M25,'_key'!$A$1330),FALSE),"✓","✗")) -> 0 | W25: CSM | Z25: =IF(ISBLANK(X25),"",IF(IFERROR(ABS(X25-'_key'!$A$1462)<=0.005,FALSE),"✓","✗")) -> 0
A26: RPT-020 | O26: =IF(ISBLANK(E26),"",IF(IFERROR(ABS(E26-'_key'!$A$1331)<=0.005,FALSE),"✓","✗")) -> 0 | P26: =IF(ISBLANK(F26),"",IF(IFERROR(ABS(F26-'_key'!$A$1332)<=0.005,FALSE),"✓","✗")) -> 0 | Q26: =IF(ISBLANK(G26),"",IF(IFERROR(ABS(G26-'_key'!$A$1333)<=0.005,FALSE),"✓","✗")) -> 0 | R26: =IF(ISBLANK(H26),"",IF(IFERROR(EXACT(H26,'_key'!$A$1334),FALSE),"✓","✗")) -> 0 | S26: =IF(ISBLANK(J26),"",IF(IFERROR(ABS(J26-'_key'!$A$1335)<=0.005,FALSE),"✓","✗")) -> 0 | T26: =IF(ISBLANK(L26),"",IF(IFERROR(EXACT(L26,'_key'!$A$1336),FALSE),"✓","✗")) -> 0 | U26: =IF(ISBLANK(M26),"",IF(IFERROR(EXACT(M26,'_key'!$A$1337),FALSE),"✓","✗")) -> 0 | W26: Account Manager | Z26: =IF(ISBLANK(X26),"",IF(IFERROR(ABS(X26-'_key'!$A$1463)<=0.005,FALSE),"✓","✗")) -> 0
A27: RPT-021 | O27: =IF(ISBLANK(E27),"",IF(IFERROR(ABS(E27-'_key'!$A$1338)<=0.005,FALSE),"✓","✗")) -> 0 | P27: =IF(ISBLANK(F27),"",IF(IFERROR(ABS(F27-'_key'!$A$1339)<=0.005,FALSE),"✓","✗")) -> 0 | Q27: =IF(ISBLANK(G27),"",IF(IFERROR(ABS(G27-'_key'!$A$1340)<=0.005,FALSE),"✓","✗")) -> 0 | R27: =IF(ISBLANK(H27),"",IF(IFERROR(ABS(H27-'_key'!$A$1341)<=0.005,FALSE),"✓","✗")) -> 0 | S27: =IF(ISBLANK(J27),"",IF(IFERROR(ABS(J27-'_key'!$A$1342)<=0.005,FALSE),"✓","✗")) -> 0 | T27: =IF(ISBLANK(L27),"",IF(IFERROR(ABS(L27-'_key'!$A$1343)<=0.01,FALSE),"✓","✗")) -> 0 | U27: =IF(ISBLANK(M27),"",IF(IFERROR(EXACT(M27,'_key'!$A$1344),FALSE),"✓","✗")) -> 0 | W27: CS Leadership | Z27: =IF(ISBLANK(X27),"",IF(IFERROR(ABS(X27-'_key'!$A$1464)<=0.005,FALSE),"✓","✗")) -> 0
A28: RPT-022 | O28: =IF(ISBLANK(E28),"",IF(IFERROR(ABS(E28-'_key'!$A$1345)<=0.005,FALSE),"✓","✗")) -> 0 | P28: =IF(ISBLANK(F28),"",IF(IFERROR(ABS(F28-'_key'!$A$1346)<=0.005,FALSE),"✓","✗")) -> 0 | Q28: =IF(ISBLANK(G28),"",IF(IFERROR(ABS(G28-'_key'!$A$1347)<=0.005,FALSE),"✓","✗")) -> 0 | R28: =IF(ISBLANK(H28),"",IF(IFERROR(ABS(H28-'_key'!$A$1348)<=0.005,FALSE),"✓","✗")) -> 0 | S28: =IF(ISBLANK(J28),"",IF(IFERROR(ABS(J28-'_key'!$A$1349)<=0.005,FALSE),"✓","✗")) -> 0 | T28: =IF(ISBLANK(L28),"",IF(IFERROR(ABS(L28-'_key'!$A$1350)<=0.01,FALSE),"✓","✗")) -> 0 | U28: =IF(ISBLANK(M28),"",IF(IFERROR(EXACT(M28,'_key'!$A$1351),FALSE),"✓","✗")) -> 0 | W28: Executive | Z28: =IF(ISBLANK(X28),"",IF(IFERROR(ABS(X28-'_key'!$A$1465)<=0.005,FALSE),"✓","✗")) -> 0
A29: RPT-023 | O29: =IF(ISBLANK(E29),"",IF(IFERROR(ABS(E29-'_key'!$A$1352)<=0.005,FALSE),"✓","✗")) -> 0 | P29: =IF(ISBLANK(F29),"",IF(IFERROR(ABS(F29-'_key'!$A$1353)<=0.005,FALSE),"✓","✗")) -> 0 | Q29: =IF(ISBLANK(G29),"",IF(IFERROR(ABS(G29-'_key'!$A$1354)<=0.005,FALSE),"✓","✗")) -> 0 | R29: =IF(ISBLANK(H29),"",IF(IFERROR(ABS(H29-'_key'!$A$1355)<=0.005,FALSE),"✓","✗")) -> 0 | S29: =IF(ISBLANK(J29),"",IF(IFERROR(ABS(J29-'_key'!$A$1356)<=0.005,FALSE),"✓","✗")) -> 0 | T29: =IF(ISBLANK(L29),"",IF(IFERROR(ABS(L29-'_key'!$A$1357)<=0.01,FALSE),"✓","✗")) -> 0 | U29: =IF(ISBLANK(M29),"",IF(IFERROR(EXACT(M29,'_key'!$A$1358),FALSE),"✓","✗")) -> 0 | W29: Support | Z29: =IF(ISBLANK(X29),"",IF(IFERROR(ABS(X29-'_key'!$A$1466)<=0.005,FALSE),"✓","✗")) -> 0
A30: RPT-024 | O30: =IF(ISBLANK(E30),"",IF(IFERROR(ABS(E30-'_key'!$A$1359)<=0.005,FALSE),"✓","✗")) -> 0 | P30: =IF(ISBLANK(F30),"",IF(IFERROR(ABS(F30-'_key'!$A$1360)<=0.005,FALSE),"✓","✗")) -> 0 | Q30: =IF(ISBLANK(G30),"",IF(IFERROR(ABS(G30-'_key'!$A$1361)<=0.005,FALSE),"✓","✗")) -> 0 | R30: =IF(ISBLANK(H30),"",IF(IFERROR(ABS(H30-'_key'!$A$1362)<=0.005,FALSE),"✓","✗")) -> 0 | S30: =IF(ISBLANK(J30),"",IF(IFERROR(ABS(J30-'_key'!$A$1363)<=0.005,FALSE),"✓","✗")) -> 0 | T30: =IF(ISBLANK(L30),"",IF(IFERROR(ABS(L30-'_key'!$A$1364)<=0.01,FALSE),"✓","✗")) -> 0 | U30: =IF(ISBLANK(M30),"",IF(IFERROR(EXACT(M30,'_key'!$A$1365),FALSE),"✓","✗")) -> 0 | W30: Product | Z30: =IF(ISBLANK(X30),"",IF(IFERROR(ABS(X30-'_key'!$A$1467)<=0.005,FALSE),"✓","✗")) -> 0
A31: RPT-025 | O31: =IF(ISBLANK(E31),"",IF(IFERROR(ABS(E31-'_key'!$A$1366)<=0.005,FALSE),"✓","✗")) -> 0 | P31: =IF(ISBLANK(F31),"",IF(IFERROR(ABS(F31-'_key'!$A$1367)<=0.005,FALSE),"✓","✗")) -> 0 | Q31: =IF(ISBLANK(G31),"",IF(IFERROR(ABS(G31-'_key'!$A$1368)<=0.005,FALSE),"✓","✗")) -> 0 | R31: =IF(ISBLANK(H31),"",IF(IFERROR(ABS(H31-'_key'!$A$1369)<=0.005,FALSE),"✓","✗")) -> 0 | S31: =IF(ISBLANK(J31),"",IF(IFERROR(ABS(J31-'_key'!$A$1370)<=0.005,FALSE),"✓","✗")) -> 0 | T31: =IF(ISBLANK(L31),"",IF(IFERROR(ABS(L31-'_key'!$A$1371)<=0.01,FALSE),"✓","✗")) -> 0 | U31: =IF(ISBLANK(M31),"",IF(IFERROR(EXACT(M31,'_key'!$A$1372),FALSE),"✓","✗")) -> 0 | W31: CS Ops | Z31: =IF(ISBLANK(X31),"",IF(IFERROR(ABS(X31-'_key'!$A$1468)<=0.005,FALSE),"✓","✗")) -> 0
A32: RPT-026 | O32: =IF(ISBLANK(E32),"",IF(IFERROR(ABS(E32-'_key'!$A$1373)<=0.005,FALSE),"✓","✗")) -> 0 | P32: =IF(ISBLANK(F32),"",IF(IFERROR(ABS(F32-'_key'!$A$1374)<=0.005,FALSE),"✓","✗")) -> 0 | Q32: =IF(ISBLANK(G32),"",IF(IFERROR(ABS(G32-'_key'!$A$1375)<=0.005,FALSE),"✓","✗")) -> 0 | R32: =IF(ISBLANK(H32),"",IF(IFERROR(ABS(H32-'_key'!$A$1376)<=0.005,FALSE),"✓","✗")) -> 0 | S32: =IF(ISBLANK(J32),"",IF(IFERROR(ABS(J32-'_key'!$A$1377)<=0.005,FALSE),"✓","✗")) -> 0 | T32: =IF(ISBLANK(L32),"",IF(IFERROR(ABS(L32-'_key'!$A$1378)<=0.01,FALSE),"✓","✗")) -> 0 | U32: =IF(ISBLANK(M32),"",IF(IFERROR(EXACT(M32,'_key'!$A$1379),FALSE),"✓","✗")) -> 0 | W32: Partner Mgmt | Z32: =IF(ISBLANK(X32),"",IF(IFERROR(ABS(X32-'_key'!$A$1469)<=0.005,FALSE),"✓","✗")) -> 0
A33: RPT-027 | O33: =IF(ISBLANK(E33),"",IF(IFERROR(ABS(E33-'_key'!$A$1380)<=0.005,FALSE),"✓","✗")) -> 0 | P33: =IF(ISBLANK(F33),"",IF(IFERROR(ABS(F33-'_key'!$A$1381)<=0.005,FALSE),"✓","✗")) -> 0 | Q33: =IF(ISBLANK(G33),"",IF(IFERROR(ABS(G33-'_key'!$A$1382)<=0.005,FALSE),"✓","✗")) -> 0 | R33: =IF(ISBLANK(H33),"",IF(IFERROR(ABS(H33-'_key'!$A$1383)<=0.005,FALSE),"✓","✗")) -> 0 | S33: =IF(ISBLANK(J33),"",IF(IFERROR(ABS(J33-'_key'!$A$1384)<=0.005,FALSE),"✓","✗")) -> 0 | T33: =IF(ISBLANK(L33),"",IF(IFERROR(ABS(L33-'_key'!$A$1385)<=0.01,FALSE),"✓","✗")) -> 0 | U33: =IF(ISBLANK(M33),"",IF(IFERROR(EXACT(M33,'_key'!$A$1386),FALSE),"✓","✗")) -> 0
A34: RPT-028 | O34: =IF(ISBLANK(E34),"",IF(IFERROR(ABS(E34-'_key'!$A$1387)<=0.005,FALSE),"✓","✗")) -> 0 | P34: =IF(ISBLANK(F34),"",IF(IFERROR(ABS(F34-'_key'!$A$1388)<=0.005,FALSE),"✓","✗")) -> 0 | Q34: =IF(ISBLANK(G34),"",IF(IFERROR(ABS(G34-'_key'!$A$1389)<=0.005,FALSE),"✓","✗")) -> 0 | R34: =IF(ISBLANK(H34),"",IF(IFERROR(ABS(H34-'_key'!$A$1390)<=0.005,FALSE),"✓","✗")) -> 0 | S34: =IF(ISBLANK(J34),"",IF(IFERROR(ABS(J34-'_key'!$A$1391)<=0.005,FALSE),"✓","✗")) -> 0 | T34: =IF(ISBLANK(L34),"",IF(IFERROR(ABS(L34-'_key'!$A$1392)<=0.01,FALSE),"✓","✗")) -> 0 | U34: =IF(ISBLANK(M34),"",IF(IFERROR(EXACT(M34,'_key'!$A$1393),FALSE),"✓","✗")) -> 0 | W34: Para la entrevista: redacta 3-5 bullets para liderazgo con los hallazgos (p. ej. 'X reportes sin uso en 90 días → retirarlos libera N h/mes'; 'Login v1 y v2 duplican información'; 'el reporte ad hoc Y se pide cada semana → automatizar'; 'un reporte contractual sin views: validar con el CSM que se esté entregando al cliente').
A35: RPT-029 | O35: =IF(ISBLANK(E35),"",IF(IFERROR(ABS(E35-'_key'!$A$1394)<=0.005,FALSE),"✓","✗")) -> 0 | P35: =IF(ISBLANK(F35),"",IF(IFERROR(ABS(F35-'_key'!$A$1395)<=0.005,FALSE),"✓","✗")) -> 0 | Q35: =IF(ISBLANK(G35),"",IF(IFERROR(ABS(G35-'_key'!$A$1396)<=0.005,FALSE),"✓","✗")) -> 0 | R35: =IF(ISBLANK(H35),"",IF(IFERROR(EXACT(H35,'_key'!$A$1397),FALSE),"✓","✗")) -> 0 | S35: =IF(ISBLANK(J35),"",IF(IFERROR(ABS(J35-'_key'!$A$1398)<=0.005,FALSE),"✓","✗")) -> 0 | T35: =IF(ISBLANK(L35),"",IF(IFERROR(EXACT(L35,'_key'!$A$1399),FALSE),"✓","✗")) -> 0 | U35: =IF(ISBLANK(M35),"",IF(IFERROR(EXACT(M35,'_key'!$A$1400),FALSE),"✓","✗")) -> 0
A36: RPT-030 | O36: =IF(ISBLANK(E36),"",IF(IFERROR(ABS(E36-'_key'!$A$1401)<=0.005,FALSE),"✓","✗")) -> 0 | P36: =IF(ISBLANK(F36),"",IF(IFERROR(ABS(F36-'_key'!$A$1402)<=0.005,FALSE),"✓","✗")) -> 0 | Q36: =IF(ISBLANK(G36),"",IF(IFERROR(ABS(G36-'_key'!$A$1403)<=0.005,FALSE),"✓","✗")) -> 0 | R36: =IF(ISBLANK(H36),"",IF(IFERROR(ABS(H36-'_key'!$A$1404)<=0.005,FALSE),"✓","✗")) -> 0 | S36: =IF(ISBLANK(J36),"",IF(IFERROR(ABS(J36-'_key'!$A$1405)<=0.005,FALSE),"✓","✗")) -> 0 | T36: =IF(ISBLANK(L36),"",IF(IFERROR(ABS(L36-'_key'!$A$1406)<=0.01,FALSE),"✓","✗")) -> 0 | U36: =IF(ISBLANK(M36),"",IF(IFERROR(EXACT(M36,'_key'!$A$1407),FALSE),"✓","✗")) -> 0
A37: RPT-031 | O37: =IF(ISBLANK(E37),"",IF(IFERROR(ABS(E37-'_key'!$A$1408)<=0.005,FALSE),"✓","✗")) -> 0 | P37: =IF(ISBLANK(F37),"",IF(IFERROR(ABS(F37-'_key'!$A$1409)<=0.005,FALSE),"✓","✗")) -> 0 | Q37: =IF(ISBLANK(G37),"",IF(IFERROR(ABS(G37-'_key'!$A$1410)<=0.005,FALSE),"✓","✗")) -> 0 | R37: =IF(ISBLANK(H37),"",IF(IFERROR(EXACT(H37,'_key'!$A$1411),FALSE),"✓","✗")) -> 0 | S37: =IF(ISBLANK(J37),"",IF(IFERROR(ABS(J37-'_key'!$A$1412)<=0.005,FALSE),"✓","✗")) -> 0 | T37: =IF(ISBLANK(L37),"",IF(IFERROR(EXACT(L37,'_key'!$A$1413),FALSE),"✓","✗")) -> 0 | U37: =IF(ISBLANK(M37),"",IF(IFERROR(EXACT(M37,'_key'!$A$1414),FALSE),"✓","✗")) -> 0
A38: RPT-032 | O38: =IF(ISBLANK(E38),"",IF(IFERROR(ABS(E38-'_key'!$A$1415)<=0.005,FALSE),"✓","✗")) -> 0 | P38: =IF(ISBLANK(F38),"",IF(IFERROR(ABS(F38-'_key'!$A$1416)<=0.005,FALSE),"✓","✗")) -> 0 | Q38: =IF(ISBLANK(G38),"",IF(IFERROR(ABS(G38-'_key'!$A$1417)<=0.005,FALSE),"✓","✗")) -> 0 | R38: =IF(ISBLANK(H38),"",IF(IFERROR(ABS(H38-'_key'!$A$1418)<=0.005,FALSE),"✓","✗")) -> 0 | S38: =IF(ISBLANK(J38),"",IF(IFERROR(ABS(J38-'_key'!$A$1419)<=0.005,FALSE),"✓","✗")) -> 0 | T38: =IF(ISBLANK(L38),"",IF(IFERROR(ABS(L38-'_key'!$A$1420)<=0.01,FALSE),"✓","✗")) -> 0 | U38: =IF(ISBLANK(M38),"",IF(IFERROR(EXACT(M38,'_key'!$A$1421),FALSE),"✓","✗")) -> 0
A39: RPT-033 | O39: =IF(ISBLANK(E39),"",IF(IFERROR(ABS(E39-'_key'!$A$1422)<=0.005,FALSE),"✓","✗")) -> 0 | P39: =IF(ISBLANK(F39),"",IF(IFERROR(ABS(F39-'_key'!$A$1423)<=0.005,FALSE),"✓","✗")) -> 0 | Q39: =IF(ISBLANK(G39),"",IF(IFERROR(ABS(G39-'_key'!$A$1424)<=0.005,FALSE),"✓","✗")) -> 0 | R39: =IF(ISBLANK(H39),"",IF(IFERROR(ABS(H39-'_key'!$A$1425)<=0.005,FALSE),"✓","✗")) -> 0 | S39: =IF(ISBLANK(J39),"",IF(IFERROR(ABS(J39-'_key'!$A$1426)<=0.005,FALSE),"✓","✗")) -> 0 | T39: =IF(ISBLANK(L39),"",IF(IFERROR(ABS(L39-'_key'!$A$1427)<=0.01,FALSE),"✓","✗")) -> 0 | U39: =IF(ISBLANK(M39),"",IF(IFERROR(EXACT(M39,'_key'!$A$1428),FALSE),"✓","✗")) -> 0
A40: RPT-034 | O40: =IF(ISBLANK(E40),"",IF(IFERROR(ABS(E40-'_key'!$A$1429)<=0.005,FALSE),"✓","✗")) -> 0 | P40: =IF(ISBLANK(F40),"",IF(IFERROR(ABS(F40-'_key'!$A$1430)<=0.005,FALSE),"✓","✗")) -> 0 | Q40: =IF(ISBLANK(G40),"",IF(IFERROR(ABS(G40-'_key'!$A$1431)<=0.005,FALSE),"✓","✗")) -> 0 | R40: =IF(ISBLANK(H40),"",IF(IFERROR(ABS(H40-'_key'!$A$1432)<=0.005,FALSE),"✓","✗")) -> 0 | S40: =IF(ISBLANK(J40),"",IF(IFERROR(ABS(J40-'_key'!$A$1433)<=0.005,FALSE),"✓","✗")) -> 0 | T40: =IF(ISBLANK(L40),"",IF(IFERROR(ABS(L40-'_key'!$A$1434)<=0.01,FALSE),"✓","✗")) -> 0 | U40: =IF(ISBLANK(M40),"",IF(IFERROR(EXACT(M40,'_key'!$A$1435),FALSE),"✓","✗")) -> 0
A41: RPT-035 | O41: =IF(ISBLANK(E41),"",IF(IFERROR(ABS(E41-'_key'!$A$1436)<=0.005,FALSE),"✓","✗")) -> 0 | P41: =IF(ISBLANK(F41),"",IF(IFERROR(ABS(F41-'_key'!$A$1437)<=0.005,FALSE),"✓","✗")) -> 0 | Q41: =IF(ISBLANK(G41),"",IF(IFERROR(ABS(G41-'_key'!$A$1438)<=0.005,FALSE),"✓","✗")) -> 0 | R41: =IF(ISBLANK(H41),"",IF(IFERROR(ABS(H41-'_key'!$A$1439)<=0.005,FALSE),"✓","✗")) -> 0 | S41: =IF(ISBLANK(J41),"",IF(IFERROR(ABS(J41-'_key'!$A$1440)<=0.005,FALSE),"✓","✗")) -> 0 | T41: =IF(ISBLANK(L41),"",IF(IFERROR(ABS(L41-'_key'!$A$1441)<=0.01,FALSE),"✓","✗")) -> 0 | U41: =IF(ISBLANK(M41),"",IF(IFERROR(EXACT(M41,'_key'!$A$1442),FALSE),"✓","✗")) -> 0
A42: RPT-036 | O42: =IF(ISBLANK(E42),"",IF(IFERROR(ABS(E42-'_key'!$A$1443)<=0.005,FALSE),"✓","✗")) -> 0 | P42: =IF(ISBLANK(F42),"",IF(IFERROR(ABS(F42-'_key'!$A$1444)<=0.005,FALSE),"✓","✗")) -> 0 | Q42: =IF(ISBLANK(G42),"",IF(IFERROR(ABS(G42-'_key'!$A$1445)<=0.005,FALSE),"✓","✗")) -> 0 | R42: =IF(ISBLANK(H42),"",IF(IFERROR(ABS(H42-'_key'!$A$1446)<=0.005,FALSE),"✓","✗")) -> 0 | S42: =IF(ISBLANK(J42),"",IF(IFERROR(ABS(J42-'_key'!$A$1447)<=0.005,FALSE),"✓","✗")) -> 0 | T42: =IF(ISBLANK(L42),"",IF(IFERROR(ABS(L42-'_key'!$A$1448)<=0.01,FALSE),"✓","✗")) -> 0 | U42: =IF(ISBLANK(M42),"",IF(IFERROR(EXACT(M42,'_key'!$A$1449),FALSE),"✓","✗")) -> 0

Sheet E5_Limpieza_Datos
A1: E5 · Limpieza y auditoría de datos (export del CRM)
A2: Objetivo: un CSM te pasó este export del CRM (columnas A-F, tal cual). Límpialo con fórmulas (columnas H-M), detecta duplicados, cuentas que no existen en el maestro y diferencias de ARR (columnas N-Q). Después resume la calidad de los datos a la derecha.
A3: Contexto: antes de cualquier reporte o health score hay que confiar en los datos. En la entrevista describe tu proceso: estandarizar → deduplicar → conciliar contra la fuente de verdad → documentar y corregir en el origen (no solo en Excel).
AD5: Resumen de calidad de datos
A6: Account ID (raw) | B6: Account Name (raw) | C6: Segment (raw) | D6: ARR (raw) | E6: Renewal (raw) | F6: CSM Email (raw) | H6: ID limpio | I6: Nombre limpio | J6: Segment limpio | K6: ARR (número) | L6: Renewal (fecha) | M6: Email limpio | N6: ¿Duplicado? | O6: ¿Existe en maestro? | P6: Dif. ARR vs maestro | Q6: # Problemas | S6: ✓H | T6: ✓I | U6: ✓J | V6: ✓K | W6: ✓L | X6: ✓M | Y6: ✓N | Z6: ✓O | AA6: ✓P | AB6: ✓Q | AD6: Métrica | AE6: Valor | AF6: Chk
E7: Formatos: AAAA-MM-DD o DD/MM/AAAA | H7: UPPER(TRIM(A8)) | I7: PROPER(TRIM(B8)) | J7: SWITCH(UPPER(TRIM(C8)), "ENTERPRISE","Enterprise", "ENT","Enterprise", "MID-MARKET",..., "MID MARKET",..., "MM",..., "SMB","SMB", "SMALL BUSINESS","SMB", "Revisar") | K7: NUMBERVALUE(SUBSTITUTE(SUBSTITUTE(D8,"$",""),"USD",""), ".", ",") | L7: IF(MID(E8,5,1)="-", DATE(LEFT(E8,4),MID(E8,6,2),RIGHT(E8,2)), DATE(RIGHT(E8,4),MID(E8,4,2),LEFT(E8,2))) | M7: LOWER(TRIM(F8)) | N7: IF(COUNTIF($H$8:H8, H8)>1, "Duplicado", "") ← rango que crece | O7: IF(ISNUMBER(MATCH(H8, tbl_Accounts[AccountID], 0)), "Sí", "No") | P7: IFERROR(K8 − XLOOKUP(H8, ...[AccountID], ...[ARR_USD]), "") | Q7: (N8<>"") + (O8="No") + IF(ISNUMBER(P8), --(P8<>0), 0) + (M8="") | AD7: Filas en el export | AF7: =IF(ISBLANK(AE7),"",IF(IFERROR(ABS(AE7-'_key'!$A$2050)<=0.0005,FALSE),"✓","✗")) -> 0
A8: ACC-0073 | B8: Riverbend Group | C8: Mid Market | D8: $80,100 | E8: 2026-10-16 | F8: sofia.ramirez@empresa-demo.com | S8: =IF(ISBLANK(H8),"",IF(IFERROR(EXACT(H8,'_key'!$A$1470),FALSE),"✓","✗")) -> 0 | T8: =IF(ISBLANK(I8),"",IF(IFERROR(EXACT(I8,'_key'!$A$1471),FALSE),"✓","✗")) -> 0 | U8: =IF(ISBLANK(J8),"",IF(IFERROR(EXACT(J8,'_key'!$A$1472),FALSE),"✓","✗")) -> 0 | V8: =IF(ISBLANK(K8),"",IF(IFERROR(ABS(K8-'_key'!$A$1473)<=0.01,FALSE),"✓","✗")) -> 0 | W8: =IF(ISBLANK(L8),"",IF(IFERROR(ABS(L8-'_key'!$A$1474)<=0.01,FALSE),"✓","✗")) -> 0 | X8: =IF(ISBLANK(M8),"",IF(IFERROR(EXACT(M8,'_key'!$A$1475),FALSE),"✓","✗")) -> 0 | Y8: =IF(ISBLANK(N8),"",IF(IFERROR(EXACT(N8,'_key'!$A$1476),FALSE),"✓","✗")) -> 0 | Z8: =IF(ISBLANK(O8),"",IF(IFERROR(EXACT(O8,'_key'!$A$1477),FALSE),"✓","✗")) -> 0 | AA8: =IF(ISBLANK(P8),"",IF(IFERROR(ABS(P8-'_key'!$A$1478)<=0.01,FALSE),"✓","✗")) -> 0 | AB8: =IF(ISBLANK(Q8),"",IF(IFERROR(ABS(Q8-'_key'!$A$1479)<=0.01,FALSE),"✓","✗")) -> 0 | AD8: IDs únicos | AF8: =IF(ISBLANK(AE8),"",IF(IFERROR(ABS(AE8-'_key'!$A$2051)<=0.0005,FALSE),"✓","✗")) -> 0
A9: ACC-0046 | B9: Atlas Energy | C9: SMB | D9: 38,200 USD | E9: 24/12/2026 | S9: =IF(ISBLANK(H9),"",IF(IFERROR(EXACT(H9,'_key'!$A$1480),FALSE),"✓","✗")) -> 0 | T9: =IF(ISBLANK(I9),"",IF(IFERROR(EXACT(I9,'_key'!$A$1481),FALSE),"✓","✗")) -> 0 | U9: =IF(ISBLANK(J9),"",IF(IFERROR(EXACT(J9,'_key'!$A$1482),FALSE),"✓","✗")) -> 0 | V9: =IF(ISBLANK(K9),"",IF(IFERROR(ABS(K9-'_key'!$A$1483)<=0.01,FALSE),"✓","✗")) -> 0 | W9: =IF(ISBLANK(L9),"",IF(IFERROR(ABS(L9-'_key'!$A$1484)<=0.01,FALSE),"✓","✗")) -> 0 | X9: =IF(ISBLANK(M9),"",IF(IFERROR(EXACT(M9,'_key'!$A$1485),FALSE),"✓","✗")) -> 0 | Y9: =IF(ISBLANK(N9),"",IF(IFERROR(EXACT(N9,'_key'!$A$1486),FALSE),"✓","✗")) -> 0 | Z9: =IF(ISBLANK(O9),"",IF(IFERROR(EXACT(O9,'_key'!$A$1487),FALSE),"✓","✗")) -> 0 | AA9: =IF(ISBLANK(P9),"",IF(IFERROR(ABS(P9-'_key'!$A$1488)<=0.01,FALSE),"✓","✗")) -> 0 | AB9: =IF(ISBLANK(Q9),"",IF(IFERROR(ABS(Q9-'_key'!$A$1489)<=0.01,FALSE),"✓","✗")) -> 0 | AD9: Filas duplicadas | AF9: =IF(ISBLANK(AE9),"",IF(IFERROR(ABS(AE9-'_key'!$A$2052)<=0.0005,FALSE),"✓","✗")) -> 0
A10: ACC-0149 | B10: COBALT MANUFACTURING | C10: SMB | D10: 12500 | E10: 2027-05-12 | F10: michael.brooks@empresa-demo.com | S10: =IF(ISBLANK(H10),"",IF(IFERROR(EXACT(H10,'_key'!$A$1490),FALSE),"✓","✗")) -> 0 | T10: =IF(ISBLANK(I10),"",IF(IFERROR(EXACT(I10,'_key'!$A$1491),FALSE),"✓","✗")) -> 0 | U10: =IF(ISBLANK(J10),"",IF(IFERROR(EXACT(J10,'_key'!$A$1492),FALSE),"✓","✗")) -> 0 | V10: =IF(ISBLANK(K10),"",IF(IFERROR(ABS(K10-'_key'!$A$1493)<=0.01,FALSE),"✓","✗")) -> 0 | W10: =IF(ISBLANK(L10),"",IF(IFERROR(ABS(L10-'_key'!$A$1494)<=0.01,FALSE),"✓","✗")) -> 0 | X10: =IF(ISBLANK(M10),"",IF(IFERROR(EXACT(M10,'_key'!$A$1495),FALSE),"✓","✗")) -> 0 | Y10: =IF(ISBLANK(N10),"",IF(IFERROR(EXACT(N10,'_key'!$A$1496),FALSE),"✓","✗")) -> 0 | Z10: =IF(ISBLANK(O10),"",IF(IFERROR(EXACT(O10,'_key'!$A$1497),FALSE),"✓","✗")) -> 0 | AA10: =IF(ISBLANK(P10),"",IF(IFERROR(ABS(P10-'_key'!$A$1498)<=0.01,FALSE),"✓","✗")) -> 0 | AB10: =IF(ISBLANK(Q10),"",IF(IFERROR(ABS(Q10-'_key'!$A$1499)<=0.01,FALSE),"✓","✗")) -> 0 | AD10: IDs que no existen en el maestro | AF10: =IF(ISBLANK(AE10),"",IF(IFERROR(ABS(AE10-'_key'!$A$2053)<=0.0005,FALSE),"✓","✗")) -> 0
A11: ACC-0129 | B11: Cobalt Legal | C11: Mid-Market | D11: 84000 | E11: 2026-01-02 | F11: Emily.Carter@Empresa-Demo.Com | S11: =IF(ISBLANK(H11),"",IF(IFERROR(EXACT(H11,'_key'!$A$1500),FALSE),"✓","✗")) -> 0 | T11: =IF(ISBLANK(I11),"",IF(IFERROR(EXACT(I11,'_key'!$A$1501),FALSE),"✓","✗")) -> 0 | U11: =IF(ISBLANK(J11),"",IF(IFERROR(EXACT(J11,'_key'!$A$1502),FALSE),"✓","✗")) -> 0 | V11: =IF(ISBLANK(K11),"",IF(IFERROR(ABS(K11-'_key'!$A$1503)<=0.01,FALSE),"✓","✗")) -> 0 | W11: =IF(ISBLANK(L11),"",IF(IFERROR(ABS(L11-'_key'!$A$1504)<=0.01,FALSE),"✓","✗")) -> 0 | X11: =IF(ISBLANK(M11),"",IF(IFERROR(EXACT(M11,'_key'!$A$1505),FALSE),"✓","✗")) -> 0 | Y11: =IF(ISBLANK(N11),"",IF(IFERROR(EXACT(N11,'_key'!$A$1506),FALSE),"✓","✗")) -> 0 | Z11: =IF(ISBLANK(O11),"",IF(IFERROR(EXACT(O11,'_key'!$A$1507),FALSE),"✓","✗")) -> 0 | AA11: =IF(ISBLANK(P11),"",IF(IFERROR(ABS(P11-'_key'!$A$1508)<=0.01,FALSE),"✓","✗")) -> 0 | AB11: =IF(ISBLANK(Q11),"",IF(IFERROR(ABS(Q11-'_key'!$A$1509)<=0.01,FALSE),"✓","✗")) -> 0 | AD11: Filas con ARR distinto al maestro | AF11: =IF(ISBLANK(AE11),"",IF(IFERROR(ABS(AE11-'_key'!$A$2054)<=0.0005,FALSE),"✓","✗")) -> 0
A12: ACC-0071 | B12: SUMMIT MANUFACTURING | C12: Small Business | D12: $36,000.00 | E12: 17/07/2027 | S12: =IF(ISBLANK(H12),"",IF(IFERROR(EXACT(H12,'_key'!$A$1510),FALSE),"✓","✗")) -> 0 | T12: =IF(ISBLANK(I12),"",IF(IFERROR(EXACT(I12,'_key'!$A$1511),FALSE),"✓","✗")) -> 0 | U12: =IF(ISBLANK(J12),"",IF(IFERROR(EXACT(J12,'_key'!$A$1512),FALSE),"✓","✗")) -> 0 | V12: =IF(ISBLANK(K12),"",IF(IFERROR(ABS(K12-'_key'!$A$1513)<=0.01,FALSE),"✓","✗")) -> 0 | W12: =IF(ISBLANK(L12),"",IF(IFERROR(ABS(L12-'_key'!$A$1514)<=0.01,FALSE),"✓","✗")) -> 0 | X12: =IF(ISBLANK(M12),"",IF(IFERROR(EXACT(M12,'_key'!$A$1515),FALSE),"✓","✗")) -> 0 | Y12: =IF(ISBLANK(N12),"",IF(IFERROR(EXACT(N12,'_key'!$A$1516),FALSE),"✓","✗")) -> 0 | Z12: =IF(ISBLANK(O12),"",IF(IFERROR(EXACT(O12,'_key'!$A$1517),FALSE),"✓","✗")) -> 0 | AA12: =IF(ISBLANK(P12),"",IF(IFERROR(ABS(P12-'_key'!$A$1518)<=0.01,FALSE),"✓","✗")) -> 0 | AB12: =IF(ISBLANK(Q12),"",IF(IFERROR(ABS(Q12-'_key'!$A$1519)<=0.01,FALSE),"✓","✗")) -> 0 | AD12: Filas sin email de CSM | AF12: =IF(ISBLANK(AE12),"",IF(IFERROR(ABS(AE12-'_key'!$A$2055)<=0.0005,FALSE),"✓","✗")) -> 0
A13: ACC-0094 | B13: DRIFTWOOD GROUP | C13: smb | D13: $9,400 | E13: 2027-04-05 | F13: lucia.herrera@empresa-demo.com | S13: =IF(ISBLANK(H13),"",IF(IFERROR(EXACT(H13,'_key'!$A$1520),FALSE),"✓","✗")) -> 0 | T13: =IF(ISBLANK(I13),"",IF(IFERROR(EXACT(I13,'_key'!$A$1521),FALSE),"✓","✗")) -> 0 | U13: =IF(ISBLANK(J13),"",IF(IFERROR(EXACT(J13,'_key'!$A$1522),FALSE),"✓","✗")) -> 0 | V13: =IF(ISBLANK(K13),"",IF(IFERROR(ABS(K13-'_key'!$A$1523)<=0.01,FALSE),"✓","✗")) -> 0 | W13: =IF(ISBLANK(L13),"",IF(IFERROR(ABS(L13-'_key'!$A$1524)<=0.01,FALSE),"✓","✗")) -> 0 | X13: =IF(ISBLANK(M13),"",IF(IFERROR(EXACT(M13,'_key'!$A$1525),FALSE),"✓","✗")) -> 0 | Y13: =IF(ISBLANK(N13),"",IF(IFERROR(EXACT(N13,'_key'!$A$1526),FALSE),"✓","✗")) -> 0 | Z13: =IF(ISBLANK(O13),"",IF(IFERROR(EXACT(O13,'_key'!$A$1527),FALSE),"✓","✗")) -> 0 | AA13: =IF(ISBLANK(P13),"",IF(IFERROR(ABS(P13-'_key'!$A$1528)<=0.01,FALSE),"✓","✗")) -> 0 | AB13: =IF(ISBLANK(Q13),"",IF(IFERROR(ABS(Q13-'_key'!$A$1529)<=0.01,FALSE),"✓","✗")) -> 0 | AD13: % filas sin problemas | AF13: =IF(ISBLANK(AE13),"",IF(IFERROR(ABS(AE13-'_key'!$A$2056)<=0.0005,FALSE),"✓","✗")) -> 0
A14: ACC-0022 | B14: westfield systems | C14: Mid Market | D14: 112500.00 | E14: 17/05/2027 | F14: sofia.ramirez@empresa-demo.com | S14: =IF(ISBLANK(H14),"",IF(IFERROR(EXACT(H14,'_key'!$A$1530),FALSE),"✓","✗")) -> 0 | T14: =IF(ISBLANK(I14),"",IF(IFERROR(EXACT(I14,'_key'!$A$1531),FALSE),"✓","✗")) -> 0 | U14: =IF(ISBLANK(J14),"",IF(IFERROR(EXACT(J14,'_key'!$A$1532),FALSE),"✓","✗")) -> 0 | V14: =IF(ISBLANK(K14),"",IF(IFERROR(ABS(K14-'_key'!$A$1533)<=0.01,FALSE),"✓","✗")) -> 0 | W14: =IF(ISBLANK(L14),"",IF(IFERROR(ABS(L14-'_key'!$A$1534)<=0.01,FALSE),"✓","✗")) -> 0 | X14: =IF(ISBLANK(M14),"",IF(IFERROR(EXACT(M14,'_key'!$A$1535),FALSE),"✓","✗")) -> 0 | Y14: =IF(ISBLANK(N14),"",IF(IFERROR(EXACT(N14,'_key'!$A$1536),FALSE),"✓","✗")) -> 0 | Z14: =IF(ISBLANK(O14),"",IF(IFERROR(EXACT(O14,'_key'!$A$1537),FALSE),"✓","✗")) -> 0 | AA14: =IF(ISBLANK(P14),"",IF(IFERROR(ABS(P14-'_key'!$A$1538)<=0.01,FALSE),"✓","✗")) -> 0 | AB14: =IF(ISBLANK(Q14),"",IF(IFERROR(ABS(Q14-'_key'!$A$1539)<=0.01,FALSE),"✓","✗")) -> 0
A15: ACC-0069 | B15: CRESCENT GROUP | C15: mid-market | D15: $136,500.00 | E15: 2027-08-08 | F15: Emily.Carter@Empresa-Demo.Com | S15: =IF(ISBLANK(H15),"",IF(IFERROR(EXACT(H15,'_key'!$A$1540),FALSE),"✓","✗")) -> 0 | T15: =IF(ISBLANK(I15),"",IF(IFERROR(EXACT(I15,'_key'!$A$1541),FALSE),"✓","✗")) -> 0 | U15: =IF(ISBLANK(J15),"",IF(IFERROR(EXACT(J15,'_key'!$A$1542),FALSE),"✓","✗")) -> 0 | V15: =IF(ISBLANK(K15),"",IF(IFERROR(ABS(K15-'_key'!$A$1543)<=0.01,FALSE),"✓","✗")) -> 0 | W15: =IF(ISBLANK(L15),"",IF(IFERROR(ABS(L15-'_key'!$A$1544)<=0.01,FALSE),"✓","✗")) -> 0 | X15: =IF(ISBLANK(M15),"",IF(IFERROR(EXACT(M15,'_key'!$A$1545),FALSE),"✓","✗")) -> 0 | Y15: =IF(ISBLANK(N15),"",IF(IFERROR(EXACT(N15,'_key'!$A$1546),FALSE),"✓","✗")) -> 0 | Z15: =IF(ISBLANK(O15),"",IF(IFERROR(EXACT(O15,'_key'!$A$1547),FALSE),"✓","✗")) -> 0 | AA15: =IF(ISBLANK(P15),"",IF(IFERROR(ABS(P15-'_key'!$A$1548)<=0.01,FALSE),"✓","✗")) -> 0 | AB15: =IF(ISBLANK(Q15),"",IF(IFERROR(ABS(Q15-'_key'!$A$1549)<=0.01,FALSE),"✓","✗")) -> 0 | AD15: Siguiente paso real: documenta las reglas de limpieza, avisa al dueño del dato (Sales Ops / CSM) y corrige en Salesforce. Opcional: repite esta limpieza con Power Query (E10) y compara.
A16: ACC-0252 | B16: Elmstone Ventures | C16: mid-market | D16: USD 68000 | E16: 24/03/2027 | S16: =IF(ISBLANK(H16),"",IF(IFERROR(EXACT(H16,'_key'!$A$1550),FALSE),"✓","✗")) -> 0 | T16: =IF(ISBLANK(I16),"",IF(IFERROR(EXACT(I16,'_key'!$A$1551),FALSE),"✓","✗")) -> 0 | U16: =IF(ISBLANK(J16),"",IF(IFERROR(EXACT(J16,'_key'!$A$1552),FALSE),"✓","✗")) -> 0 | V16: =IF(ISBLANK(K16),"",IF(IFERROR(ABS(K16-'_key'!$A$1553)<=0.01,FALSE),"✓","✗")) -> 0 | W16: =IF(ISBLANK(L16),"",IF(IFERROR(ABS(L16-'_key'!$A$1554)<=0.01,FALSE),"✓","✗")) -> 0 | X16: =IF(ISBLANK(M16),"",IF(IFERROR(EXACT(M16,'_key'!$A$1555),FALSE),"✓","✗")) -> 0 | Y16: =IF(ISBLANK(N16),"",IF(IFERROR(EXACT(N16,'_key'!$A$1556),FALSE),"✓","✗")) -> 0 | Z16: =IF(ISBLANK(O16),"",IF(IFERROR(EXACT(O16,'_key'!$A$1557),FALSE),"✓","✗")) -> 0 | AA16: =IF(ISBLANK(P16),"",IF(IFERROR(EXACT(P16,'_key'!$A$1558),FALSE),"✓","✗")) -> 0 | AB16: =IF(ISBLANK(Q16),"",IF(IFERROR(ABS(Q16-'_key'!$A$1559)<=0.01,FALSE),"✓","✗")) -> 0
A17: ACC-0034 | B17: Evergreen Logistics | C17: Mid-Market | D17: $125,200.00 | E17: 26/05/2027 | F17: EMILY.CARTER@EMPRESA-DEMO.COM | S17: =IF(ISBLANK(H17),"",IF(IFERROR(EXACT(H17,'_key'!$A$1560),FALSE),"✓","✗")) -> 0 | T17: =IF(ISBLANK(I17),"",IF(IFERROR(EXACT(I17,'_key'!$A$1561),FALSE),"✓","✗")) -> 0 | U17: =IF(ISBLANK(J17),"",IF(IFERROR(EXACT(J17,'_key'!$A$1562),FALSE),"✓","✗")) -> 0 | V17: =IF(ISBLANK(K17),"",IF(IFERROR(ABS(K17-'_key'!$A$1563)<=0.01,FALSE),"✓","✗")) -> 0 | W17: =IF(ISBLANK(L17),"",IF(IFERROR(ABS(L17-'_key'!$A$1564)<=0.01,FALSE),"✓","✗")) -> 0 | X17: =IF(ISBLANK(M17),"",IF(IFERROR(EXACT(M17,'_key'!$A$1565),FALSE),"✓","✗")) -> 0 | Y17: =IF(ISBLANK(N17),"",IF(IFERROR(EXACT(N17,'_key'!$A$1566),FALSE),"✓","✗")) -> 0 | Z17: =IF(ISBLANK(O17),"",IF(IFERROR(EXACT(O17,'_key'!$A$1567),FALSE),"✓","✗")) -> 0 | AA17: =IF(ISBLANK(P17),"",IF(IFERROR(ABS(P17-'_key'!$A$1568)<=0.01,FALSE),"✓","✗")) -> 0 | AB17: =IF(ISBLANK(Q17),"",IF(IFERROR(ABS(Q17-'_key'!$A$1569)<=0.01,FALSE),"✓","✗")) -> 0
A18: ACC-0125 | B18: PINNACLE PARTNERS | C18: Enterprise | D18: $189,000 | E18: 11/08/2027 | S18: =IF(ISBLANK(H18),"",IF(IFERROR(EXACT(H18,'_key'!$A$1570),FALSE),"✓","✗")) -> 0 | T18: =IF(ISBLANK(I18),"",IF(IFERROR(EXACT(I18,'_key'!$A$1571),FALSE),"✓","✗")) -> 0 | U18: =IF(ISBLANK(J18),"",IF(IFERROR(EXACT(J18,'_key'!$A$1572),FALSE),"✓","✗")) -> 0 | V18: =IF(ISBLANK(K18),"",IF(IFERROR(ABS(K18-'_key'!$A$1573)<=0.01,FALSE),"✓","✗")) -> 0 | W18: =IF(ISBLANK(L18),"",IF(IFERROR(ABS(L18-'_key'!$A$1574)<=0.01,FALSE),"✓","✗")) -> 0 | X18: =IF(ISBLANK(M18),"",IF(IFERROR(EXACT(M18,'_key'!$A$1575),FALSE),"✓","✗")) -> 0 | Y18: =IF(ISBLANK(N18),"",IF(IFERROR(EXACT(N18,'_key'!$A$1576),FALSE),"✓","✗")) -> 0 | Z18: =IF(ISBLANK(O18),"",IF(IFERROR(EXACT(O18,'_key'!$A$1577),FALSE),"✓","✗")) -> 0 | AA18: =IF(ISBLANK(P18),"",IF(IFERROR(ABS(P18-'_key'!$A$1578)<=0.01,FALSE),"✓","✗")) -> 0 | AB18: =IF(ISBLANK(Q18),"",IF(IFERROR(ABS(Q18-'_key'!$A$1579)<=0.01,FALSE),"✓","✗")) -> 0
A19: ACC-0092 | B19: Riverbend Capital | C19: Mid-Market | D19: 100400 | E19: 2027-08-14 | F19: SOFIA.RAMIREZ@EMPRESA-DEMO.COM | S19: =IF(ISBLANK(H19),"",IF(IFERROR(EXACT(H19,'_key'!$A$1580),FALSE),"✓","✗")) -> 0 | T19: =IF(ISBLANK(I19),"",IF(IFERROR(EXACT(I19,'_key'!$A$1581),FALSE),"✓","✗")) -> 0 | U19: =IF(ISBLANK(J19),"",IF(IFERROR(EXACT(J19,'_key'!$A$1582),FALSE),"✓","✗")) -> 0 | V19: =IF(ISBLANK(K19),"",IF(IFERROR(ABS(K19-'_key'!$A$1583)<=0.01,FALSE),"✓","✗")) -> 0 | W19: =IF(ISBLANK(L19),"",IF(IFERROR(ABS(L19-'_key'!$A$1584)<=0.01,FALSE),"✓","✗")) -> 0 | X19: =IF(ISBLANK(M19),"",IF(IFERROR(EXACT(M19,'_key'!$A$1585),FALSE),"✓","✗")) -> 0 | Y19: =IF(ISBLANK(N19),"",IF(IFERROR(EXACT(N19,'_key'!$A$1586),FALSE),"✓","✗")) -> 0 | Z19: =IF(ISBLANK(O19),"",IF(IFERROR(EXACT(O19,'_key'!$A$1587),FALSE),"✓","✗")) -> 0 | AA19: =IF(ISBLANK(P19),"",IF(IFERROR(ABS(P19-'_key'!$A$1588)<=0.01,FALSE),"✓","✗")) -> 0 | AB19: =IF(ISBLANK(Q19),"",IF(IFERROR(ABS(Q19-'_key'!$A$1589)<=0.01,FALSE),"✓","✗")) -> 0
A20: ACC-0150 | B20: sterling retail | C20: Ent | D20: 209,600 USD | E20: 10/08/2026 | F20: ANA.LOPEZ@EMPRESA-DEMO.COM | S20: =IF(ISBLANK(H20),"",IF(IFERROR(EXACT(H20,'_key'!$A$1590),FALSE),"✓","✗")) -> 0 | T20: =IF(ISBLANK(I20),"",IF(IFERROR(EXACT(I20,'_key'!$A$1591),FALSE),"✓","✗")) -> 0 | U20: =IF(ISBLANK(J20),"",IF(IFERROR(EXACT(J20,'_key'!$A$1592),FALSE),"✓","✗")) -> 0 | V20: =IF(ISBLANK(K20),"",IF(IFERROR(ABS(K20-'_key'!$A$1593)<=0.01,FALSE),"✓","✗")) -> 0 | W20: =IF(ISBLANK(L20),"",IF(IFERROR(ABS(L20-'_key'!$A$1594)<=0.01,FALSE),"✓","✗")) -> 0 | X20: =IF(ISBLANK(M20),"",IF(IFERROR(EXACT(M20,'_key'!$A$1595),FALSE),"✓","✗")) -> 0 | Y20: =IF(ISBLANK(N20),"",IF(IFERROR(EXACT(N20,'_key'!$A$1596),FALSE),"✓","✗")) -> 0 | Z20: =IF(ISBLANK(O20),"",IF(IFERROR(EXACT(O20,'_key'!$A$1597),FALSE),"✓","✗")) -> 0 | AA20: =IF(ISBLANK(P20),"",IF(IFERROR(ABS(P20-'_key'!$A$1598)<=0.01,FALSE),"✓","✗")) -> 0 | AB20: =IF(ISBLANK(Q20),"",IF(IFERROR(ABS(Q20-'_key'!$A$1599)<=0.01,FALSE),"✓","✗")) -> 0
A21: ACC-0068 | B21: Horizon Financial | C21: SMB | D21: 20,100 USD | E21: 2026-11-09 | F21: JAMES.WALKER@EMPRESA-DEMO.COM | S21: =IF(ISBLANK(H21),"",IF(IFERROR(EXACT(H21,'_key'!$A$1600),FALSE),"✓","✗")) -> 0 | T21: =IF(ISBLANK(I21),"",IF(IFERROR(EXACT(I21,'_key'!$A$1601),FALSE),"✓","✗")) -> 0 | U21: =IF(ISBLANK(J21),"",IF(IFERROR(EXACT(J21,'_key'!$A$1602),FALSE),"✓","✗")) -> 0 | V21: =IF(ISBLANK(K21),"",IF(IFERROR(ABS(K21-'_key'!$A$1603)<=0.01,FALSE),"✓","✗")) -> 0 | W21: =IF(ISBLANK(L21),"",IF(IFERROR(ABS(L21-'_key'!$A$1604)<=0.01,FALSE),"✓","✗")) -> 0 | X21: =IF(ISBLANK(M21),"",IF(IFERROR(EXACT(M21,'_key'!$A$1605),FALSE),"✓","✗")) -> 0 | Y21: =IF(ISBLANK(N21),"",IF(IFERROR(EXACT(N21,'_key'!$A$1606),FALSE),"✓","✗")) -> 0 | Z21: =IF(ISBLANK(O21),"",IF(IFERROR(EXACT(O21,'_key'!$A$1607),FALSE),"✓","✗")) -> 0 | AA21: =IF(ISBLANK(P21),"",IF(IFERROR(ABS(P21-'_key'!$A$1608)<=0.01,FALSE),"✓","✗")) -> 0 | AB21: =IF(ISBLANK(Q21),"",IF(IFERROR(ABS(Q21-'_key'!$A$1609)<=0.01,FALSE),"✓","✗")) -> 0
A22: ACC-0060 | B22: Vantage Retail | C22: Mid Market | D22: 41500 | E22: 2027-09-13 | F22: DANIEL.ORTIZ@EMPRESA-DEMO.COM | S22: =IF(ISBLANK(H22),"",IF(IFERROR(EXACT(H22,'_key'!$A$1610),FALSE),"✓","✗")) -> 0 | T22: =IF(ISBLANK(I22),"",IF(IFERROR(EXACT(I22,'_key'!$A$1611),FALSE),"✓","✗")) -> 0 | U22: =IF(ISBLANK(J22),"",IF(IFERROR(EXACT(J22,'_key'!$A$1612),FALSE),"✓","✗")) -> 0 | V22: =IF(ISBLANK(K22),"",IF(IFERROR(ABS(K22-'_key'!$A$1613)<=0.01,FALSE),"✓","✗")) -> 0 | W22: =IF(ISBLANK(L22),"",IF(IFERROR(ABS(L22-'_key'!$A$1614)<=0.01,FALSE),"✓","✗")) -> 0 | X22: =IF(ISBLANK(M22),"",IF(IFERROR(EXACT(M22,'_key'!$A$1615),FALSE),"✓","✗")) -> 0 | Y22: =IF(ISBLANK(N22),"",IF(IFERROR(EXACT(N22,'_key'!$A$1616),FALSE),"✓","✗")) -> 0 | Z22: =IF(ISBLANK(O22),"",IF(IFERROR(EXACT(O22,'_key'!$A$1617),FALSE),"✓","✗")) -> 0 | AA22: =IF(ISBLANK(P22),"",IF(IFERROR(ABS(P22-'_key'!$A$1618)<=0.01,FALSE),"✓","✗")) -> 0 | AB22: =IF(ISBLANK(Q22),"",IF(IFERROR(ABS(Q22-'_key'!$A$1619)<=0.01,FALSE),"✓","✗")) -> 0
A23: acc-0113 | B23: Keystone Insurance | C23: smb | D23: $22,300 | E23: 25/03/2027 | F23: james.walker@empresa-demo.com | S23: =IF(ISBLANK(H23),"",IF(IFERROR(EXACT(H23,'_key'!$A$1620),FALSE),"✓","✗")) -> 0 | T23: =IF(ISBLANK(I23),"",IF(IFERROR(EXACT(I23,'_key'!$A$1621),FALSE),"✓","✗")) -> 0 | U23: =IF(ISBLANK(J23),"",IF(IFERROR(EXACT(J23,'_key'!$A$1622),FALSE),"✓","✗")) -> 0 | V23: =IF(ISBLANK(K23),"",IF(IFERROR(ABS(K23-'_key'!$A$1623)<=0.01,FALSE),"✓","✗")) -> 0 | W23: =IF(ISBLANK(L23),"",IF(IFERROR(ABS(L23-'_key'!$A$1624)<=0.01,FALSE),"✓","✗")) -> 0 | X23: =IF(ISBLANK(M23),"",IF(IFERROR(EXACT(M23,'_key'!$A$1625),FALSE),"✓","✗")) -> 0 | Y23: =IF(ISBLANK(N23),"",IF(IFERROR(EXACT(N23,'_key'!$A$1626),FALSE),"✓","✗")) -> 0 | Z23: =IF(ISBLANK(O23),"",IF(IFERROR(EXACT(O23,'_key'!$A$1627),FALSE),"✓","✗")) -> 0 | AA23: =IF(ISBLANK(P23),"",IF(IFERROR(ABS(P23-'_key'!$A$1628)<=0.01,FALSE),"✓","✗")) -> 0 | AB23: =IF(ISBLANK(Q23),"",IF(IFERROR(ABS(Q23-'_key'!$A$1629)<=0.01,FALSE),"✓","✗")) -> 0
A24: acc-0096 | B24: Riverbend Insurance | C24: SMB | D24: USD 18100 | E24: 2026-10-21 | F24: james.walker@empresa-demo.com | S24: =IF(ISBLANK(H24),"",IF(IFERROR(EXACT(H24,'_key'!$A$1630),FALSE),"✓","✗")) -> 0 | T24: =IF(ISBLANK(I24),"",IF(IFERROR(EXACT(I24,'_key'!$A$1631),FALSE),"✓","✗")) -> 0 | U24: =IF(ISBLANK(J24),"",IF(IFERROR(EXACT(J24,'_key'!$A$1632),FALSE),"✓","✗")) -> 0 | V24: =IF(ISBLANK(K24),"",IF(IFERROR(ABS(K24-'_key'!$A$1633)<=0.01,FALSE),"✓","✗")) -> 0 | W24: =IF(ISBLANK(L24),"",IF(IFERROR(ABS(L24-'_key'!$A$1634)<=0.01,FALSE),"✓","✗")) -> 0 | X24: =IF(ISBLANK(M24),"",IF(IFERROR(EXACT(M24,'_key'!$A$1635),FALSE),"✓","✗")) -> 0 | Y24: =IF(ISBLANK(N24),"",IF(IFERROR(EXACT(N24,'_key'!$A$1636),FALSE),"✓","✗")) -> 0 | Z24: =IF(ISBLANK(O24),"",IF(IFERROR(EXACT(O24,'_key'!$A$1637),FALSE),"✓","✗")) -> 0 | AA24: =IF(ISBLANK(P24),"",IF(IFERROR(ABS(P24-'_key'!$A$1638)<=0.01,FALSE),"✓","✗")) -> 0 | AB24: =IF(ISBLANK(Q24),"",IF(IFERROR(ABS(Q24-'_key'!$A$1639)<=0.01,FALSE),"✓","✗")) -> 0
A25: ACC-0129 | B25: Cobalt Legal | C25: Mid-Market | D25: 89000.00 | E25: 2026-01-02 | F25: EMILY.CARTER@EMPRESA-DEMO.COM | S25: =IF(ISBLANK(H25),"",IF(IFERROR(EXACT(H25,'_key'!$A$1640),FALSE),"✓","✗")) -> 0 | T25: =IF(ISBLANK(I25),"",IF(IFERROR(EXACT(I25,'_key'!$A$1641),FALSE),"✓","✗")) -> 0 | U25: =IF(ISBLANK(J25),"",IF(IFERROR(EXACT(J25,'_key'!$A$1642),FALSE),"✓","✗")) -> 0 | V25: =IF(ISBLANK(K25),"",IF(IFERROR(ABS(K25-'_key'!$A$1643)<=0.01,FALSE),"✓","✗")) -> 0 | W25: =IF(ISBLANK(L25),"",IF(IFERROR(ABS(L25-'_key'!$A$1644)<=0.01,FALSE),"✓","✗")) -> 0 | X25: =IF(ISBLANK(M25),"",IF(IFERROR(EXACT(M25,'_key'!$A$1645),FALSE),"✓","✗")) -> 0 | Y25: =IF(ISBLANK(N25),"",IF(IFERROR(EXACT(N25,'_key'!$A$1646),FALSE),"✓","✗")) -> 0 | Z25: =IF(ISBLANK(O25),"",IF(IFERROR(EXACT(O25,'_key'!$A$1647),FALSE),"✓","✗")) -> 0 | AA25: =IF(ISBLANK(P25),"",IF(IFERROR(ABS(P25-'_key'!$A$1648)<=0.01,FALSE),"✓","✗")) -> 0 | AB25: =IF(ISBLANK(Q25),"",IF(IFERROR(ABS(Q25-'_key'!$A$1649)<=0.01,FALSE),"✓","✗")) -> 0
A26: ACC-0042 | B26: KEYSTONE PARTNERS | C26: Mid-Market | D26: $71,700.00 | E26: 30/04/2027 | S26: =IF(ISBLANK(H26),"",IF(IFERROR(EXACT(H26,'_key'!$A$1650),FALSE),"✓","✗")) -> 0 | T26: =IF(ISBLANK(I26),"",IF(IFERROR(EXACT(I26,'_key'!$A$1651),FALSE),"✓","✗")) -> 0 | U26: =IF(ISBLANK(J26),"",IF(IFERROR(EXACT(J26,'_key'!$A$1652),FALSE),"✓","✗")) -> 0 | V26: =IF(ISBLANK(K26),"",IF(IFERROR(ABS(K26-'_key'!$A$1653)<=0.01,FALSE),"✓","✗")) -> 0 | W26: =IF(ISBLANK(L26),"",IF(IFERROR(ABS(L26-'_key'!$A$1654)<=0.01,FALSE),"✓","✗")) -> 0 | X26: =IF(ISBLANK(M26),"",IF(IFERROR(EXACT(M26,'_key'!$A$1655),FALSE),"✓","✗")) -> 0 | Y26: =IF(ISBLANK(N26),"",IF(IFERROR(EXACT(N26,'_key'!$A$1656),FALSE),"✓","✗")) -> 0 | Z26: =IF(ISBLANK(O26),"",IF(IFERROR(EXACT(O26,'_key'!$A$1657),FALSE),"✓","✗")) -> 0 | AA26: =IF(ISBLANK(P26),"",IF(IFERROR(ABS(P26-'_key'!$A$1658)<=0.01,FALSE),"✓","✗")) -> 0 | AB26: =IF(ISBLANK(Q26),"",IF(IFERROR(ABS(Q26-'_key'!$A$1659)<=0.01,FALSE),"✓","✗")) -> 0
A27: ACC-0253 | B27: cobalt ventures | C27: SMB | D27: USD 80000 | E27: 24/02/2027 | F27: james.walker@empresa-demo.com | S27: =IF(ISBLANK(H27),"",IF(IFERROR(EXACT(H27,'_key'!$A$1660),FALSE),"✓","✗")) -> 0 | T27: =IF(ISBLANK(I27),"",IF(IFERROR(EXACT(I27,'_key'!$A$1661),FALSE),"✓","✗")) -> 0 | U27: =IF(ISBLANK(J27),"",IF(IFERROR(EXACT(J27,'_key'!$A$1662),FALSE),"✓","✗")) -> 0 | V27: =IF(ISBLANK(K27),"",IF(IFERROR(ABS(K27-'_key'!$A$1663)<=0.01,FALSE),"✓","✗")) -> 0 | W27: =IF(ISBLANK(L27),"",IF(IFERROR(ABS(L27-'_key'!$A$1664)<=0.01,FALSE),"✓","✗")) -> 0 | X27: =IF(ISBLANK(M27),"",IF(IFERROR(EXACT(M27,'_key'!$A$1665),FALSE),"✓","✗")) -> 0 | Y27: =IF(ISBLANK(N27),"",IF(IFERROR(EXACT(N27,'_key'!$A$1666),FALSE),"✓","✗")) -> 0 | Z27: =IF(ISBLANK(O27),"",IF(IFERROR(EXACT(O27,'_key'!$A$1667),FALSE),"✓","✗")) -> 0 | AA27: =IF(ISBLANK(P27),"",IF(IFERROR(EXACT(P27,'_key'!$A$1668),FALSE),"✓","✗")) -> 0 | AB27: =IF(ISBLANK(Q27),"",IF(IFERROR(ABS(Q27-'_key'!$A$1669)<=0.01,FALSE),"✓","✗")) -> 0
A28: ACC-0128 | B28: Riverbend Manufacturing | C28: SMB | D28: 24900.00 | E28: 16/09/2027 | F28: Lucia.Herrera@Empresa-Demo.Com | S28: =IF(ISBLANK(H28),"",IF(IFERROR(EXACT(H28,'_key'!$A$1670),FALSE),"✓","✗")) -> 0 | T28: =IF(ISBLANK(I28),"",IF(IFERROR(EXACT(I28,'_key'!$A$1671),FALSE),"✓","✗")) -> 0 | U28: =IF(ISBLANK(J28),"",IF(IFERROR(EXACT(J28,'_key'!$A$1672),FALSE),"✓","✗")) -> 0 | V28: =IF(ISBLANK(K28),"",IF(IFERROR(ABS(K28-'_key'!$A$1673)<=0.01,FALSE),"✓","✗")) -> 0 | W28: =IF(ISBLANK(L28),"",IF(IFERROR(ABS(L28-'_key'!$A$1674)<=0.01,FALSE),"✓","✗")) -> 0 | X28: =IF(ISBLANK(M28),"",IF(IFERROR(EXACT(M28,'_key'!$A$1675),FALSE),"✓","✗")) -> 0 | Y28: =IF(ISBLANK(N28),"",IF(IFERROR(EXACT(N28,'_key'!$A$1676),FALSE),"✓","✗")) -> 0 | Z28: =IF(ISBLANK(O28),"",IF(IFERROR(EXACT(O28,'_key'!$A$1677),FALSE),"✓","✗")) -> 0 | AA28: =IF(ISBLANK(P28),"",IF(IFERROR(ABS(P28-'_key'!$A$1678)<=0.01,FALSE),"✓","✗")) -> 0 | AB28: =IF(ISBLANK(Q28),"",IF(IFERROR(ABS(Q28-'_key'!$A$1679)<=0.01,FALSE),"✓","✗")) -> 0
A29: ACC-0145 | B29: lakeshore holdings | C29: Enterprise | D29: 320,700 USD | E29: 2027-09-02 | F29: Carlos.Mendez@Empresa-Demo.Com | S29: =IF(ISBLANK(H29),"",IF(IFERROR(EXACT(H29,'_key'!$A$1680),FALSE),"✓","✗")) -> 0 | T29: =IF(ISBLANK(I29),"",IF(IFERROR(EXACT(I29,'_key'!$A$1681),FALSE),"✓","✗")) -> 0 | U29: =IF(ISBLANK(J29),"",IF(IFERROR(EXACT(J29,'_key'!$A$1682),FALSE),"✓","✗")) -> 0 | V29: =IF(ISBLANK(K29),"",IF(IFERROR(ABS(K29-'_key'!$A$1683)<=0.01,FALSE),"✓","✗")) -> 0 | W29: =IF(ISBLANK(L29),"",IF(IFERROR(ABS(L29-'_key'!$A$1684)<=0.01,FALSE),"✓","✗")) -> 0 | X29: =IF(ISBLANK(M29),"",IF(IFERROR(EXACT(M29,'_key'!$A$1685),FALSE),"✓","✗")) -> 0 | Y29: =IF(ISBLANK(N29),"",IF(IFERROR(EXACT(N29,'_key'!$A$1686),FALSE),"✓","✗")) -> 0 | Z29: =IF(ISBLANK(O29),"",IF(IFERROR(EXACT(O29,'_key'!$A$1687),FALSE),"✓","✗")) -> 0 | AA29: =IF(ISBLANK(P29),"",IF(IFERROR(ABS(P29-'_key'!$A$1688)<=0.01,FALSE),"✓","✗")) -> 0 | AB29: =IF(ISBLANK(Q29),"",IF(IFERROR(ABS(Q29-'_key'!$A$1689)<=0.01,FALSE),"✓","✗")) -> 0
A30: ACC-0140 | B30: Silverline Systems | C30: Small Business | D30: USD 8500 | E30: 2027-05-02 | F30: james.walker@empresa-demo.com | S30: =IF(ISBLANK(H30),"",IF(IFERROR(EXACT(H30,'_key'!$A$1690),FALSE),"✓","✗")) -> 0 | T30: =IF(ISBLANK(I30),"",IF(IFERROR(EXACT(I30,'_key'!$A$1691),FALSE),"✓","✗")) -> 0 | U30: =IF(ISBLANK(J30),"",IF(IFERROR(EXACT(J30,'_key'!$A$1692),FALSE),"✓","✗")) -> 0 | V30: =IF(ISBLANK(K30),"",IF(IFERROR(ABS(K30-'_key'!$A$1693)<=0.01,FALSE),"✓","✗")) -> 0 | W30: =IF(ISBLANK(L30),"",IF(IFERROR(ABS(L30-'_key'!$A$1694)<=0.01,FALSE),"✓","✗")) -> 0 | X30: =IF(ISBLANK(M30),"",IF(IFERROR(EXACT(M30,'_key'!$A$1695),FALSE),"✓","✗")) -> 0 | Y30: =IF(ISBLANK(N30),"",IF(IFERROR(EXACT(N30,'_key'!$A$1696),FALSE),"✓","✗")) -> 0 | Z30: =IF(ISBLANK(O30),"",IF(IFERROR(EXACT(O30,'_key'!$A$1697),FALSE),"✓","✗")) -> 0 | AA30: =IF(ISBLANK(P30),"",IF(IFERROR(ABS(P30-'_key'!$A$1698)<=0.01,FALSE),"✓","✗")) -> 0 | AB30: =IF(ISBLANK(Q30),"",IF(IFERROR(ABS(Q30-'_key'!$A$1699)<=0.01,FALSE),"✓","✗")) -> 0
A31: ACC-0130 | B31: Lakeshore Partners | C31: Mid-Market | D31: 45000.00 | E31: 23/04/2027 | S31: =IF(ISBLANK(H31),"",IF(IFERROR(EXACT(H31,'_key'!$A$1700),FALSE),"✓","✗")) -> 0 | T31: =IF(ISBLANK(I31),"",IF(IFERROR(EXACT(I31,'_key'!$A$1701),FALSE),"✓","✗")) -> 0 | U31: =IF(ISBLANK(J31),"",IF(IFERROR(EXACT(J31,'_key'!$A$1702),FALSE),"✓","✗")) -> 0 | V31: =IF(ISBLANK(K31),"",IF(IFERROR(ABS(K31-'_key'!$A$1703)<=0.01,FALSE),"✓","✗")) -> 0 | W31: =IF(ISBLANK(L31),"",IF(IFERROR(ABS(L31-'_key'!$A$1704)<=0.01,FALSE),"✓","✗")) -> 0 | X31: =IF(ISBLANK(M31),"",IF(IFERROR(EXACT(M31,'_key'!$A$1705),FALSE),"✓","✗")) -> 0 | Y31: =IF(ISBLANK(N31),"",IF(IFERROR(EXACT(N31,'_key'!$A$1706),FALSE),"✓","✗")) -> 0 | Z31: =IF(ISBLANK(O31),"",IF(IFERROR(EXACT(O31,'_key'!$A$1707),FALSE),"✓","✗")) -> 0 | AA31: =IF(ISBLANK(P31),"",IF(IFERROR(ABS(P31-'_key'!$A$1708)<=0.01,FALSE),"✓","✗")) -> 0 | AB31: =IF(ISBLANK(Q31),"",IF(IFERROR(ABS(Q31-'_key'!$A$1709)<=0.01,FALSE),"✓","✗")) -> 0
A32: ACC-0008 | B32: EVERGREEN SYSTEMS | C32: Ent | D32: USD 224800 | E32: 2026-11-22 | S32: =IF(ISBLANK(H32),"",IF(IFERROR(EXACT(H32,'_key'!$A$1710),FALSE),"✓","✗")) -> 0 | T32: =IF(ISBLANK(I32),"",IF(IFERROR(EXACT(I32,'_key'!$A$1711),FALSE),"✓","✗")) -> 0 | U32: =IF(ISBLANK(J32),"",IF(IFERROR(EXACT(J32,'_key'!$A$1712),FALSE),"✓","✗")) -> 0 | V32: =IF(ISBLANK(K32),"",IF(IFERROR(ABS(K32-'_key'!$A$1713)<=0.01,FALSE),"✓","✗")) -> 0 | W32: =IF(ISBLANK(L32),"",IF(IFERROR(ABS(L32-'_key'!$A$1714)<=0.01,FALSE),"✓","✗")) -> 0 | X32: =IF(ISBLANK(M32),"",IF(IFERROR(EXACT(M32,'_key'!$A$1715),FALSE),"✓","✗")) -> 0 | Y32: =IF(ISBLANK(N32),"",IF(IFERROR(EXACT(N32,'_key'!$A$1716),FALSE),"✓","✗")) -> 0 | Z32: =IF(ISBLANK(O32),"",IF(IFERROR(EXACT(O32,'_key'!$A$1717),FALSE),"✓","✗")) -> 0 | AA32: =IF(ISBLANK(P32),"",IF(IFERROR(ABS(P32-'_key'!$A$1718)<=0.01,FALSE),"✓","✗")) -> 0 | AB32: =IF(ISBLANK(Q32),"",IF(IFERROR(ABS(Q32-'_key'!$A$1719)<=0.01,FALSE),"✓","✗")) -> 0
A33: acc-0128 | B33: riverbend manufacturing | C33: SMB | D33: 24900.00 | E33: 2027-09-16 | F33: Lucia.Herrera@Empresa-Demo.Com | S33: =IF(ISBLANK(H33),"",IF(IFERROR(EXACT(H33,'_key'!$A$1720),FALSE),"✓","✗")) -> 0 | T33: =IF(ISBLANK(I33),"",IF(IFERROR(EXACT(I33,'_key'!$A$1721),FALSE),"✓","✗")) -> 0 | U33: =IF(ISBLANK(J33),"",IF(IFERROR(EXACT(J33,'_key'!$A$1722),FALSE),"✓","✗")) -> 0 | V33: =IF(ISBLANK(K33),"",IF(IFERROR(ABS(K33-'_key'!$A$1723)<=0.01,FALSE),"✓","✗")) -> 0 | W33: =IF(ISBLANK(L33),"",IF(IFERROR(ABS(L33-'_key'!$A$1724)<=0.01,FALSE),"✓","✗")) -> 0 | X33: =IF(ISBLANK(M33),"",IF(IFERROR(EXACT(M33,'_key'!$A$1725),FALSE),"✓","✗")) -> 0 | Y33: =IF(ISBLANK(N33),"",IF(IFERROR(EXACT(N33,'_key'!$A$1726),FALSE),"✓","✗")) -> 0 | Z33: =IF(ISBLANK(O33),"",IF(IFERROR(EXACT(O33,'_key'!$A$1727),FALSE),"✓","✗")) -> 0 | AA33: =IF(ISBLANK(P33),"",IF(IFERROR(ABS(P33-'_key'!$A$1728)<=0.01,FALSE),"✓","✗")) -> 0 | AB33: =IF(ISBLANK(Q33),"",IF(IFERROR(ABS(Q33-'_key'!$A$1729)<=0.01,FALSE),"✓","✗")) -> 0
A34: ACC-0114 | B34: Monarch Bank | C34: Enterprise | D34: $595,800 | E34: 23/06/2027 | F34: Carlos.Mendez@Empresa-Demo.Com | S34: =IF(ISBLANK(H34),"",IF(IFERROR(EXACT(H34,'_key'!$A$1730),FALSE),"✓","✗")) -> 0 | T34: =IF(ISBLANK(I34),"",IF(IFERROR(EXACT(I34,'_key'!$A$1731),FALSE),"✓","✗")) -> 0 | U34: =IF(ISBLANK(J34),"",IF(IFERROR(EXACT(J34,'_key'!$A$1732),FALSE),"✓","✗")) -> 0 | V34: =IF(ISBLANK(K34),"",IF(IFERROR(ABS(K34-'_key'!$A$1733)<=0.01,FALSE),"✓","✗")) -> 0 | W34: =IF(ISBLANK(L34),"",IF(IFERROR(ABS(L34-'_key'!$A$1734)<=0.01,FALSE),"✓","✗")) -> 0 | X34: =IF(ISBLANK(M34),"",IF(IFERROR(EXACT(M34,'_key'!$A$1735),FALSE),"✓","✗")) -> 0 | Y34: =IF(ISBLANK(N34),"",IF(IFERROR(EXACT(N34,'_key'!$A$1736),FALSE),"✓","✗")) -> 0 | Z34: =IF(ISBLANK(O34),"",IF(IFERROR(EXACT(O34,'_key'!$A$1737),FALSE),"✓","✗")) -> 0 | AA34: =IF(ISBLANK(P34),"",IF(IFERROR(ABS(P34-'_key'!$A$1738)<=0.01,FALSE),"✓","✗")) -> 0 | AB34: =IF(ISBLANK(Q34),"",IF(IFERROR(ABS(Q34-'_key'!$A$1739)<=0.01,FALSE),"✓","✗")) -> 0
A35: ACC-0044 | B35: ATLAS HEALTH | C35: mid-market | D35: $105,800.00 | E35: 2027-09-26 | F35: sofia.ramirez@empresa-demo.com | S35: =IF(ISBLANK(H35),"",IF(IFERROR(EXACT(H35,'_key'!$A$1740),FALSE),"✓","✗")) -> 0 | T35: =IF(ISBLANK(I35),"",IF(IFERROR(EXACT(I35,'_key'!$A$1741),FALSE),"✓","✗")) -> 0 | U35: =IF(ISBLANK(J35),"",IF(IFERROR(EXACT(J35,'_key'!$A$1742),FALSE),"✓","✗")) -> 0 | V35: =IF(ISBLANK(K35),"",IF(IFERROR(ABS(K35-'_key'!$A$1743)<=0.01,FALSE),"✓","✗")) -> 0 | W35: =IF(ISBLANK(L35),"",IF(IFERROR(ABS(L35-'_key'!$A$1744)<=0.01,FALSE),"✓","✗")) -> 0 | X35: =IF(ISBLANK(M35),"",IF(IFERROR(EXACT(M35,'_key'!$A$1745),FALSE),"✓","✗")) -> 0 | Y35: =IF(ISBLANK(N35),"",IF(IFERROR(EXACT(N35,'_key'!$A$1746),FALSE),"✓","✗")) -> 0 | Z35: =IF(ISBLANK(O35),"",IF(IFERROR(EXACT(O35,'_key'!$A$1747),FALSE),"✓","✗")) -> 0 | AA35: =IF(ISBLANK(P35),"",IF(IFERROR(ABS(P35-'_key'!$A$1748)<=0.01,FALSE),"✓","✗")) -> 0 | AB35: =IF(ISBLANK(Q35),"",IF(IFERROR(ABS(Q35-'_key'!$A$1749)<=0.01,FALSE),"✓","✗")) -> 0
A36: ACC-0076 | B36: HARBOR CAPITAL | C36: enterprise | D36: 486200.00 | E36: 2026-12-12 | F36: CARLOS.MENDEZ@EMPRESA-DEMO.COM | S36: =IF(ISBLANK(H36),"",IF(IFERROR(EXACT(H36,'_key'!$A$1750),FALSE),"✓","✗")) -> 0 | T36: =IF(ISBLANK(I36),"",IF(IFERROR(EXACT(I36,'_key'!$A$1751),FALSE),"✓","✗")) -> 0 | U36: =IF(ISBLANK(J36),"",IF(IFERROR(EXACT(J36,'_key'!$A$1752),FALSE),"✓","✗")) -> 0 | V36: =IF(ISBLANK(K36),"",IF(IFERROR(ABS(K36-'_key'!$A$1753)<=0.01,FALSE),"✓","✗")) -> 0 | W36: =IF(ISBLANK(L36),"",IF(IFERROR(ABS(L36-'_key'!$A$1754)<=0.01,FALSE),"✓","✗")) -> 0 | X36: =IF(ISBLANK(M36),"",IF(IFERROR(EXACT(M36,'_key'!$A$1755),FALSE),"✓","✗")) -> 0 | Y36: =IF(ISBLANK(N36),"",IF(IFERROR(EXACT(N36,'_key'!$A$1756),FALSE),"✓","✗")) -> 0 | Z36: =IF(ISBLANK(O36),"",IF(IFERROR(EXACT(O36,'_key'!$A$1757),FALSE),"✓","✗")) -> 0 | AA36: =IF(ISBLANK(P36),"",IF(IFERROR(ABS(P36-'_key'!$A$1758)<=0.01,FALSE),"✓","✗")) -> 0 | AB36: =IF(ISBLANK(Q36),"",IF(IFERROR(ABS(Q36-'_key'!$A$1759)<=0.01,FALSE),"✓","✗")) -> 0
A37: ACC-0026 | B37: Aurora Energy | C37: Ent | D37: $301,100.00 | E37: 19/08/2027 | F37: carlos.mendez@empresa-demo.com | S37: =IF(ISBLANK(H37),"",IF(IFERROR(EXACT(H37,'_key'!$A$1760),FALSE),"✓","✗")) -> 0 | T37: =IF(ISBLANK(I37),"",IF(IFERROR(EXACT(I37,'_key'!$A$1761),FALSE),"✓","✗")) -> 0 | U37: =IF(ISBLANK(J37),"",IF(IFERROR(EXACT(J37,'_key'!$A$1762),FALSE),"✓","✗")) -> 0 | V37: =IF(ISBLANK(K37),"",IF(IFERROR(ABS(K37-'_key'!$A$1763)<=0.01,FALSE),"✓","✗")) -> 0 | W37: =IF(ISBLANK(L37),"",IF(IFERROR(ABS(L37-'_key'!$A$1764)<=0.01,FALSE),"✓","✗")) -> 0 | X37: =IF(ISBLANK(M37),"",IF(IFERROR(EXACT(M37,'_key'!$A$1765),FALSE),"✓","✗")) -> 0 | Y37: =IF(ISBLANK(N37),"",IF(IFERROR(EXACT(N37,'_key'!$A$1766),FALSE),"✓","✗")) -> 0 | Z37: =IF(ISBLANK(O37),"",IF(IFERROR(EXACT(O37,'_key'!$A$1767),FALSE),"✓","✗")) -> 0 | AA37: =IF(ISBLANK(P37),"",IF(IFERROR(ABS(P37-'_key'!$A$1768)<=0.01,FALSE),"✓","✗")) -> 0 | AB37: =IF(ISBLANK(Q37),"",IF(IFERROR(ABS(Q37-'_key'!$A$1769)<=0.01,FALSE),"✓","✗")) -> 0
A38: ACC-0251 | B38: liberty ventures | C38: ENTERPRISE | D38: 27,000 USD | E38: 14/04/2027 | F38: ana.lopez@empresa-demo.com | S38: =IF(ISBLANK(H38),"",IF(IFERROR(EXACT(H38,'_key'!$A$1770),FALSE),"✓","✗")) -> 0 | T38: =IF(ISBLANK(I38),"",IF(IFERROR(EXACT(I38,'_key'!$A$1771),FALSE),"✓","✗")) -> 0 | U38: =IF(ISBLANK(J38),"",IF(IFERROR(EXACT(J38,'_key'!$A$1772),FALSE),"✓","✗")) -> 0 | V38: =IF(ISBLANK(K38),"",IF(IFERROR(ABS(K38-'_key'!$A$1773)<=0.01,FALSE),"✓","✗")) -> 0 | W38: =IF(ISBLANK(L38),"",IF(IFERROR(ABS(L38-'_key'!$A$1774)<=0.01,FALSE),"✓","✗")) -> 0 | X38: =IF(ISBLANK(M38),"",IF(IFERROR(EXACT(M38,'_key'!$A$1775),FALSE),"✓","✗")) -> 0 | Y38: =IF(ISBLANK(N38),"",IF(IFERROR(EXACT(N38,'_key'!$A$1776),FALSE),"✓","✗")) -> 0 | Z38: =IF(ISBLANK(O38),"",IF(IFERROR(EXACT(O38,'_key'!$A$1777),FALSE),"✓","✗")) -> 0 | AA38: =IF(ISBLANK(P38),"",IF(IFERROR(EXACT(P38,'_key'!$A$1778),FALSE),"✓","✗")) -> 0 | AB38: =IF(ISBLANK(Q38),"",IF(IFERROR(ABS(Q38-'_key'!$A$1779)<=0.01,FALSE),"✓","✗")) -> 0
A39: ACC-0029 | B39: Sierra Holdings | C39: smb | D39: 21700.00 | E39: 02/08/2027 | F39: Michael.Brooks@Empresa-Demo.Com | S39: =IF(ISBLANK(H39),"",IF(IFERROR(EXACT(H39,'_key'!$A$1780),FALSE),"✓","✗")) -> 0 | T39: =IF(ISBLANK(I39),"",IF(IFERROR(EXACT(I39,'_key'!$A$1781),FALSE),"✓","✗")) -> 0 | U39: =IF(ISBLANK(J39),"",IF(IFERROR(EXACT(J39,'_key'!$A$1782),FALSE),"✓","✗")) -> 0 | V39: =IF(ISBLANK(K39),"",IF(IFERROR(ABS(K39-'_key'!$A$1783)<=0.01,FALSE),"✓","✗")) -> 0 | W39: =IF(ISBLANK(L39),"",IF(IFERROR(ABS(L39-'_key'!$A$1784)<=0.01,FALSE),"✓","✗")) -> 0 | X39: =IF(ISBLANK(M39),"",IF(IFERROR(EXACT(M39,'_key'!$A$1785),FALSE),"✓","✗")) -> 0 | Y39: =IF(ISBLANK(N39),"",IF(IFERROR(EXACT(N39,'_key'!$A$1786),FALSE),"✓","✗")) -> 0 | Z39: =IF(ISBLANK(O39),"",IF(IFERROR(EXACT(O39,'_key'!$A$1787),FALSE),"✓","✗")) -> 0 | AA39: =IF(ISBLANK(P39),"",IF(IFERROR(ABS(P39-'_key'!$A$1788)<=0.01,FALSE),"✓","✗")) -> 0 | AB39: =IF(ISBLANK(Q39),"",IF(IFERROR(ABS(Q39-'_key'!$A$1789)<=0.01,FALSE),"✓","✗")) -> 0
A40: ACC-0030 | B40: liberty financial | C40: mid-market | D40: 45,700 USD | E40: 06/05/2027 | F40: emily.carter@empresa-demo.com | S40: =IF(ISBLANK(H40),"",IF(IFERROR(EXACT(H40,'_key'!$A$1790),FALSE),"✓","✗")) -> 0 | T40: =IF(ISBLANK(I40),"",IF(IFERROR(EXACT(I40,'_key'!$A$1791),FALSE),"✓","✗")) -> 0 | U40: =IF(ISBLANK(J40),"",IF(IFERROR(EXACT(J40,'_key'!$A$1792),FALSE),"✓","✗")) -> 0 | V40: =IF(ISBLANK(K40),"",IF(IFERROR(ABS(K40-'_key'!$A$1793)<=0.01,FALSE),"✓","✗")) -> 0 | W40: =IF(ISBLANK(L40),"",IF(IFERROR(ABS(L40-'_key'!$A$1794)<=0.01,FALSE),"✓","✗")) -> 0 | X40: =IF(ISBLANK(M40),"",IF(IFERROR(EXACT(M40,'_key'!$A$1795),FALSE),"✓","✗")) -> 0 | Y40: =IF(ISBLANK(N40),"",IF(IFERROR(EXACT(N40,'_key'!$A$1796),FALSE),"✓","✗")) -> 0 | Z40: =IF(ISBLANK(O40),"",IF(IFERROR(EXACT(O40,'_key'!$A$1797),FALSE),"✓","✗")) -> 0 | AA40: =IF(ISBLANK(P40),"",IF(IFERROR(ABS(P40-'_key'!$A$1798)<=0.01,FALSE),"✓","✗")) -> 0 | AB40: =IF(ISBLANK(Q40),"",IF(IFERROR(ABS(Q40-'_key'!$A$1799)<=0.01,FALSE),"✓","✗")) -> 0
A41: ACC-0133 | B41: pioneer capital | C41: Mid Market | D41: USD 86100 | E41: 26/05/2027 | S41: =IF(ISBLANK(H41),"",IF(IFERROR(EXACT(H41,'_key'!$A$1800),FALSE),"✓","✗")) -> 0 | T41: =IF(ISBLANK(I41),"",IF(IFERROR(EXACT(I41,'_key'!$A$1801),FALSE),"✓","✗")) -> 0 | U41: =IF(ISBLANK(J41),"",IF(IFERROR(EXACT(J41,'_key'!$A$1802),FALSE),"✓","✗")) -> 0 | V41: =IF(ISBLANK(K41),"",IF(IFERROR(ABS(K41-'_key'!$A$1803)<=0.01,FALSE),"✓","✗")) -> 0 | W41: =IF(ISBLANK(L41),"",IF(IFERROR(ABS(L41-'_key'!$A$1804)<=0.01,FALSE),"✓","✗")) -> 0 | X41: =IF(ISBLANK(M41),"",IF(IFERROR(EXACT(M41,'_key'!$A$1805),FALSE),"✓","✗")) -> 0 | Y41: =IF(ISBLANK(N41),"",IF(IFERROR(EXACT(N41,'_key'!$A$1806),FALSE),"✓","✗")) -> 0 | Z41: =IF(ISBLANK(O41),"",IF(IFERROR(EXACT(O41,'_key'!$A$1807),FALSE),"✓","✗")) -> 0 | AA41: =IF(ISBLANK(P41),"",IF(IFERROR(ABS(P41-'_key'!$A$1808)<=0.01,FALSE),"✓","✗")) -> 0 | AB41: =IF(ISBLANK(Q41),"",IF(IFERROR(ABS(Q41-'_key'!$A$1809)<=0.01,FALSE),"✓","✗")) -> 0
A42: ACC-0079 | B42: Ironwood Systems | C42: SMB | D42: $12,700.00 | E42: 30/03/2027 | S42: =IF(ISBLANK(H42),"",IF(IFERROR(EXACT(H42,'_key'!$A$1810),FALSE),"✓","✗")) -> 0 | T42: =IF(ISBLANK(I42),"",IF(IFERROR(EXACT(I42,'_key'!$A$1811),FALSE),"✓","✗")) -> 0 | U42: =IF(ISBLANK(J42),"",IF(IFERROR(EXACT(J42,'_key'!$A$1812),FALSE),"✓","✗")) -> 0 | V42: =IF(ISBLANK(K42),"",IF(IFERROR(ABS(K42-'_key'!$A$1813)<=0.01,FALSE),"✓","✗")) -> 0 | W42: =IF(ISBLANK(L42),"",IF(IFERROR(ABS(L42-'_key'!$A$1814)<=0.01,FALSE),"✓","✗")) -> 0 | X42: =IF(ISBLANK(M42),"",IF(IFERROR(EXACT(M42,'_key'!$A$1815),FALSE),"✓","✗")) -> 0 | Y42: =IF(ISBLANK(N42),"",IF(IFERROR(EXACT(N42,'_key'!$A$1816),FALSE),"✓","✗")) -> 0 | Z42: =IF(ISBLANK(O42),"",IF(IFERROR(EXACT(O42,'_key'!$A$1817),FALSE),"✓","✗")) -> 0 | AA42: =IF(ISBLANK(P42),"",IF(IFERROR(ABS(P42-'_key'!$A$1818)<=0.01,FALSE),"✓","✗")) -> 0 | AB42: =IF(ISBLANK(Q42),"",IF(IFERROR(ABS(Q42-'_key'!$A$1819)<=0.01,FALSE),"✓","✗")) -> 0
A43: ACC-0096 | B43: Riverbend Insurance | C43: SMB | D43: USD 18100 | E43: 2026-10-21 | F43: james.walker@empresa-demo.com | S43: =IF(ISBLANK(H43),"",IF(IFERROR(EXACT(H43,'_key'!$A$1820),FALSE),"✓","✗")) -> 0 | T43: =IF(ISBLANK(I43),"",IF(IFERROR(EXACT(I43,'_key'!$A$1821),FALSE),"✓","✗")) -> 0 | U43: =IF(ISBLANK(J43),"",IF(IFERROR(EXACT(J43,'_key'!$A$1822),FALSE),"✓","✗")) -> 0 | V43: =IF(ISBLANK(K43),"",IF(IFERROR(ABS(K43-'_key'!$A$1823)<=0.01,FALSE),"✓","✗")) -> 0 | W43: =IF(ISBLANK(L43),"",IF(IFERROR(ABS(L43-'_key'!$A$1824)<=0.01,FALSE),"✓","✗")) -> 0 | X43: =IF(ISBLANK(M43),"",IF(IFERROR(EXACT(M43,'_key'!$A$1825),FALSE),"✓","✗")) -> 0 | Y43: =IF(ISBLANK(N43),"",IF(IFERROR(EXACT(N43,'_key'!$A$1826),FALSE),"✓","✗")) -> 0 | Z43: =IF(ISBLANK(O43),"",IF(IFERROR(EXACT(O43,'_key'!$A$1827),FALSE),"✓","✗")) -> 0 | AA43: =IF(ISBLANK(P43),"",IF(IFERROR(ABS(P43-'_key'!$A$1828)<=0.01,FALSE),"✓","✗")) -> 0 | AB43: =IF(ISBLANK(Q43),"",IF(IFERROR(ABS(Q43-'_key'!$A$1829)<=0.01,FALSE),"✓","✗")) -> 0
A44: ACC-0067 | B44: Meridian Manufacturing | C44: Ent | D44: 479800 | E44: 22/06/2027 | F44: ana.lopez@empresa-demo.com | S44: =IF(ISBLANK(H44),"",IF(IFERROR(EXACT(H44,'_key'!$A$1830),FALSE),"✓","✗")) -> 0 | T44: =IF(ISBLANK(I44),"",IF(IFERROR(EXACT(I44,'_key'!$A$1831),FALSE),"✓","✗")) -> 0 | U44: =IF(ISBLANK(J44),"",IF(IFERROR(EXACT(J44,'_key'!$A$1832),FALSE),"✓","✗")) -> 0 | V44: =IF(ISBLANK(K44),"",IF(IFERROR(ABS(K44-'_key'!$A$1833)<=0.01,FALSE),"✓","✗")) -> 0 | W44: =IF(ISBLANK(L44),"",IF(IFERROR(ABS(L44-'_key'!$A$1834)<=0.01,FALSE),"✓","✗")) -> 0 | X44: =IF(ISBLANK(M44),"",IF(IFERROR(EXACT(M44,'_key'!$A$1835),FALSE),"✓","✗")) -> 0 | Y44: =IF(ISBLANK(N44),"",IF(IFERROR(EXACT(N44,'_key'!$A$1836),FALSE),"✓","✗")) -> 0 | Z44: =IF(ISBLANK(O44),"",IF(IFERROR(EXACT(O44,'_key'!$A$1837),FALSE),"✓","✗")) -> 0 | AA44: =IF(ISBLANK(P44),"",IF(IFERROR(ABS(P44-'_key'!$A$1838)<=0.01,FALSE),"✓","✗")) -> 0 | AB44: =IF(ISBLANK(Q44),"",IF(IFERROR(ABS(Q44-'_key'!$A$1839)<=0.01,FALSE),"✓","✗")) -> 0
A45: ACC-0083 | B45: cedar partners | C45: SMB | D45: 37400 | E45: 2027-06-28 | F45: lucia.herrera@empresa-demo.com | S45: =IF(ISBLANK(H45),"",IF(IFERROR(EXACT(H45,'_key'!$A$1840),FALSE),"✓","✗")) -> 0 | T45: =IF(ISBLANK(I45),"",IF(IFERROR(EXACT(I45,'_key'!$A$1841),FALSE),"✓","✗")) -> 0 | U45: =IF(ISBLANK(J45),"",IF(IFERROR(EXACT(J45,'_key'!$A$1842),FALSE),"✓","✗")) -> 0 | V45: =IF(ISBLANK(K45),"",IF(IFERROR(ABS(K45-'_key'!$A$1843)<=0.01,FALSE),"✓","✗")) -> 0 | W45: =IF(ISBLANK(L45),"",IF(IFERROR(ABS(L45-'_key'!$A$1844)<=0.01,FALSE),"✓","✗")) -> 0 | X45: =IF(ISBLANK(M45),"",IF(IFERROR(EXACT(M45,'_key'!$A$1845),FALSE),"✓","✗")) -> 0 | Y45: =IF(ISBLANK(N45),"",IF(IFERROR(EXACT(N45,'_key'!$A$1846),FALSE),"✓","✗")) -> 0 | Z45: =IF(ISBLANK(O45),"",IF(IFERROR(EXACT(O45,'_key'!$A$1847),FALSE),"✓","✗")) -> 0 | AA45: =IF(ISBLANK(P45),"",IF(IFERROR(ABS(P45-'_key'!$A$1848)<=0.01,FALSE),"✓","✗")) -> 0 | AB45: =IF(ISBLANK(Q45),"",IF(IFERROR(ABS(Q45-'_key'!$A$1849)<=0.01,FALSE),"✓","✗")) -> 0
A46: ACC-0053 | B46: blue ridge partners | C46: Small Business | D46: $36,400 | E46: 03/07/2027 | S46: =IF(ISBLANK(H46),"",IF(IFERROR(EXACT(H46,'_key'!$A$1850),FALSE),"✓","✗")) -> 0 | T46: =IF(ISBLANK(I46),"",IF(IFERROR(EXACT(I46,'_key'!$A$1851),FALSE),"✓","✗")) -> 0 | U46: =IF(ISBLANK(J46),"",IF(IFERROR(EXACT(J46,'_key'!$A$1852),FALSE),"✓","✗")) -> 0 | V46: =IF(ISBLANK(K46),"",IF(IFERROR(ABS(K46-'_key'!$A$1853)<=0.01,FALSE),"✓","✗")) -> 0 | W46: =IF(ISBLANK(L46),"",IF(IFERROR(ABS(L46-'_key'!$A$1854)<=0.01,FALSE),"✓","✗")) -> 0 | X46: =IF(ISBLANK(M46),"",IF(IFERROR(EXACT(M46,'_key'!$A$1855),FALSE),"✓","✗")) -> 0 | Y46: =IF(ISBLANK(N46),"",IF(IFERROR(EXACT(N46,'_key'!$A$1856),FALSE),"✓","✗")) -> 0 | Z46: =IF(ISBLANK(O46),"",IF(IFERROR(EXACT(O46,'_key'!$A$1857),FALSE),"✓","✗")) -> 0 | AA46: =IF(ISBLANK(P46),"",IF(IFERROR(ABS(P46-'_key'!$A$1858)<=0.01,FALSE),"✓","✗")) -> 0 | AB46: =IF(ISBLANK(Q46),"",IF(IFERROR(ABS(Q46-'_key'!$A$1859)<=0.01,FALSE),"✓","✗")) -> 0
A47: ACC-0062 | B47: coastal energy | C47: smb | D47: 20,400 USD | E47: 12/06/2027 | S47: =IF(ISBLANK(H47),"",IF(IFERROR(EXACT(H47,'_key'!$A$1860),FALSE),"✓","✗")) -> 0 | T47: =IF(ISBLANK(I47),"",IF(IFERROR(EXACT(I47,'_key'!$A$1861),FALSE),"✓","✗")) -> 0 | U47: =IF(ISBLANK(J47),"",IF(IFERROR(EXACT(J47,'_key'!$A$1862),FALSE),"✓","✗")) -> 0 | V47: =IF(ISBLANK(K47),"",IF(IFERROR(ABS(K47-'_key'!$A$1863)<=0.01,FALSE),"✓","✗")) -> 0 | W47: =IF(ISBLANK(L47),"",IF(IFERROR(ABS(L47-'_key'!$A$1864)<=0.01,FALSE),"✓","✗")) -> 0 | X47: =IF(ISBLANK(M47),"",IF(IFERROR(EXACT(M47,'_key'!$A$1865),FALSE),"✓","✗")) -> 0 | Y47: =IF(ISBLANK(N47),"",IF(IFERROR(EXACT(N47,'_key'!$A$1866),FALSE),"✓","✗")) -> 0 | Z47: =IF(ISBLANK(O47),"",IF(IFERROR(EXACT(O47,'_key'!$A$1867),FALSE),"✓","✗")) -> 0 | AA47: =IF(ISBLANK(P47),"",IF(IFERROR(ABS(P47-'_key'!$A$1868)<=0.01,FALSE),"✓","✗")) -> 0 | AB47: =IF(ISBLANK(Q47),"",IF(IFERROR(ABS(Q47-'_key'!$A$1869)<=0.01,FALSE),"✓","✗")) -> 0
A48: ACC-0081 | B48: Atlas Logistics | C48: SMB | D48: $35,700 | E48: 01/11/2026 | F48: Michael.Brooks@Empresa-Demo.Com | S48: =IF(ISBLANK(H48),"",IF(IFERROR(EXACT(H48,'_key'!$A$1870),FALSE),"✓","✗")) -> 0 | T48: =IF(ISBLANK(I48),"",IF(IFERROR(EXACT(I48,'_key'!$A$1871),FALSE),"✓","✗")) -> 0 | U48: =IF(ISBLANK(J48),"",IF(IFERROR(EXACT(J48,'_key'!$A$1872),FALSE),"✓","✗")) -> 0 | V48: =IF(ISBLANK(K48),"",IF(IFERROR(ABS(K48-'_key'!$A$1873)<=0.01,FALSE),"✓","✗")) -> 0 | W48: =IF(ISBLANK(L48),"",IF(IFERROR(ABS(L48-'_key'!$A$1874)<=0.01,FALSE),"✓","✗")) -> 0 | X48: =IF(ISBLANK(M48),"",IF(IFERROR(EXACT(M48,'_key'!$A$1875),FALSE),"✓","✗")) -> 0 | Y48: =IF(ISBLANK(N48),"",IF(IFERROR(EXACT(N48,'_key'!$A$1876),FALSE),"✓","✗")) -> 0 | Z48: =IF(ISBLANK(O48),"",IF(IFERROR(EXACT(O48,'_key'!$A$1877),FALSE),"✓","✗")) -> 0 | AA48: =IF(ISBLANK(P48),"",IF(IFERROR(ABS(P48-'_key'!$A$1878)<=0.01,FALSE),"✓","✗")) -> 0 | AB48: =IF(ISBLANK(Q48),"",IF(IFERROR(ABS(Q48-'_key'!$A$1879)<=0.01,FALSE),"✓","✗")) -> 0
A49: ACC-0081 | B49: Atlas Logistics | C49: SMB | D49: 35700.00 | E49: 01/11/2026 | F49: MICHAEL.BROOKS@EMPRESA-DEMO.COM | S49: =IF(ISBLANK(H49),"",IF(IFERROR(EXACT(H49,'_key'!$A$1880),FALSE),"✓","✗")) -> 0 | T49: =IF(ISBLANK(I49),"",IF(IFERROR(EXACT(I49,'_key'!$A$1881),FALSE),"✓","✗")) -> 0 | U49: =IF(ISBLANK(J49),"",IF(IFERROR(EXACT(J49,'_key'!$A$1882),FALSE),"✓","✗")) -> 0 | V49: =IF(ISBLANK(K49),"",IF(IFERROR(ABS(K49-'_key'!$A$1883)<=0.01,FALSE),"✓","✗")) -> 0 | W49: =IF(ISBLANK(L49),"",IF(IFERROR(ABS(L49-'_key'!$A$1884)<=0.01,FALSE),"✓","✗")) -> 0 | X49: =IF(ISBLANK(M49),"",IF(IFERROR(EXACT(M49,'_key'!$A$1885),FALSE),"✓","✗")) -> 0 | Y49: =IF(ISBLANK(N49),"",IF(IFERROR(EXACT(N49,'_key'!$A$1886),FALSE),"✓","✗")) -> 0 | Z49: =IF(ISBLANK(O49),"",IF(IFERROR(EXACT(O49,'_key'!$A$1887),FALSE),"✓","✗")) -> 0 | AA49: =IF(ISBLANK(P49),"",IF(IFERROR(ABS(P49-'_key'!$A$1888)<=0.01,FALSE),"✓","✗")) -> 0 | AB49: =IF(ISBLANK(Q49),"",IF(IFERROR(ABS(Q49-'_key'!$A$1889)<=0.01,FALSE),"✓","✗")) -> 0
A50: ACC-0018 | B50: Horizon Health | C50: Small Business | D50: 18600 | E50: 2027-03-31 | F50: michael.brooks@empresa-demo.com | S50: =IF(ISBLANK(H50),"",IF(IFERROR(EXACT(H50,'_key'!$A$1890),FALSE),"✓","✗")) -> 0 | T50: =IF(ISBLANK(I50),"",IF(IFERROR(EXACT(I50,'_key'!$A$1891),FALSE),"✓","✗")) -> 0 | U50: =IF(ISBLANK(J50),"",IF(IFERROR(EXACT(J50,'_key'!$A$1892),FALSE),"✓","✗")) -> 0 | V50: =IF(ISBLANK(K50),"",IF(IFERROR(ABS(K50-'_key'!$A$1893)<=0.01,FALSE),"✓","✗")) -> 0 | W50: =IF(ISBLANK(L50),"",IF(IFERROR(ABS(L50-'_key'!$A$1894)<=0.01,FALSE),"✓","✗")) -> 0 | X50: =IF(ISBLANK(M50),"",IF(IFERROR(EXACT(M50,'_key'!$A$1895),FALSE),"✓","✗")) -> 0 | Y50: =IF(ISBLANK(N50),"",IF(IFERROR(EXACT(N50,'_key'!$A$1896),FALSE),"✓","✗")) -> 0 | Z50: =IF(ISBLANK(O50),"",IF(IFERROR(EXACT(O50,'_key'!$A$1897),FALSE),"✓","✗")) -> 0 | AA50: =IF(ISBLANK(P50),"",IF(IFERROR(ABS(P50-'_key'!$A$1898)<=0.01,FALSE),"✓","✗")) -> 0 | AB50: =IF(ISBLANK(Q50),"",IF(IFERROR(ABS(Q50-'_key'!$A$1899)<=0.01,FALSE),"✓","✗")) -> 0
A51: ACC-0036 | B51: Granite Logistics | C51: SMB | D51: 30100 | E51: 03/02/2027 | F51: James.Walker@Empresa-Demo.Com | S51: =IF(ISBLANK(H51),"",IF(IFERROR(EXACT(H51,'_key'!$A$1900),FALSE),"✓","✗")) -> 0 | T51: =IF(ISBLANK(I51),"",IF(IFERROR(EXACT(I51,'_key'!$A$1901),FALSE),"✓","✗")) -> 0 | U51: =IF(ISBLANK(J51),"",IF(IFERROR(EXACT(J51,'_key'!$A$1902),FALSE),"✓","✗")) -> 0 | V51: =IF(ISBLANK(K51),"",IF(IFERROR(ABS(K51-'_key'!$A$1903)<=0.01,FALSE),"✓","✗")) -> 0 | W51: =IF(ISBLANK(L51),"",IF(IFERROR(ABS(L51-'_key'!$A$1904)<=0.01,FALSE),"✓","✗")) -> 0 | X51: =IF(ISBLANK(M51),"",IF(IFERROR(EXACT(M51,'_key'!$A$1905),FALSE),"✓","✗")) -> 0 | Y51: =IF(ISBLANK(N51),"",IF(IFERROR(EXACT(N51,'_key'!$A$1906),FALSE),"✓","✗")) -> 0 | Z51: =IF(ISBLANK(O51),"",IF(IFERROR(EXACT(O51,'_key'!$A$1907),FALSE),"✓","✗")) -> 0 | AA51: =IF(ISBLANK(P51),"",IF(IFERROR(ABS(P51-'_key'!$A$1908)<=0.01,FALSE),"✓","✗")) -> 0 | AB51: =IF(ISBLANK(Q51),"",IF(IFERROR(ABS(Q51-'_key'!$A$1909)<=0.01,FALSE),"✓","✗")) -> 0
A52: ACC-0148 | B52: Pioneer Financial | C52: SMB | D52: 22,000 USD | E52: 2027-06-16 | S52: =IF(ISBLANK(H52),"",IF(IFERROR(EXACT(H52,'_key'!$A$1910),FALSE),"✓","✗")) -> 0 | T52: =IF(ISBLANK(I52),"",IF(IFERROR(EXACT(I52,'_key'!$A$1911),FALSE),"✓","✗")) -> 0 | U52: =IF(ISBLANK(J52),"",IF(IFERROR(EXACT(J52,'_key'!$A$1912),FALSE),"✓","✗")) -> 0 | V52: =IF(ISBLANK(K52),"",IF(IFERROR(ABS(K52-'_key'!$A$1913)<=0.01,FALSE),"✓","✗")) -> 0 | W52: =IF(ISBLANK(L52),"",IF(IFERROR(ABS(L52-'_key'!$A$1914)<=0.01,FALSE),"✓","✗")) -> 0 | X52: =IF(ISBLANK(M52),"",IF(IFERROR(EXACT(M52,'_key'!$A$1915),FALSE),"✓","✗")) -> 0 | Y52: =IF(ISBLANK(N52),"",IF(IFERROR(EXACT(N52,'_key'!$A$1916),FALSE),"✓","✗")) -> 0 | Z52: =IF(ISBLANK(O52),"",IF(IFERROR(EXACT(O52,'_key'!$A$1917),FALSE),"✓","✗")) -> 0 | AA52: =IF(ISBLANK(P52),"",IF(IFERROR(ABS(P52-'_key'!$A$1918)<=0.01,FALSE),"✓","✗")) -> 0 | AB52: =IF(ISBLANK(Q52),"",IF(IFERROR(ABS(Q52-'_key'!$A$1919)<=0.01,FALSE),"✓","✗")) -> 0
A53: ACC-0066 | B53: LIBERTY LOGISTICS | C53: Small Business | D53: 18400.00 | E53: 16/10/2026 | S53: =IF(ISBLANK(H53),"",IF(IFERROR(EXACT(H53,'_key'!$A$1920),FALSE),"✓","✗")) -> 0 | T53: =IF(ISBLANK(I53),"",IF(IFERROR(EXACT(I53,'_key'!$A$1921),FALSE),"✓","✗")) -> 0 | U53: =IF(ISBLANK(J53),"",IF(IFERROR(EXACT(J53,'_key'!$A$1922),FALSE),"✓","✗")) -> 0 | V53: =IF(ISBLANK(K53),"",IF(IFERROR(ABS(K53-'_key'!$A$1923)<=0.01,FALSE),"✓","✗")) -> 0 | W53: =IF(ISBLANK(L53),"",IF(IFERROR(ABS(L53-'_key'!$A$1924)<=0.01,FALSE),"✓","✗")) -> 0 | X53: =IF(ISBLANK(M53),"",IF(IFERROR(EXACT(M53,'_key'!$A$1925),FALSE),"✓","✗")) -> 0 | Y53: =IF(ISBLANK(N53),"",IF(IFERROR(EXACT(N53,'_key'!$A$1926),FALSE),"✓","✗")) -> 0 | Z53: =IF(ISBLANK(O53),"",IF(IFERROR(EXACT(O53,'_key'!$A$1927),FALSE),"✓","✗")) -> 0 | AA53: =IF(ISBLANK(P53),"",IF(IFERROR(ABS(P53-'_key'!$A$1928)<=0.01,FALSE),"✓","✗")) -> 0 | AB53: =IF(ISBLANK(Q53),"",IF(IFERROR(ABS(Q53-'_key'!$A$1929)<=0.01,FALSE),"✓","✗")) -> 0
A54: ACC-0032 | B54: FALCON CAPITAL | C54: Mid-Market | D54: $114,500 | E54: 2026-12-25 | F54: emily.carter@empresa-demo.com | S54: =IF(ISBLANK(H54),"",IF(IFERROR(EXACT(H54,'_key'!$A$1930),FALSE),"✓","✗")) -> 0 | T54: =IF(ISBLANK(I54),"",IF(IFERROR(EXACT(I54,'_key'!$A$1931),FALSE),"✓","✗")) -> 0 | U54: =IF(ISBLANK(J54),"",IF(IFERROR(EXACT(J54,'_key'!$A$1932),FALSE),"✓","✗")) -> 0 | V54: =IF(ISBLANK(K54),"",IF(IFERROR(ABS(K54-'_key'!$A$1933)<=0.01,FALSE),"✓","✗")) -> 0 | W54: =IF(ISBLANK(L54),"",IF(IFERROR(ABS(L54-'_key'!$A$1934)<=0.01,FALSE),"✓","✗")) -> 0 | X54: =IF(ISBLANK(M54),"",IF(IFERROR(EXACT(M54,'_key'!$A$1935),FALSE),"✓","✗")) -> 0 | Y54: =IF(ISBLANK(N54),"",IF(IFERROR(EXACT(N54,'_key'!$A$1936),FALSE),"✓","✗")) -> 0 | Z54: =IF(ISBLANK(O54),"",IF(IFERROR(EXACT(O54,'_key'!$A$1937),FALSE),"✓","✗")) -> 0 | AA54: =IF(ISBLANK(P54),"",IF(IFERROR(ABS(P54-'_key'!$A$1938)<=0.01,FALSE),"✓","✗")) -> 0 | AB54: =IF(ISBLANK(Q54),"",IF(IFERROR(ABS(Q54-'_key'!$A$1939)<=0.01,FALSE),"✓","✗")) -> 0
A55: ACC-0063 | B55: Oakmont Logistics | C55: Small Business | D55: 19,900 USD | E55: 14/08/2027 | F55: Michael.Brooks@Empresa-Demo.Com | S55: =IF(ISBLANK(H55),"",IF(IFERROR(EXACT(H55,'_key'!$A$1940),FALSE),"✓","✗")) -> 0 | T55: =IF(ISBLANK(I55),"",IF(IFERROR(EXACT(I55,'_key'!$A$1941),FALSE),"✓","✗")) -> 0 | U55: =IF(ISBLANK(J55),"",IF(IFERROR(EXACT(J55,'_key'!$A$1942),FALSE),"✓","✗")) -> 0 | V55: =IF(ISBLANK(K55),"",IF(IFERROR(ABS(K55-'_key'!$A$1943)<=0.01,FALSE),"✓","✗")) -> 0 | W55: =IF(ISBLANK(L55),"",IF(IFERROR(ABS(L55-'_key'!$A$1944)<=0.01,FALSE),"✓","✗")) -> 0 | X55: =IF(ISBLANK(M55),"",IF(IFERROR(EXACT(M55,'_key'!$A$1945),FALSE),"✓","✗")) -> 0 | Y55: =IF(ISBLANK(N55),"",IF(IFERROR(EXACT(N55,'_key'!$A$1946),FALSE),"✓","✗")) -> 0 | Z55: =IF(ISBLANK(O55),"",IF(IFERROR(EXACT(O55,'_key'!$A$1947),FALSE),"✓","✗")) -> 0 | AA55: =IF(ISBLANK(P55),"",IF(IFERROR(ABS(P55-'_key'!$A$1948)<=0.01,FALSE),"✓","✗")) -> 0 | AB55: =IF(ISBLANK(Q55),"",IF(IFERROR(ABS(Q55-'_key'!$A$1949)<=0.01,FALSE),"✓","✗")) -> 0
A56: ACC-0084 | B56: Aurora Partners | C56: Mid Market | D56: $104,100.00 | E56: 15/07/2027 | F56: sofia.ramirez@empresa-demo.com | S56: =IF(ISBLANK(H56),"",IF(IFERROR(EXACT(H56,'_key'!$A$1950),FALSE),"✓","✗")) -> 0 | T56: =IF(ISBLANK(I56),"",IF(IFERROR(EXACT(I56,'_key'!$A$1951),FALSE),"✓","✗")) -> 0 | U56: =IF(ISBLANK(J56),"",IF(IFERROR(EXACT(J56,'_key'!$A$1952),FALSE),"✓","✗")) -> 0 | V56: =IF(ISBLANK(K56),"",IF(IFERROR(ABS(K56-'_key'!$A$1953)<=0.01,FALSE),"✓","✗")) -> 0 | W56: =IF(ISBLANK(L56),"",IF(IFERROR(ABS(L56-'_key'!$A$1954)<=0.01,FALSE),"✓","✗")) -> 0 | X56: =IF(ISBLANK(M56),"",IF(IFERROR(EXACT(M56,'_key'!$A$1955),FALSE),"✓","✗")) -> 0 | Y56: =IF(ISBLANK(N56),"",IF(IFERROR(EXACT(N56,'_key'!$A$1956),FALSE),"✓","✗")) -> 0 | Z56: =IF(ISBLANK(O56),"",IF(IFERROR(EXACT(O56,'_key'!$A$1957),FALSE),"✓","✗")) -> 0 | AA56: =IF(ISBLANK(P56),"",IF(IFERROR(ABS(P56-'_key'!$A$1958)<=0.01,FALSE),"✓","✗")) -> 0 | AB56: =IF(ISBLANK(Q56),"",IF(IFERROR(ABS(Q56-'_key'!$A$1959)<=0.01,FALSE),"✓","✗")) -> 0
A57: ACC-0254 | B57: cobalt ventures | C57: enterprise | D57: $10,000 | E57: 29/03/2027 | S57: =IF(ISBLANK(H57),"",IF(IFERROR(EXACT(H57,'_key'!$A$1960),FALSE),"✓","✗")) -> 0 | T57: =IF(ISBLANK(I57),"",IF(IFERROR(EXACT(I57,'_key'!$A$1961),FALSE),"✓","✗")) -> 0 | U57: =IF(ISBLANK(J57),"",IF(IFERROR(EXACT(J57,'_key'!$A$1962),FALSE),"✓","✗")) -> 0 | V57: =IF(ISBLANK(K57),"",IF(IFERROR(ABS(K57-'_key'!$A$1963)<=0.01,FALSE),"✓","✗")) -> 0 | W57: =IF(ISBLANK(L57),"",IF(IFERROR(ABS(L57-'_key'!$A$1964)<=0.01,FALSE),"✓","✗")) -> 0 | X57: =IF(ISBLANK(M57),"",IF(IFERROR(EXACT(M57,'_key'!$A$1965),FALSE),"✓","✗")) -> 0 | Y57: =IF(ISBLANK(N57),"",IF(IFERROR(EXACT(N57,'_key'!$A$1966),FALSE),"✓","✗")) -> 0 | Z57: =IF(ISBLANK(O57),"",IF(IFERROR(EXACT(O57,'_key'!$A$1967),FALSE),"✓","✗")) -> 0 | AA57: =IF(ISBLANK(P57),"",IF(IFERROR(EXACT(P57,'_key'!$A$1968),FALSE),"✓","✗")) -> 0 | AB57: =IF(ISBLANK(Q57),"",IF(IFERROR(ABS(Q57-'_key'!$A$1969)<=0.01,FALSE),"✓","✗")) -> 0
A58: ACC-0142 | B58: HORIZON SYSTEMS | C58: Mid Market | D58: USD 45300 | E58: 07/07/2027 | F58: Emily.Carter@Empresa-Demo.Com | S58: =IF(ISBLANK(H58),"",IF(IFERROR(EXACT(H58,'_key'!$A$1970),FALSE),"✓","✗")) -> 0 | T58: =IF(ISBLANK(I58),"",IF(IFERROR(EXACT(I58,'_key'!$A$1971),FALSE),"✓","✗")) -> 0 | U58: =IF(ISBLANK(J58),"",IF(IFERROR(EXACT(J58,'_key'!$A$1972),FALSE),"✓","✗")) -> 0 | V58: =IF(ISBLANK(K58),"",IF(IFERROR(ABS(K58-'_key'!$A$1973)<=0.01,FALSE),"✓","✗")) -> 0 | W58: =IF(ISBLANK(L58),"",IF(IFERROR(ABS(L58-'_key'!$A$1974)<=0.01,FALSE),"✓","✗")) -> 0 | X58: =IF(ISBLANK(M58),"",IF(IFERROR(EXACT(M58,'_key'!$A$1975),FALSE),"✓","✗")) -> 0 | Y58: =IF(ISBLANK(N58),"",IF(IFERROR(EXACT(N58,'_key'!$A$1976),FALSE),"✓","✗")) -> 0 | Z58: =IF(ISBLANK(O58),"",IF(IFERROR(EXACT(O58,'_key'!$A$1977),FALSE),"✓","✗")) -> 0 | AA58: =IF(ISBLANK(P58),"",IF(IFERROR(ABS(P58-'_key'!$A$1978)<=0.01,FALSE),"✓","✗")) -> 0 | AB58: =IF(ISBLANK(Q58),"",IF(IFERROR(ABS(Q58-'_key'!$A$1979)<=0.01,FALSE),"✓","✗")) -> 0
A59: ACC-0067 | B59: meridian manufacturing | C59: enterprise | D59: 477,300 USD | E59: 2027-06-22 | F59: Ana.Lopez@Empresa-Demo.Com | S59: =IF(ISBLANK(H59),"",IF(IFERROR(EXACT(H59,'_key'!$A$1980),FALSE),"✓","✗")) -> 0 | T59: =IF(ISBLANK(I59),"",IF(IFERROR(EXACT(I59,'_key'!$A$1981),FALSE),"✓","✗")) -> 0 | U59: =IF(ISBLANK(J59),"",IF(IFERROR(EXACT(J59,'_key'!$A$1982),FALSE),"✓","✗")) -> 0 | V59: =IF(ISBLANK(K59),"",IF(IFERROR(ABS(K59-'_key'!$A$1983)<=0.01,FALSE),"✓","✗")) -> 0 | W59: =IF(ISBLANK(L59),"",IF(IFERROR(ABS(L59-'_key'!$A$1984)<=0.01,FALSE),"✓","✗")) -> 0 | X59: =IF(ISBLANK(M59),"",IF(IFERROR(EXACT(M59,'_key'!$A$1985),FALSE),"✓","✗")) -> 0 | Y59: =IF(ISBLANK(N59),"",IF(IFERROR(EXACT(N59,'_key'!$A$1986),FALSE),"✓","✗")) -> 0 | Z59: =IF(ISBLANK(O59),"",IF(IFERROR(EXACT(O59,'_key'!$A$1987),FALSE),"✓","✗")) -> 0 | AA59: =IF(ISBLANK(P59),"",IF(IFERROR(ABS(P59-'_key'!$A$1988)<=0.01,FALSE),"✓","✗")) -> 0 | AB59: =IF(ISBLANK(Q59),"",IF(IFERROR(ABS(Q59-'_key'!$A$1989)<=0.01,FALSE),"✓","✗")) -> 0
A60: ACC-0114 | B60: MONARCH BANK | C60: Ent | D60: USD 595800 | E60: 23/06/2027 | F60: carlos.mendez@empresa-demo.com | S60: =IF(ISBLANK(H60),"",IF(IFERROR(EXACT(H60,'_key'!$A$1990),FALSE),"✓","✗")) -> 0 | T60: =IF(ISBLANK(I60),"",IF(IFERROR(EXACT(I60,'_key'!$A$1991),FALSE),"✓","✗")) -> 0 | U60: =IF(ISBLANK(J60),"",IF(IFERROR(EXACT(J60,'_key'!$A$1992),FALSE),"✓","✗")) -> 0 | V60: =IF(ISBLANK(K60),"",IF(IFERROR(ABS(K60-'_key'!$A$1993)<=0.01,FALSE),"✓","✗")) -> 0 | W60: =IF(ISBLANK(L60),"",IF(IFERROR(ABS(L60-'_key'!$A$1994)<=0.01,FALSE),"✓","✗")) -> 0 | X60: =IF(ISBLANK(M60),"",IF(IFERROR(EXACT(M60,'_key'!$A$1995),FALSE),"✓","✗")) -> 0 | Y60: =IF(ISBLANK(N60),"",IF(IFERROR(EXACT(N60,'_key'!$A$1996),FALSE),"✓","✗")) -> 0 | Z60: =IF(ISBLANK(O60),"",IF(IFERROR(EXACT(O60,'_key'!$A$1997),FALSE),"✓","✗")) -> 0 | AA60: =IF(ISBLANK(P60),"",IF(IFERROR(ABS(P60-'_key'!$A$1998)<=0.01,FALSE),"✓","✗")) -> 0 | AB60: =IF(ISBLANK(Q60),"",IF(IFERROR(ABS(Q60-'_key'!$A$1999)<=0.01,FALSE),"✓","✗")) -> 0
A61: ACC-0095 | B61: Westfield Energy | C61: mid-market | D61: USD 131300 | E61: 2027-03-22 | F61: sofia.ramirez@empresa-demo.com | S61: =IF(ISBLANK(H61),"",IF(IFERROR(EXACT(H61,'_key'!$A$2000),FALSE),"✓","✗")) -> 0 | T61: =IF(ISBLANK(I61),"",IF(IFERROR(EXACT(I61,'_key'!$A$2001),FALSE),"✓","✗")) -> 0 | U61: =IF(ISBLANK(J61),"",IF(IFERROR(EXACT(J61,'_key'!$A$2002),FALSE),"✓","✗")) -> 0 | V61: =IF(ISBLANK(K61),"",IF(IFERROR(ABS(K61-'_key'!$A$2003)<=0.01,FALSE),"✓","✗")) -> 0 | W61: =IF(ISBLANK(L61),"",IF(IFERROR(ABS(L61-'_key'!$A$2004)<=0.01,FALSE),"✓","✗")) -> 0 | X61: =IF(ISBLANK(M61),"",IF(IFERROR(EXACT(M61,'_key'!$A$2005),FALSE),"✓","✗")) -> 0 | Y61: =IF(ISBLANK(N61),"",IF(IFERROR(EXACT(N61,'_key'!$A$2006),FALSE),"✓","✗")) -> 0 | Z61: =IF(ISBLANK(O61),"",IF(IFERROR(EXACT(O61,'_key'!$A$2007),FALSE),"✓","✗")) -> 0 | AA61: =IF(ISBLANK(P61),"",IF(IFERROR(ABS(P61-'_key'!$A$2008)<=0.01,FALSE),"✓","✗")) -> 0 | AB61: =IF(ISBLANK(Q61),"",IF(IFERROR(ABS(Q61-'_key'!$A$2009)<=0.01,FALSE),"✓","✗")) -> 0
A62: ACC-0098 | B62: BRIGHTPATH PHARMA | C62: Ent | D62: $186,000.00 | E62: 07/08/2027 | S62: =IF(ISBLANK(H62),"",IF(IFERROR(EXACT(H62,'_key'!$A$2010),FALSE),"✓","✗")) -> 0 | T62: =IF(ISBLANK(I62),"",IF(IFERROR(EXACT(I62,'_key'!$A$2011),FALSE),"✓","✗")) -> 0 | U62: =IF(ISBLANK(J62),"",IF(IFERROR(EXACT(J62,'_key'!$A$2012),FALSE),"✓","✗")) -> 0 | V62: =IF(ISBLANK(K62),"",IF(IFERROR(ABS(K62-'_key'!$A$2013)<=0.01,FALSE),"✓","✗")) -> 0 | W62: =IF(ISBLANK(L62),"",IF(IFERROR(ABS(L62-'_key'!$A$2014)<=0.01,FALSE),"✓","✗")) -> 0 | X62: =IF(ISBLANK(M62),"",IF(IFERROR(EXACT(M62,'_key'!$A$2015),FALSE),"✓","✗")) -> 0 | Y62: =IF(ISBLANK(N62),"",IF(IFERROR(EXACT(N62,'_key'!$A$2016),FALSE),"✓","✗")) -> 0 | Z62: =IF(ISBLANK(O62),"",IF(IFERROR(EXACT(O62,'_key'!$A$2017),FALSE),"✓","✗")) -> 0 | AA62: =IF(ISBLANK(P62),"",IF(IFERROR(ABS(P62-'_key'!$A$2018)<=0.01,FALSE),"✓","✗")) -> 0 | AB62: =IF(ISBLANK(Q62),"",IF(IFERROR(ABS(Q62-'_key'!$A$2019)<=0.01,FALSE),"✓","✗")) -> 0
A63: ACC-0117 | B63: Ironwood Retail | C63: SMB | D63: $21,200.00 | E63: 08/01/2027 | F63: james.walker@empresa-demo.com | S63: =IF(ISBLANK(H63),"",IF(IFERROR(EXACT(H63,'_key'!$A$2020),FALSE),"✓","✗")) -> 0 | T63: =IF(ISBLANK(I63),"",IF(IFERROR(EXACT(I63,'_key'!$A$2021),FALSE),"✓","✗")) -> 0 | U63: =IF(ISBLANK(J63),"",IF(IFERROR(EXACT(J63,'_key'!$A$2022),FALSE),"✓","✗")) -> 0 | V63: =IF(ISBLANK(K63),"",IF(IFERROR(ABS(K63-'_key'!$A$2023)<=0.01,FALSE),"✓","✗")) -> 0 | W63: =IF(ISBLANK(L63),"",IF(IFERROR(ABS(L63-'_key'!$A$2024)<=0.01,FALSE),"✓","✗")) -> 0 | X63: =IF(ISBLANK(M63),"",IF(IFERROR(EXACT(M63,'_key'!$A$2025),FALSE),"✓","✗")) -> 0 | Y63: =IF(ISBLANK(N63),"",IF(IFERROR(EXACT(N63,'_key'!$A$2026),FALSE),"✓","✗")) -> 0 | Z63: =IF(ISBLANK(O63),"",IF(IFERROR(EXACT(O63,'_key'!$A$2027),FALSE),"✓","✗")) -> 0 | AA63: =IF(ISBLANK(P63),"",IF(IFERROR(ABS(P63-'_key'!$A$2028)<=0.01,FALSE),"✓","✗")) -> 0 | AB63: =IF(ISBLANK(Q63),"",IF(IFERROR(ABS(Q63-'_key'!$A$2029)<=0.01,FALSE),"✓","✗")) -> 0
A64: ACC-0004 | B64: Sterling Financial | C64: smb | D64: $23,200 | E64: 07/11/2026 | F64: michael.brooks@empresa-demo.com | S64: =IF(ISBLANK(H64),"",IF(IFERROR(EXACT(H64,'_key'!$A$2030),FALSE),"✓","✗")) -> 0 | T64: =IF(ISBLANK(I64),"",IF(IFERROR(EXACT(I64,'_key'!$A$2031),FALSE),"✓","✗")) -> 0 | U64: =IF(ISBLANK(J64),"",IF(IFERROR(EXACT(J64,'_key'!$A$2032),FALSE),"✓","✗")) -> 0 | V64: =IF(ISBLANK(K64),"",IF(IFERROR(ABS(K64-'_key'!$A$2033)<=0.01,FALSE),"✓","✗")) -> 0 | W64: =IF(ISBLANK(L64),"",IF(IFERROR(ABS(L64-'_key'!$A$2034)<=0.01,FALSE),"✓","✗")) -> 0 | X64: =IF(ISBLANK(M64),"",IF(IFERROR(EXACT(M64,'_key'!$A$2035),FALSE),"✓","✗")) -> 0 | Y64: =IF(ISBLANK(N64),"",IF(IFERROR(EXACT(N64,'_key'!$A$2036),FALSE),"✓","✗")) -> 0 | Z64: =IF(ISBLANK(O64),"",IF(IFERROR(EXACT(O64,'_key'!$A$2037),FALSE),"✓","✗")) -> 0 | AA64: =IF(ISBLANK(P64),"",IF(IFERROR(ABS(P64-'_key'!$A$2038)<=0.01,FALSE),"✓","✗")) -> 0 | AB64: =IF(ISBLANK(Q64),"",IF(IFERROR(ABS(Q64-'_key'!$A$2039)<=0.01,FALSE),"✓","✗")) -> 0
A65: ACC-0104 | B65: LIBERTY RETAIL | C65: Mid Market | D65: $119,100 | E65: 2026-12-08 | F65: emily.carter@empresa-demo.com | S65: =IF(ISBLANK(H65),"",IF(IFERROR(EXACT(H65,'_key'!$A$2040),FALSE),"✓","✗")) -> 0 | T65: =IF(ISBLANK(I65),"",IF(IFERROR(EXACT(I65,'_key'!$A$2041),FALSE),"✓","✗")) -> 0 | U65: =IF(ISBLANK(J65),"",IF(IFERROR(EXACT(J65,'_key'!$A$2042),FALSE),"✓","✗")) -> 0 | V65: =IF(ISBLANK(K65),"",IF(IFERROR(ABS(K65-'_key'!$A$2043)<=0.01,FALSE),"✓","✗")) -> 0 | W65: =IF(ISBLANK(L65),"",IF(IFERROR(ABS(L65-'_key'!$A$2044)<=0.01,FALSE),"✓","✗")) -> 0 | X65: =IF(ISBLANK(M65),"",IF(IFERROR(EXACT(M65,'_key'!$A$2045),FALSE),"✓","✗")) -> 0 | Y65: =IF(ISBLANK(N65),"",IF(IFERROR(EXACT(N65,'_key'!$A$2046),FALSE),"✓","✗")) -> 0 | Z65: =IF(ISBLANK(O65),"",IF(IFERROR(EXACT(O65,'_key'!$A$2047),FALSE),"✓","✗")) -> 0 | AA65: =IF(ISBLANK(P65),"",IF(IFERROR(ABS(P65-'_key'!$A$2048)<=0.01,FALSE),"✓","✗")) -> 0 | AB65: =IF(ISBLANK(Q65),"",IF(IFERROR(ABS(Q65-'_key'!$A$2049)<=0.01,FALSE),"✓","✗")) -> 0

Sheet E6_Pivots
A1: E6 · Tablas dinámicas (Pivot Tables)
A2: Objetivo: crea cada tabla dinámica en una hoja nueva (Insertar > Tabla dinámica, origen = la tabla indicada) y copia aquí los resultados (a mano o con GETPIVOTDATA). Las ✓ te dicen si tu pivot está bien. En la versión de soluciones verás cómo obtener lo mismo con fórmulas.
A3: Tip: usa siempre una Tabla de Excel como origen (se expande sola), cambia 'Resumir valores por' y 'Mostrar valores como' (% del total), agrupa fechas por mes, agrega segmentaciones (slicers) y una escala de tiempo. Recuerda 'Actualizar' después de cambiar datos.
A5: P1 · Cuentas y ARR por Producto (solo activas)
A6: Origen: tbl_Accounts. Filtros: Status = Active. Filas: Product. Valores: Recuento de AccountID, Suma de ARR_USD y otra vez Suma de ARR_USD mostrada como '% del total general'. Extra: agrega un campo calculado ARR por licencia = ARR_USD / LicensedSeats y un slicer por Region.
A7: Product | B7: # Cuentas | C7: ARR | D7: % del ARR | K7: ✓B | L7: ✓C | M7: ✓D
A8: Legal Spend Mgmt | K8: =IF(ISBLANK(B8),"",IF(IFERROR(ABS(B8-'_key'!$A$2057)<=0.005,FALSE),"✓","✗")) -> 0 | L8: =IF(ISBLANK(C8),"",IF(IFERROR(ABS(C8-'_key'!$A$2058)<=0.005,FALSE),"✓","✗")) -> 0 | M8: =IF(ISBLANK(D8),"",IF(IFERROR(ABS(D8-'_key'!$A$2059)<=0.0005,FALSE),"✓","✗")) -> 0
A9: Matter Management | K9: =IF(ISBLANK(B9),"",IF(IFERROR(ABS(B9-'_key'!$A$2060)<=0.005,FALSE),"✓","✗")) -> 0 | L9: =IF(ISBLANK(C9),"",IF(IFERROR(ABS(C9-'_key'!$A$2061)<=0.005,FALSE),"✓","✗")) -> 0 | M9: =IF(ISBLANK(D9),"",IF(IFERROR(ABS(D9-'_key'!$A$2062)<=0.0005,FALSE),"✓","✗")) -> 0
A10: Contract Lifecycle | K10: =IF(ISBLANK(B10),"",IF(IFERROR(ABS(B10-'_key'!$A$2063)<=0.005,FALSE),"✓","✗")) -> 0 | L10: =IF(ISBLANK(C10),"",IF(IFERROR(ABS(C10-'_key'!$A$2064)<=0.005,FALSE),"✓","✗")) -> 0 | M10: =IF(ISBLANK(D10),"",IF(IFERROR(ABS(D10-'_key'!$A$2065)<=0.0005,FALSE),"✓","✗")) -> 0
A11: GRC / Risk | K11: =IF(ISBLANK(B11),"",IF(IFERROR(ABS(B11-'_key'!$A$2066)<=0.005,FALSE),"✓","✗")) -> 0 | L11: =IF(ISBLANK(C11),"",IF(IFERROR(ABS(C11-'_key'!$A$2067)<=0.005,FALSE),"✓","✗")) -> 0 | M11: =IF(ISBLANK(D11),"",IF(IFERROR(ABS(D11-'_key'!$A$2068)<=0.0005,FALSE),"✓","✗")) -> 0
A12: HR Compliance | K12: =IF(ISBLANK(B12),"",IF(IFERROR(ABS(B12-'_key'!$A$2069)<=0.005,FALSE),"✓","✗")) -> 0 | L12: =IF(ISBLANK(C12),"",IF(IFERROR(ABS(C12-'_key'!$A$2070)<=0.005,FALSE),"✓","✗")) -> 0 | M12: =IF(ISBLANK(D12),"",IF(IFERROR(ABS(D12-'_key'!$A$2071)<=0.0005,FALSE),"✓","✗")) -> 0
A13: Workflow Automation | K13: =IF(ISBLANK(B13),"",IF(IFERROR(ABS(B13-'_key'!$A$2072)<=0.005,FALSE),"✓","✗")) -> 0 | L13: =IF(ISBLANK(C13),"",IF(IFERROR(ABS(C13-'_key'!$A$2073)<=0.005,FALSE),"✓","✗")) -> 0 | M13: =IF(ISBLANK(D13),"",IF(IFERROR(ABS(D13-'_key'!$A$2074)<=0.0005,FALSE),"✓","✗")) -> 0
A15: P2 · Usuarios activos por Mes y Segmento
A16: Origen: tbl_Usage. Primero agrega a tbl_Usage una columna Segment con XLOOKUP hacia tbl_Accounts (o usa el Modelo de datos con una relación por AccountID). Filas: Month (agrupado por meses/años). Columnas: Segment. Valores: Suma de ActiveUsers. Extra: inserta un gráfico dinámico de líneas.
A17: Month | B17: Enterprise | C17: Mid-Market | D17: SMB | K17: ✓B | L17: ✓C | M17: ✓D
A18: 45931 | K18: =IF(ISBLANK(B18),"",IF(IFERROR(ABS(B18-'_key'!$A$2075)<=0.005,FALSE),"✓","✗")) -> 0 | L18: =IF(ISBLANK(C18),"",IF(IFERROR(ABS(C18-'_key'!$A$2076)<=0.005,FALSE),"✓","✗")) -> 0 | M18: =IF(ISBLANK(D18),"",IF(IFERROR(ABS(D18-'_key'!$A$2077)<=0.005,FALSE),"✓","✗")) -> 0
A19: 45962 | K19: =IF(ISBLANK(B19),"",IF(IFERROR(ABS(B19-'_key'!$A$2078)<=0.005,FALSE),"✓","✗")) -> 0 | L19: =IF(ISBLANK(C19),"",IF(IFERROR(ABS(C19-'_key'!$A$2079)<=0.005,FALSE),"✓","✗")) -> 0 | M19: =IF(ISBLANK(D19),"",IF(IFERROR(ABS(D19-'_key'!$A$2080)<=0.005,FALSE),"✓","✗")) -> 0
A20: 45992 | K20: =IF(ISBLANK(B20),"",IF(IFERROR(ABS(B20-'_key'!$A$2081)<=0.005,FALSE),"✓","✗")) -> 0 | L20: =IF(ISBLANK(C20),"",IF(IFERROR(ABS(C20-'_key'!$A$2082)<=0.005,FALSE),"✓","✗")) -> 0 | M20: =IF(ISBLANK(D20),"",IF(IFERROR(ABS(D20-'_key'!$A$2083)<=0.005,FALSE),"✓","✗")) -> 0
A21: 46023 | K21: =IF(ISBLANK(B21),"",IF(IFERROR(ABS(B21-'_key'!$A$2084)<=0.005,FALSE),"✓","✗")) -> 0 | L21: =IF(ISBLANK(C21),"",IF(IFERROR(ABS(C21-'_key'!$A$2085)<=0.005,FALSE),"✓","✗")) -> 0 | M21: =IF(ISBLANK(D21),"",IF(IFERROR(ABS(D21-'_key'!$A$2086)<=0.005,FALSE),"✓","✗")) -> 0
A22: 46054 | K22: =IF(ISBLANK(B22),"",IF(IFERROR(ABS(B22-'_key'!$A$2087)<=0.005,FALSE),"✓","✗")) -> 0 | L22: =IF(ISBLANK(C22),"",IF(IFERROR(ABS(C22-'_key'!$A$2088)<=0.005,FALSE),"✓","✗")) -> 0 | M22: =IF(ISBLANK(D22),"",IF(IFERROR(ABS(D22-'_key'!$A$2089)<=0.005,FALSE),"✓","✗")) -> 0
A23: 46082 | K23: =IF(ISBLANK(B23),"",IF(IFERROR(ABS(B23-'_key'!$A$2090)<=0.005,FALSE),"✓","✗")) -> 0 | L23: =IF(ISBLANK(C23),"",IF(IFERROR(ABS(C23-'_key'!$A$2091)<=0.005,FALSE),"✓","✗")) -> 0 | M23: =IF(ISBLANK(D23),"",IF(IFERROR(ABS(D23-'_key'!$A$2092)<=0.005,FALSE),"✓","✗")) -> 0
A24: 46113 | K24: =IF(ISBLANK(B24),"",IF(IFERROR(ABS(B24-'_key'!$A$2093)<=0.005,FALSE),"✓","✗")) -> 0 | L24: =IF(ISBLANK(C24),"",IF(IFERROR(ABS(C24-'_key'!$A$2094)<=0.005,FALSE),"✓","✗")) -> 0 | M24: =IF(ISBLANK(D24),"",IF(IFERROR(ABS(D24-'_key'!$A$2095)<=0.005,FALSE),"✓","✗")) -> 0
A25: 46143 | K25: =IF(ISBLANK(B25),"",IF(IFERROR(ABS(B25-'_key'!$A$2096)<=0.005,FALSE),"✓","✗")) -> 0 | L25: =IF(ISBLANK(C25),"",IF(IFERROR(ABS(C25-'_key'!$A$2097)<=0.005,FALSE),"✓","✗")) -> 0 | M25: =IF(ISBLANK(D25),"",IF(IFERROR(ABS(D25-'_key'!$A$2098)<=0.005,FALSE),"✓","✗")) -> 0
A26: 46174 | K26: =IF(ISBLANK(B26),"",IF(IFERROR(ABS(B26-'_key'!$A$2099)<=0.005,FALSE),"✓","✗")) -> 0 | L26: =IF(ISBLANK(C26),"",IF(IFERROR(ABS(C26-'_key'!$A$2100)<=0.005,FALSE),"✓","✗")) -> 0 | M26: =IF(ISBLANK(D26),"",IF(IFERROR(ABS(D26-'_key'!$A$2101)<=0.005,FALSE),"✓","✗")) -> 0
A27: 46204 | K27: =IF(ISBLANK(B27),"",IF(IFERROR(ABS(B27-'_key'!$A$2102)<=0.005,FALSE),"✓","✗")) -> 0 | L27: =IF(ISBLANK(C27),"",IF(IFERROR(ABS(C27-'_key'!$A$2103)<=0.005,FALSE),"✓","✗")) -> 0 | M27: =IF(ISBLANK(D27),"",IF(IFERROR(ABS(D27-'_key'!$A$2104)<=0.005,FALSE),"✓","✗")) -> 0
A28: 46235 | K28: =IF(ISBLANK(B28),"",IF(IFERROR(ABS(B28-'_key'!$A$2105)<=0.005,FALSE),"✓","✗")) -> 0 | L28: =IF(ISBLANK(C28),"",IF(IFERROR(ABS(C28-'_key'!$A$2106)<=0.005,FALSE),"✓","✗")) -> 0 | M28: =IF(ISBLANK(D28),"",IF(IFERROR(ABS(D28-'_key'!$A$2107)<=0.005,FALSE),"✓","✗")) -> 0
A29: 46266 | K29: =IF(ISBLANK(B29),"",IF(IFERROR(ABS(B29-'_key'!$A$2108)<=0.005,FALSE),"✓","✗")) -> 0 | L29: =IF(ISBLANK(C29),"",IF(IFERROR(ABS(C29-'_key'!$A$2109)<=0.005,FALSE),"✓","✗")) -> 0 | M29: =IF(ISBLANK(D29),"",IF(IFERROR(ABS(D29-'_key'!$A$2110)<=0.005,FALSE),"✓","✗")) -> 0
A31: P3 · Tickets por Categoría y Prioridad + CSAT
A32: Origen: tbl_Tickets. Filas: Category. Columnas: Priority. Valores: Recuento de TicketID. Agrega también Promedio de CSAT (Resumir valores por > Promedio) en una columna aparte. Extra: aplica formato condicional de escala de color a la matriz.
A33: Category | B33: P1 | C33: P2 | D33: P3 | E33: P4 | F33: CSAT promedio | K33: ✓B | L33: ✓C | M33: ✓D | N33: ✓E | O33: ✓F
A34: Bug | K34: =IF(ISBLANK(B34),"",IF(IFERROR(ABS(B34-'_key'!$A$2111)<=0.005,FALSE),"✓","✗")) -> 0 | L34: =IF(ISBLANK(C34),"",IF(IFERROR(ABS(C34-'_key'!$A$2112)<=0.005,FALSE),"✓","✗")) -> 0 | M34: =IF(ISBLANK(D34),"",IF(IFERROR(ABS(D34-'_key'!$A$2113)<=0.005,FALSE),"✓","✗")) -> 0 | N34: =IF(ISBLANK(E34),"",IF(IFERROR(ABS(E34-'_key'!$A$2114)<=0.005,FALSE),"✓","✗")) -> 0 | O34: =IF(ISBLANK(F34),"",IF(IFERROR(ABS(F34-'_key'!$A$2115)<=0.005,FALSE),"✓","✗")) -> 0
A35: How-to | K35: =IF(ISBLANK(B35),"",IF(IFERROR(ABS(B35-'_key'!$A$2116)<=0.005,FALSE),"✓","✗")) -> 0 | L35: =IF(ISBLANK(C35),"",IF(IFERROR(ABS(C35-'_key'!$A$2117)<=0.005,FALSE),"✓","✗")) -> 0 | M35: =IF(ISBLANK(D35),"",IF(IFERROR(ABS(D35-'_key'!$A$2118)<=0.005,FALSE),"✓","✗")) -> 0 | N35: =IF(ISBLANK(E35),"",IF(IFERROR(ABS(E35-'_key'!$A$2119)<=0.005,FALSE),"✓","✗")) -> 0 | O35: =IF(ISBLANK(F35),"",IF(IFERROR(ABS(F35-'_key'!$A$2120)<=0.005,FALSE),"✓","✗")) -> 0
A36: Integration | K36: =IF(ISBLANK(B36),"",IF(IFERROR(ABS(B36-'_key'!$A$2121)<=0.005,FALSE),"✓","✗")) -> 0 | L36: =IF(ISBLANK(C36),"",IF(IFERROR(ABS(C36-'_key'!$A$2122)<=0.005,FALSE),"✓","✗")) -> 0 | M36: =IF(ISBLANK(D36),"",IF(IFERROR(ABS(D36-'_key'!$A$2123)<=0.005,FALSE),"✓","✗")) -> 0 | N36: =IF(ISBLANK(E36),"",IF(IFERROR(ABS(E36-'_key'!$A$2124)<=0.005,FALSE),"✓","✗")) -> 0 | O36: =IF(ISBLANK(F36),"",IF(IFERROR(ABS(F36-'_key'!$A$2125)<=0.005,FALSE),"✓","✗")) -> 0
A37: Performance | K37: =IF(ISBLANK(B37),"",IF(IFERROR(ABS(B37-'_key'!$A$2126)<=0.005,FALSE),"✓","✗")) -> 0 | L37: =IF(ISBLANK(C37),"",IF(IFERROR(ABS(C37-'_key'!$A$2127)<=0.005,FALSE),"✓","✗")) -> 0 | M37: =IF(ISBLANK(D37),"",IF(IFERROR(ABS(D37-'_key'!$A$2128)<=0.005,FALSE),"✓","✗")) -> 0 | N37: =IF(ISBLANK(E37),"",IF(IFERROR(ABS(E37-'_key'!$A$2129)<=0.005,FALSE),"✓","✗")) -> 0 | O37: =IF(ISBLANK(F37),"",IF(IFERROR(ABS(F37-'_key'!$A$2130)<=0.005,FALSE),"✓","✗")) -> 0
A38: Billing | K38: =IF(ISBLANK(B38),"",IF(IFERROR(ABS(B38-'_key'!$A$2131)<=0.005,FALSE),"✓","✗")) -> 0 | L38: =IF(ISBLANK(C38),"",IF(IFERROR(ABS(C38-'_key'!$A$2132)<=0.005,FALSE),"✓","✗")) -> 0 | M38: =IF(ISBLANK(D38),"",IF(IFERROR(ABS(D38-'_key'!$A$2133)<=0.005,FALSE),"✓","✗")) -> 0 | N38: =IF(ISBLANK(E38),"",IF(IFERROR(ABS(E38-'_key'!$A$2134)<=0.005,FALSE),"✓","✗")) -> 0 | O38: =IF(ISBLANK(F38),"",IF(IFERROR(ABS(F38-'_key'!$A$2135)<=0.005,FALSE),"✓","✗")) -> 0
A39: Feature Request | K39: =IF(ISBLANK(B39),"",IF(IFERROR(ABS(B39-'_key'!$A$2136)<=0.005,FALSE),"✓","✗")) -> 0 | L39: =IF(ISBLANK(C39),"",IF(IFERROR(ABS(C39-'_key'!$A$2137)<=0.005,FALSE),"✓","✗")) -> 0 | M39: =IF(ISBLANK(D39),"",IF(IFERROR(ABS(D39-'_key'!$A$2138)<=0.005,FALSE),"✓","✗")) -> 0 | N39: =IF(ISBLANK(E39),"",IF(IFERROR(ABS(E39-'_key'!$A$2139)<=0.005,FALSE),"✓","✗")) -> 0 | O39: =IF(ISBLANK(F39),"",IF(IFERROR(ABS(F39-'_key'!$A$2140)<=0.005,FALSE),"✓","✗")) -> 0
A40: Data/Reporting | K40: =IF(ISBLANK(B40),"",IF(IFERROR(ABS(B40-'_key'!$A$2141)<=0.005,FALSE),"✓","✗")) -> 0 | L40: =IF(ISBLANK(C40),"",IF(IFERROR(ABS(C40-'_key'!$A$2142)<=0.005,FALSE),"✓","✗")) -> 0 | M40: =IF(ISBLANK(D40),"",IF(IFERROR(ABS(D40-'_key'!$A$2143)<=0.005,FALSE),"✓","✗")) -> 0 | N40: =IF(ISBLANK(E40),"",IF(IFERROR(ABS(E40-'_key'!$A$2144)<=0.005,FALSE),"✓","✗")) -> 0 | O40: =IF(ISBLANK(F40),"",IF(IFERROR(ABS(F40-'_key'!$A$2145)<=0.005,FALSE),"✓","✗")) -> 0
A42: P4 · Top 5 reportes más vistos
A43: Origen: tbl_ReportLog. Filtro: Action = View. Filas: ReportID. Valores: Recuento de LogID. Ordena descendente y aplica Filtro de valor > Top 10 (cámbialo a 5). Extra: agrega ReportName con el Modelo de datos o con una columna XLOOKUP en el log.
A44: Posición | B44: ReportID | C44: Views | K44: ✓B | L44: ✓C
A45: 1 | K45: =IF(ISBLANK(B45),"",IF(IFERROR(COUNTIFS(tbl_ReportLog[ReportID],B45,tbl_ReportLog[Action],"View")='_key'!$A$2146,FALSE),"✓","✗")) -> 0 | L45: =IF(ISBLANK(C45),"",IF(IFERROR(ABS(C45-'_key'!$A$2147)<=0.005,FALSE),"✓","✗")) -> 0
A46: 2 | K46: =IF(ISBLANK(B46),"",IF(IFERROR(COUNTIFS(tbl_ReportLog[ReportID],B46,tbl_ReportLog[Action],"View")='_key'!$A$2148,FALSE),"✓","✗")) -> 0 | L46: =IF(ISBLANK(C46),"",IF(IFERROR(ABS(C46-'_key'!$A$2149)<=0.005,FALSE),"✓","✗")) -> 0
A47: 3 | K47: =IF(ISBLANK(B47),"",IF(IFERROR(COUNTIFS(tbl_ReportLog[ReportID],B47,tbl_ReportLog[Action],"View")='_key'!$A$2150,FALSE),"✓","✗")) -> 0 | L47: =IF(ISBLANK(C47),"",IF(IFERROR(ABS(C47-'_key'!$A$2151)<=0.005,FALSE),"✓","✗")) -> 0
A48: 4 | K48: =IF(ISBLANK(B48),"",IF(IFERROR(COUNTIFS(tbl_ReportLog[ReportID],B48,tbl_ReportLog[Action],"View")='_key'!$A$2152,FALSE),"✓","✗")) -> 0 | L48: =IF(ISBLANK(C48),"",IF(IFERROR(ABS(C48-'_key'!$A$2153)<=0.005,FALSE),"✓","✗")) -> 0
A49: 5 | K49: =IF(ISBLANK(B49),"",IF(IFERROR(COUNTIFS(tbl_ReportLog[ReportID],B49,tbl_ReportLog[Action],"View")='_key'!$A$2154,FALSE),"✓","✗")) -> 0 | L49: =IF(ISBLANK(C49),"",IF(IFERROR(ABS(C49-'_key'!$A$2155)<=0.005,FALSE),"✓","✗")) -> 0
A51: P5 · Views por rol de usuario
A52: Origen: tbl_ReportLog. Filtro: Action = View. Filas: UserRole. Valores: Recuento de LogID y el mismo campo como '% del total de columnas'. Extra: Columnas = Date agrupada por Mes para ver la tendencia; agrega una escala de tiempo (Timeline).
A53: UserRole | B53: Views | K53: ✓B
A54: CSM | K54: =IF(ISBLANK(B54),"",IF(IFERROR(ABS(B54-'_key'!$A$2156)<=0.005,FALSE),"✓","✗")) -> 0
A55: Account Manager | K55: =IF(ISBLANK(B55),"",IF(IFERROR(ABS(B55-'_key'!$A$2157)<=0.005,FALSE),"✓","✗")) -> 0
A56: CS Leadership | K56: =IF(ISBLANK(B56),"",IF(IFERROR(ABS(B56-'_key'!$A$2158)<=0.005,FALSE),"✓","✗")) -> 0
A57: Executive | K57: =IF(ISBLANK(B57),"",IF(IFERROR(ABS(B57-'_key'!$A$2159)<=0.005,FALSE),"✓","✗")) -> 0
A58: Support | K58: =IF(ISBLANK(B58),"",IF(IFERROR(ABS(B58-'_key'!$A$2160)<=0.005,FALSE),"✓","✗")) -> 0
A59: Product | K59: =IF(ISBLANK(B59),"",IF(IFERROR(ABS(B59-'_key'!$A$2161)<=0.005,FALSE),"✓","✗")) -> 0
A60: CS Ops | K60: =IF(ISBLANK(B60),"",IF(IFERROR(ABS(B60-'_key'!$A$2162)<=0.005,FALSE),"✓","✗")) -> 0
A61: Partner Mgmt | K61: =IF(ISBLANK(B61),"",IF(IFERROR(ABS(B61-'_key'!$A$2163)<=0.005,FALSE),"✓","✗")) -> 0
A63: P6 · NPS por Segmento
A64: Origen: tbl_NPS. Agrega 2 columnas a tbl_NPS: Segment (XLOOKUP a tbl_Accounts) y NPS_Category =IFS([@Score]>=9,"Promoter",[@Score]>=7,"Passive",TRUE,"Detractor"). Pivot: Filas Segment, Columnas NPS_Category, Valores Recuento de SurveyID. Luego calcula NPS = (P − D) / Total × 100 fuera del pivot (usa GETPIVOTDATA).
A65: Segment | B65: Promoter | C65: Passive | D65: Detractor | E65: NPS | K65: ✓B | L65: ✓C | M65: ✓D | N65: ✓E
A66: Enterprise | K66: =IF(ISBLANK(B66),"",IF(IFERROR(ABS(B66-'_key'!$A$2164)<=0.005,FALSE),"✓","✗")) -> 0 | L66: =IF(ISBLANK(C66),"",IF(IFERROR(ABS(C66-'_key'!$A$2165)<=0.005,FALSE),"✓","✗")) -> 0 | M66: =IF(ISBLANK(D66),"",IF(IFERROR(ABS(D66-'_key'!$A$2166)<=0.005,FALSE),"✓","✗")) -> 0 | N66: =IF(ISBLANK(E66),"",IF(IFERROR(ABS(E66-'_key'!$A$2167)<=0.05,FALSE),"✓","✗")) -> 0
A67: Mid-Market | K67: =IF(ISBLANK(B67),"",IF(IFERROR(ABS(B67-'_key'!$A$2168)<=0.005,FALSE),"✓","✗")) -> 0 | L67: =IF(ISBLANK(C67),"",IF(IFERROR(ABS(C67-'_key'!$A$2169)<=0.005,FALSE),"✓","✗")) -> 0 | M67: =IF(ISBLANK(D67),"",IF(IFERROR(ABS(D67-'_key'!$A$2170)<=0.005,FALSE),"✓","✗")) -> 0 | N67: =IF(ISBLANK(E67),"",IF(IFERROR(ABS(E67-'_key'!$A$2171)<=0.05,FALSE),"✓","✗")) -> 0
A68: SMB | K68: =IF(ISBLANK(B68),"",IF(IFERROR(ABS(B68-'_key'!$A$2172)<=0.005,FALSE),"✓","✗")) -> 0 | L68: =IF(ISBLANK(C68),"",IF(IFERROR(ABS(C68-'_key'!$A$2173)<=0.005,FALSE),"✓","✗")) -> 0 | M68: =IF(ISBLANK(D68),"",IF(IFERROR(ABS(D68-'_key'!$A$2174)<=0.005,FALSE),"✓","✗")) -> 0 | N68: =IF(ISBLANK(E68),"",IF(IFERROR(ABS(E68-'_key'!$A$2175)<=0.05,FALSE),"✓","✗")) -> 0
A70: GETPIVOTDATA: escribe '=' y haz clic en una celda del pivot; Excel genera algo como =GETPIVOTDATA("SurveyID", Pivot!$A$3, "Segment", "SMB", "NPS_Category", "Promoter"). Así tus cálculos no se rompen si el pivot cambia de tamaño.

Sheet E7_Dinamicas_365
A1: E7 · Funciones de matriz dinámica (Excel 365)
